Workbook
Name Años_préstamo: #REF!
Name Capital: #REF!
Name Datos: #REF!
Name Día_de_pago: DATE(YEAR(Inicio_prestamo),MONTH(Inicio_prestamo)+Payment_Number,DAY(Inicio_prestamo))
Name Fecha_de_pago: #REF!
Name Fila_de_encabezado: ROW(#REF!)
Name Importe_del_préstamo: #REF!
Name Impresión_completa: #REF!
Name Inicio_prestamo: #REF!
Name Int: #REF!
Name Int_acum: #REF!
Name Interés_total: #REF!
Name Núm_de_pago: #REF!
Name Núm_pagos_al_año: #REF!
Name Número_de_pagos: MATCH(0.01,Saldo_final,-1)+1
Name Pago_adicional: #REF!
Name Pago_mensual_programado: #REF!
Name Pago_progr: #REF!
Name Pago_total: #REF!
Name Pagos_adicionales_programados: #REF!
Name Restablecer_área_de_impresión: OFFSET(Impresión_completa,0,0,Última_fila)
Name Saldo_final: #REF!
Name Saldo_inicial: #REF!
Name Tasa_de_interés: #REF!
Name Tasa_de_interés_programada: #REF!
Name Última_fila: IF(Valores_especificados,Fila_de_encabezado+Número_de_pagos,Fila_de_encabezado)
Name Valores_especificados: IF(Importe_del_préstamo*Tasa_de_interés*Años_préstamo*Inicio_prestamo>0,1,0)

Sheet CORTE 4200
B1: Primavera 2026 | N1: Venta | O1: =+SUM(O10,O19,O28,O37,O46,O55,O64,O73,O82,O91,O100,O109,O118,O127,O136,O145,O154,O163,O172,O181,O190,O199,O217,O226,O244,O253,O262,O271,O280,O298,O307,O316,O325,O334,O343,O352,O361,O370,O379,O388,O397,O406,O415,O424,O433,O442,O451,O460,O469,O487,O496,O505,O523,O532,O541,O550,O559,O568,O577,O586,O595,O604,O613,O622,O631,O640,O649,O658,O667,O676,O685,O694,O703,O712,O721,O730,O739,O748,O757,O766,O775,O802,O820,O829,O838,'4219 Ex 4166'!AA4,O811,O784,O478,O235,O289,O793,O208,O514) -> 21161 | Q1: Mayor | S1: 1.2 | T1: 2.1 | U1: 2.4 | V1: 2.1 | W1: 1.5 | X1: 0.9 | Y1: =SUM(S1:X1) -> 10.2
D2: 4200 | N2: Giro | Q2: Tienda K | S2: 3 | T2: 5 | U2: 5 | V2: 4 | W2: 1 | X2: 1 | Y2: =SUM(S2:X2) -> 19
Q3: Tienda F | S3: 1 | T3: 2 | U3: 3 | V3: 2 | W3: 2 | X3: 1 | Y3: =SUM(S3:X3) -> 11
A6: 4200
A8: Art. | B8: TELA | E8: Obsv
A9: 4201-00 | B9: Ibiza Blue | C9: Tiro | D9: Cintura | F9: Tallas | G9: 34 | H9: 36 | I9: 38 | J9: 40 | K9: 42 | L9: 44 | M9: 46 | O9: TOTAL | Q9: Tallas | S9: 36 | T9: 38 | U9: 40 | V9: 42 | W9: 44 | X9: 46 | Z9: TOTAL
A10: =+A9 -> 4201-00 | B10: Fecha | F10: Venta | H10: ='BASE DATOS'!C4 -> 72 | I10: ='BASE DATOS'!D4 -> 158 | J10: ='BASE DATOS'!E4 -> 165 | K10: ='BASE DATOS'!F4 -> 158 | L10: ='BASE DATOS'!G4 -> 108 | M10: ='BASE DATOS'!H4 -> 87 | O10: =SUM(H10:N10) -> 748 | Z10: =SUBTOTAL(9,S10:Y10) -> 0 | AD10: 1137
A11: =+A10 -> 4201-00 | B11: 45979 | C11: Bota | D11: Pitillo | E11: Giro | F11: 11507 | H11: =78-H20 -> 39 | I11: =118-I20 -> 59 | J11: =124-J20 -> 62 | K11: =118-K20 -> 59 | L11: =78-L20 -> 39 | M11: =46-M20 -> 23 | O11: =SUM(H11:N11) -> 281 | Q11: Corte Total | Z11: =SUM(S11:Y11) -> 0 | AD11: 1579
A12: =+A11 -> 4201-00 | B12: 46043 | E12: Giro | F12: 11550 | H12: =50-H29-H21 -> 24 | I12: =100-I29-I21 -> 50 | J12: =120-J29-J21 -> 62 | K12: =100-K29-K21 -> 46 | L12: =90-L29-L21 -> 50 | M12: =60-M29-M21 -> 29 | O12: =SUM(H12:N12) -> 261 | Q12: Tienda K | R12: =78/19 -> 4.1052632 | Z12: =SUM(S12:Y12) -> 0 | AD12: =+AD11-AD10 -> 442
A13: =+A12 -> 4201-00 | B13: 46055 | D13: Bio Focalizado | E13: Giro | F13: 11553 | H13: 55 | I13: 110 | J13: 129 | K13: 110 | L13: 55 | M13: 38 | O13: =SUM(H13:N13) -> 497 | Q13: Tienda F | R13: =25/11 -> 2.2727273 | Z13: =SUM(S13:Y13) -> 0
A14: =+A13 -> 4201-00 | E14: Giro | O14: =SUM(H14:N14) -> 0 | Z14: =SUM(S14:Y14) -> 0
A15: =+A14 -> 4201-00 | E15: Giro | O15: =SUM(H15:N15) -> 0 | Q15: Mayor | R15: =500/10.2 -> 49.019608 | S15: =49*1.2 -> 58.8 | T15: =49*2.1 -> 102.9 | U15: =49*2.4 -> 117.6 | V15: =49*2.4 -> 117.6 | W15: =49*1.5 -> 73.5 | X15: =49*0.9 -> 44.1 | Z15: =SUM(S15:Y15) -> 514.5
A16: =+A15 -> 4201-00 | E16: Saldo | F16: =+B9 -> Ibiza Blue | H16: =+H10-H11-H12-H13-H15+H14 -> -46 | I16: =+I10-I11-I12-I13-I15+I14 -> -61 | J16: =+J10-J11-J12-J13-J15-J14 -> -88 | K16: =+K10-K11-K12-K13-K15-K14 -> -57 | L16: =+L10-L11-L12-L13-L15-L14 -> -36 | M16: =+M10-M11-M12-M13-M15-M14 -> -3 | O16: =SUM(H16:N16) -> -291 | S16: =SUM(S12:S15) -> 58.8 | T16: =SUM(T12:T15) -> 102.9 | U16: =SUM(U12:U15) -> 117.6 | V16: =SUM(V12:V15) -> 117.6 | W16: =SUM(W12:W15) -> 73.5 | X16: =SUM(X12:X15) -> 44.1 | Z16: =SUM(S16:Y16) -> 514.5
A17: Art. | B17: TELA | E17: Obsv
A18: 4201-01 | B18: Ibiza Blue | C18: Tiro | D18: Cintura | F18: Tallas | G18: 34 | H18: 36 | I18: 38 | J18: 40 | K18: 42 | L18: 44 | M18: 46 | O18: TOTAL | Q18: Tallas | S18: 36 | T18: 38 | U18: 40 | V18: 42 | W18: 44 | X18: 46 | Z18: TOTAL
A19: =+A18 -> 4201-01 | B19: Fecha | F19: Venta | H19: ='BASE DATOS'!C5 -> 34 | I19: ='BASE DATOS'!D5 -> 53 | J19: ='BASE DATOS'!E5 -> 60 | K19: ='BASE DATOS'!F5 -> 57 | L19: ='BASE DATOS'!G5 -> 41 | M19: ='BASE DATOS'!H5 -> 26 | O19: =SUM(H19:N19) -> 271 | Z19: =SUBTOTAL(9,S19:Y19) -> 0
A20: =+A19 -> 4201-01 | B20: 45979 | C20: Bota | D20: Pitillo | E20: Giro | F20: 11507 | H20: 39 | I20: 59 | J20: 62 | K20: 59 | L20: 39 | M20: 23 | O20: =SUM(H20:N20) -> 281 | Q20: Corte Total | Z20: =SUM(S20:Y20) -> 0
A21: =+A20 -> 4201-01 | E21: Giro | F21: 11550 | H21: 2 | I21: 8 | J21: 12 | K21: 10 | L21: 7 | M21: 8 | O21: =SUM(H21:N21) -> 47 | Q21: Tienda K | R21: =78/19 -> 4.1052632 | Z21: =SUM(S21:Y21) -> 0
A22: =+A21 -> 4201-01 | D22: Bio Focalizado Oxidado | E22: Giro | O22: =SUM(H22:N22) -> 0 | Q22: Tienda F | R22: =25/11 -> 2.2727273 | Z22: =SUM(S22:Y22) -> 0
A23: =+A22 -> 4201-01 | E23: Giro | O23: =SUM(H23:N23) -> 0 | Z23: =SUM(S23:Y23) -> 0
A24: =+A23 -> 4201-01 | E24: Giro | O24: =SUM(H24:N24) -> 0 | Q24: Mayor | R24: =500/10.2 -> 49.019608 | S24: =49*1.2 -> 58.8 | T24: =49*2.1 -> 102.9 | U24: =49*2.4 -> 117.6 | V24: =49*2.4 -> 117.6 | W24: =49*1.5 -> 73.5 | X24: =49*0.9 -> 44.1 | Z24: =SUM(S24:Y24) -> 514.5
A25: =+A24 -> 4201-01 | E25: Saldo | F25: =+B18 -> Ibiza Blue | H25: =+H19-H20-H21-H22-H24+H23 -> -7 | I25: =+I19-I20-I21-I22-I24+I23 -> -14 | J25: =+J19-J20-J21-J22-J24-J23 -> -14 | K25: =+K19-K20-K21-K22-K24-K23 -> -12 | L25: =+L19-L20-L21-L22-L24-L23 -> -5 | M25: =+M19-M20-M21-M22-M24-M23 -> -5 | O25: =SUM(H25:N25) -> -57 | S25: =SUM(S21:S24) -> 58.8 | T25: =SUM(T21:T24) -> 102.9 | U25: =SUM(U21:U24) -> 117.6 | V25: =SUM(V21:V24) -> 117.6 | W25: =SUM(W21:W24) -> 73.5 | X25: =SUM(X21:X24) -> 44.1 | Z25: =SUM(S25:Y25) -> 514.5
A26: Art. | B26: TELA | E26: Obsv
A27: 4201-60 | B27: Ibiza Blue | C27: Tiro | D27: Cintura | F27: Tallas | G27: 34 | H27: 36 | I27: 38 | J27: 40 | K27: 42 | L27: 44 | M27: 46 | O27: TOTAL | Q27: Tallas | S27: 36 | T27: 38 | U27: 40 | V27: 42 | W27: 44 | X27: 46 | Z27: TOTAL
A28: =+A27 -> 4201-60 | B28: Fecha | F28: Venta | H28: ='BASE DATOS'!C6 -> 21 | I28: ='BASE DATOS'!D6 -> 38 | J28: ='BASE DATOS'!E6 -> 42 | K28: ='BASE DATOS'!F6 -> 40 | L28: ='BASE DATOS'!G6 -> 31 | M28: ='BASE DATOS'!H6 -> 22 | O28: =SUM(H28:N28) -> 194 | Z28: =SUBTOTAL(9,S28:Y28) -> 0
A29: =+A28 -> 4201-60 | C29: Bota | D29: Pitillo | E29: Giro | F29: 11550 | H29: 24 | I29: 42 | J29: 46 | K29: 44 | L29: 33 | M29: 23 | O29: =SUM(H29:N29) -> 212 | Q29: Corte Total | Z29: =SUM(S29:Y29) -> 0
A30: =+A29 -> 4201-60 | E30: Giro | O30: =SUM(H30:N30) -> 0 | Q30: Tienda K | R30: =78/19 -> 4.1052632 | Z30: =SUM(S30:Y30) -> 0
A31: =+A30 -> 4201-60 | D31: Bio Focalizado | E31: Giro | O31: =SUM(H31:N31) -> 0 | Q31: Tienda F | R31: =25/11 -> 2.2727273 | Z31: =SUM(S31:Y31) -> 0
A32: =+A31 -> 4201-60 | D32: Tachas | E32: Giro | O32: =SUM(H32:N32) -> 0 | Z32: =SUM(S32:Y32) -> 0
A33: =+A32 -> 4201-60 | E33: Giro | O33: =SUM(H33:N33) -> 0 | Q33: Mayor | R33: =500/10.2 -> 49.019608 | S33: =49*1.2 -> 58.8 | T33: =49*2.1 -> 102.9 | U33: =49*2.4 -> 117.6 | V33: =49*2.4 -> 117.6 | W33: =49*1.5 -> 73.5 | X33: =49*0.9 -> 44.1 | Z33: =SUM(S33:Y33) -> 514.5
A34: =+A33 -> 4201-60 | E34: Saldo | F34: =+B27 -> Ibiza Blue | H34: =+H28-H29-H30-H31-H33+H32 -> -3 | I34: =+I28-I29-I30-I31-I33+I32 -> -4 | J34: =+J28-J29-J30-J31-J33-J32 -> -4 | K34: =+K28-K29-K30-K31-K33-K32 -> -4 | L34: =+L28-L29-L30-L31-L33-L32 -> -2 | M34: =+M28-M29-M30-M31-M33-M32 -> -1 | O34: =SUM(H34:N34) -> -18 | S34: =SUM(S30:S33) -> 58.8 | T34: =SUM(T30:T33) -> 102.9 | U34: =SUM(U30:U33) -> 117.6 | V34: =SUM(V30:V33) -> 117.6 | W34: =SUM(W30:W33) -> 73.5 | X34: =SUM(X30:X33) -> 44.1 | Z34: =SUM(S34:Y34) -> 514.5
A35: Art. | B35: TELA | E35: Obsv | AC35: Giro | AD35: 46085 | AE35: 36 | AF35: 38 | AG35: 40 | AH35: 42 | AI35: 44 | AJ35: 46 | AK35: Total
A36: 4202 | B36: Ibiza Blue | C36: Tiro | D36: Cintura | F36: Tallas | G36: 34 | H36: 36 | I36: 38 | J36: 40 | K36: 42 | L36: 44 | M36: 46 | O36: TOTAL | Q36: Tallas | S36: 36 | T36: 38 | U36: 40 | V36: 42 | W36: 44 | X36: 46 | Z36: TOTAL | AC36: O.Corte | AD36: 11566 | AF36: 68 | AG36: 88 | AH36: 78 | AI36: 54 | AJ36: 48 | AK36: =SUM(AE36:AJ36) -> 336
A37: =+A36 -> 4202 | B37: Fecha | D37: =+B36 -> Ibiza Blue | F37: Venta | H37: ='BASE DATOS'!C7 -> 85 | I37: ='BASE DATOS'!D7 -> 181 | J37: ='BASE DATOS'!E7 -> 196 | K37: ='BASE DATOS'!F7 -> 188 | L37: ='BASE DATOS'!G7 -> 127 | M37: ='BASE DATOS'!H7 -> 99 | O37: =SUM(H37:N37) -> 876 | Z37: =SUBTOTAL(9,S37:Y37) -> 0 | AC37: Artículo | AD37: 4202
A38: =+A37 -> 4202 | B38: 45986 | C38: Bota | D38: Recto | E38: Giro | F38: 11514 | H38: 78 | I38: 100 | J38: 100 | K38: 100 | L38: 78 | M38: 50 | O38: =SUM(H38:N38) -> 506 | Q38: Corte Total | Z38: =SUM(S38:Y38) -> 0 | AC38: Tela | AD38: Ibiza Blue
A39: =+A38 -> 4202 | B39: 46085 | D39: EX 4189 | E39: Giro | F39: 11566 | I39: 90 | J39: 90 | K39: 100 | L39: 65 | M39: 60 | O39: =SUM(H39:N39) -> 405 | Q39: Tienda K | R39: =78/19 -> 4.1052632 | Z39: =SUM(S39:Y39) -> 0 | AC39: Tiro | AD39: Cintura
A40: =+A39 -> 4202 | E40: Giro | Q40: Tienda F | R40: =25/11 -> 2.2727273 | Z40: =SUM(S40:Y40) -> 0 | AC40: Bota | AD40: Recto
A41: =+A40 -> 4202 | E41: Giro | O41: =SUM(H41:N41) -> 0 | Z41: =SUM(S41:Y41) -> 0
A42: =+A41 -> 4202 | E42: Giro | O42: =SUM(H42:N42) -> 0 | Q42: Mayor | R42: =500/10.2 -> 49.019608 | S42: =49*1.2 -> 58.8 | T42: =49*2.1 -> 102.9 | U42: =49*2.4 -> 117.6 | V42: =49*2.4 -> 117.6 | W42: =49*1.5 -> 73.5 | X42: =49*0.9 -> 44.1 | Z42: =SUM(S42:Y42) -> 514.5
A43: =+A42 -> 4202 | E43: Saldo | F43: =+B36 -> Ibiza Blue | H43: =+H37-H38-H39-H40-H42+H41 -> 7 | I43: =+I37-I38-I39-I40-I42+I41 -> -9 | J43: =+J37-J38-J39-J40-J42-J41 -> 6 | K43: =+K37-K38-K39-K40-K42-K41 -> -12 | L43: =+L37-L38-L39-L40-L42-L41 -> -16 | M43: =+M37-M38-M39-M40-M42-M41 -> -11 | O43: =SUM(H43:N43) -> -35 | S43: =SUM(S39:S42) -> 58.8 | T43: =SUM(T39:T42) -> 102.9 | U43: =SUM(U39:U42) -> 117.6 | V43: =SUM(V39:V42) -> 117.6 | W43: =SUM(W39:W42) -> 73.5 | X43: =SUM(X39:X42) -> 44.1 | Z43: =SUM(S43:Y43) -> 514.5
A44: Art. | B44: TELA | E44: Obsv | AC44: Giro | AD44: 46094 | AE44: 36 | AF44: 38 | AG44: 40 | AH44: 42 | AI44: 44 | AJ44: 46 | AK44: Total
A45: 4203-00 | B45: B2868-V3 | C45: Tiro | D45: Medio | F45: Tallas | G45: 34 | H45: 36 | I45: 38 | J45: 40 | K45: 42 | L45: 44 | M45: 46 | O45: TOTAL | Q45: Tallas | S45: 36 | T45: 38 | U45: 40 | V45: 42 | W45: 44 | X45: 46 | Z45: TOTAL | AC45: O.Corte | AD45: 11571 | AE45: 50 | AF45: 100 | AG45: 100 | AH45: 100 | AI45: 65 | AJ45: 50 | AK45: =SUM(AE45:AJ45) -> 465
A46: =+A45 -> 4203-00 | B46: Fecha | D46: =+B45 -> B2868-V3 | F46: Venta | H46: ='BASE DATOS'!C8 -> 4 | I46: ='BASE DATOS'!D8 -> 9 | J46: ='BASE DATOS'!E8 -> 9 | K46: ='BASE DATOS'!F8 -> 7 | L46: ='BASE DATOS'!G8 -> 2 | M46: ='BASE DATOS'!H8 -> 1 | O46: =SUM(H46:N46) -> 32 | Z46: =SUBTOTAL(9,S46:Y46) -> 0 | AC46: Artículo | AD46: 4203
A47: =+A46 -> 4203-00 | B47: 46094 | C47: Bota | D47: Tobillero | E47: Giro | F47: 11571 | H47: =50-H56 -> 4 | I47: =100-I56 -> 9 | J47: =100-J56 -> 9 | K47: =100-K56 -> 7 | L47: =66-L56 -> 3 | M47: =50-M56 -> 1 | O47: =SUM(H47:N47) -> 33 | Q47: Corte Total | Z47: =SUM(S47:Y47) -> 0 | AC47: Tela | AD47: B2868-V3
A48: =+A47 -> 4203-00 | E48: Giro | O48: =SUM(H48:N48) -> 0 | Q48: Tienda K | R48: =78/19 -> 4.1052632 | Z48: =SUM(S48:Y48) -> 0 | AC48: Tiro | AD48: Medio
A49: =+A48 -> 4203-00 | E49: Giro | O49: =SUM(H49:N49) -> 0 | Q49: Tienda F | R49: =25/11 -> 2.2727273 | Z49: =SUM(S49:Y49) -> 0 | AC49: Bota | AD49: Tobillero
A50: =+A49 -> 4203-00 | E50: Giro | O50: =SUM(H50:N50) -> 0 | Z50: =SUM(S50:Y50) -> 0
A51: =+A50 -> 4203-00 | E51: Giro | O51: =SUM(H51:N51) -> 0 | Q51: Mayor | R51: =500/10.2 -> 49.019608 | S51: =49*1.2 -> 58.8 | T51: =49*2.1 -> 102.9 | U51: =49*2.4 -> 117.6 | V51: =49*2.4 -> 117.6 | W51: =49*1.5 -> 73.5 | X51: =49*0.9 -> 44.1 | Z51: =SUM(S51:Y51) -> 514.5
A52: =+A51 -> 4203-00 | E52: Saldo | F52: =+B45 -> B2868-V3 | H52: =+H46-H47-H48-H49-H51+H50 -> 0 | I52: =+I46-I47-I48-I49-I51+I50 -> 0 | J52: =+J46-J47-J48-J49-J51-J50 -> 0 | K52: =+K46-K47-K48-K49-K51-K50 -> 0 | L52: =+L46-L47-L48-L49-L51-L50 -> -1 | M52: =+M46-M47-M48-M49-M51-M50 -> 0 | O52: =SUM(H52:N52) -> -1 | S52: =SUM(S48:S51) -> 58.8 | T52: =SUM(T48:T51) -> 102.9 | U52: =SUM(U48:U51) -> 117.6 | V52: =SUM(V48:V51) -> 117.6 | W52: =SUM(W48:W51) -> 73.5 | X52: =SUM(X48:X51) -> 44.1 | Z52: =SUM(S52:Y52) -> 514.5
A53: Art. | B53: TELA | E53: Obsv
A54: 4203-01 | B54: B2868-V3 | C54: Tiro | D54: Medio | F54: Tallas | G54: 34 | H54: 36 | I54: 38 | J54: 40 | K54: 42 | L54: 44 | M54: 46 | O54: TOTAL | Q54: Tallas | S54: 36 | T54: 38 | U54: 40 | V54: 42 | W54: 44 | X54: 46 | Z54: TOTAL
A55: =+A54 -> 4203-01 | B55: Fecha | D55: =+B54 -> B2868-V3 | F55: Venta | H55: 40 | I55: 70 | J55: 70 | K55: 70 | L55: 50 | M55: 45 | O55: =SUM(H55:N55) -> 345 | Z55: =SUBTOTAL(9,S55:Y55) -> 0
A56: =+A55 -> 4203-01 | B56: 46094 | C56: Bota | D56: Tobillero | E56: Giro | F56: 11571 | H56: 46 | I56: 91 | J56: 91 | K56: 93 | L56: 63 | M56: 49 | O56: =SUM(H56:N56) -> 433 | Q56: Corte Total | Z56: =SUM(S56:Y56) -> 0
A57: =+A56 -> 4203-01 | E57: Giro | O57: =SUM(H57:N57) -> 0 | Q57: Tienda K | R57: =78/19 -> 4.1052632 | Z57: =SUM(S57:Y57) -> 0
A58: =+A57 -> 4203-01 | E58: Giro | O58: =SUM(H58:N58) -> 0 | Q58: Tienda F | R58: =25/11 -> 2.2727273 | Z58: =SUM(S58:Y58) -> 0
A59: =+A58 -> 4203-01 | E59: Giro | O59: =SUM(H59:N59) -> 0 | Z59: =SUM(S59:Y59) -> 0
A60: =+A59 -> 4203-01 | E60: Giro | O60: =SUM(H60:N60) -> 0 | Q60: Mayor | R60: =500/10.2 -> 49.019608 | S60: =49*1.2 -> 58.8 | T60: =49*2.1 -> 102.9 | U60: =49*2.4 -> 117.6 | V60: =49*2.4 -> 117.6 | W60: =49*1.5 -> 73.5 | X60: =49*0.9 -> 44.1 | Z60: =SUM(S60:Y60) -> 514.5
A61: =+A60 -> 4203-01 | E61: Saldo | F61: =+B54 -> B2868-V3 | H61: =+H55-H56-H57-H58-H60+H59 -> -6 | I61: =+I55-I56-I57-I58-I60+I59 -> -21 | J61: =+J55-J56-J57-J58-J60-J59 -> -21 | K61: =+K55-K56-K57-K58-K60-K59 -> -23 | L61: =+L55-L56-L57-L58-L60-L59 -> -13 | M61: =+M55-M56-M57-M58-M60-M59 -> -4 | O61: =SUM(H61:N61) -> -88 | S61: =SUM(S57:S60) -> 58.8 | T61: =SUM(T57:T60) -> 102.9 | U61: =SUM(U57:U60) -> 117.6 | V61: =SUM(V57:V60) -> 117.6 | W61: =SUM(W57:W60) -> 73.5 | X61: =SUM(X57:X60) -> 44.1 | Z61: =SUM(S61:Y61) -> 514.5 | AD61: Dimarsa Marzo Urgente
A62: Art. | B62: TELA | E62: Obsv | AC62: Giro | AD62: 46085 | AE62: 36 | AF62: 38 | AG62: 40 | AH62: 42 | AI62: 44 | AJ62: 46 | AK62: Total
A63: 4204-00 | B63: B2868-V3 | C63: Tiro | D63: Medio | F63: Tallas | G63: 34 | H63: 36 | I63: 38 | J63: 40 | K63: 42 | L63: 44 | M63: 46 | O63: TOTAL | Q63: Tallas | S63: 36 | T63: 38 | U63: 40 | V63: 42 | W63: 44 | X63: 46 | Z63: TOTAL | AC63: O.Corte | AD63: 11567 | AE63: 10 | AF63: 72 | AG63: 90 | AH63: 72 | AI63: 46 | AJ63: 44 | AK63: =SUM(AE63:AJ63) -> 334
A64: =+A63 -> 4204-00 | B64: Fecha | D64: =+B63 -> B2868-V3 | F64: Venta | H64: ='BASE DATOS'!C10 -> 39 | I64: ='BASE DATOS'!D10 -> 82 | J64: ='BASE DATOS'!E10 -> 90 | K64: ='BASE DATOS'!F10 -> 81 | L64: ='BASE DATOS'!G10 -> 54 | M64: ='BASE DATOS'!H10 -> 40 | O64: =SUM(H64:N64) -> 386 | Z64: =SUBTOTAL(9,S64:Y64) -> 0 | AC64: Artículo | AD64: 4204
A65: =+A64 -> 4204-00 | B65: 46006 | C65: Bota | D65: Flared | E65: Giro | F65: 11542 | H65: =78-H74-H83 -> 54 | I65: =100-I74-I83 -> 37 | J65: =100-J74-J83 -> 34 | K65: =100-K74-K83 -> 44 | L65: =78-L74-L83 -> 30 | M65: =50-M74-M83 -> 23 | O65: =SUM(H65:N65) -> 222 | Q65: Corte Total | Z65: =SUM(S65:Y65) -> 0 | AC65: Tela | AD65: B2868-V3
A66: =+A65 -> 4204-00 | B66: 46086 | D66: EX 4112 | E66: Giro | F66: 11567 | H66: =10-H84 -> 0 | I66: =72-I84 -> 46 | J66: =90-J84 -> 59 | K66: =72-K84 -> 38 | L66: =46-L84 -> 30 | M66: =44-M84 -> 18 | O66: =SUM(H66:N66) -> 191 | Q66: Tienda K | R66: =78/19 -> 4.1052632 | Z66: =SUM(S66:Y66) -> 0 | AC66: Tiro | AD66: Medio
A67: =+A66 -> 4204-00 | E67: Giro | O67: =SUM(H67:N67) -> 0 | Q67: Tienda F | R67: =25/11 -> 2.2727273 | Z67: =SUM(S67:Y67) -> 0 | AC67: Bota | AD67: Flare
A68: =+A67 -> 4204-00 | E68: Giro | O68: =SUM(H68:N68) -> 0 | Z68: =SUM(S68:Y68) -> 0
A69: =+A68 -> 4204-00 | E69: Giro | O69: =SUM(H69:N69) -> 0 | Q69: Mayor | R69: =500/10.2 -> 49.019608 | S69: =49*1.2 -> 58.8 | T69: =49*2.1 -> 102.9 | U69: =49*2.4 -> 117.6 | V69: =49*2.4 -> 117.6 | W69: =49*1.5 -> 73.5 | X69: =49*0.9 -> 44.1 | Z69: =SUM(S69:Y69) -> 514.5 | AC69: Disponible después del giro | AE69: -25 | AF69: -21 | AG69: -22 | AH69: -19 | AI69: -15 | AJ69: -10 | AK69: =SUM(AE69:AJ69) -> -112
A70: =+A69 -> 4204-00 | E70: Saldo | F70: =+B63 -> B2868-V3 | H70: =+H64-H65-H66-H67-H69+H68 -> -15 | I70: =+I64-I65-I66-I67-I69+I68 -> -1 | J70: =+J64-J65-J66-J67-J69-J68 -> -3 | K70: =+K64-K65-K66-K67-K69-K68 -> -1 | L70: =+L64-L65-L66-L67-L69-L68 -> -6 | M70: =+M64-M65-M66-M67-M69-M68 -> -1 | O70: =SUM(H70:N70) -> -27 | S70: =SUM(S66:S69) -> 58.8 | T70: =SUM(T66:T69) -> 102.9 | U70: =SUM(U66:U69) -> 117.6 | V70: =SUM(V66:V69) -> 117.6 | W70: =SUM(W66:W69) -> 73.5 | X70: =SUM(X66:X69) -> 44.1 | Z70: =SUM(S70:Y70) -> 514.5
A71: Art. | B71: TELA | E71: Obsv
A72: 4204-01 | B72: B2868-V3 | C72: Tiro | D72: Medio | F72: Tallas | G72: 34 | H72: 36 | I72: 38 | J72: 40 | K72: 42 | L72: 44 | M72: 46 | O72: TOTAL | Q72: Tallas | S72: 36 | T72: 38 | U72: 40 | V72: 42 | W72: 44 | X72: 46 | Z72: TOTAL
A73: =+A72 -> 4204-01 | B73: Fecha | D73: =+B72 -> B2868-V3 | F73: Venta | H73: ='BASE DATOS'!C11 -> 2 | I73: ='BASE DATOS'!D11 -> 6 | J73: ='BASE DATOS'!E11 -> 9 | K73: ='BASE DATOS'!F11 -> 8 | L73: ='BASE DATOS'!G11 -> 7 | M73: ='BASE DATOS'!H11 -> 5 | O73: =SUM(H73:N73) -> 37 | Z73: =SUBTOTAL(9,S73:Y73) -> 0
A74: =+A73 -> 4204-01 | C74: Bota | D74: Flared | E74: Giro | F74: 11542 | I74: 6 | J74: 9 | K74: 8 | L74: 7 | M74: 5 | O74: =SUM(H74:N74) -> 35 | Q74: Corte Total | Z74: =SUM(S74:Y74) -> 0
A75: =+A74 -> 4204-01 | D75: EX 4112 | E75: Giro | O75: =SUM(H75:N75) -> 0 | Q75: Tienda K | R75: =78/19 -> 4.1052632 | Z75: =SUM(S75:Y75) -> 0
A76: =+A75 -> 4204-01 | E76: Giro | O76: =SUM(H76:N76) -> 0 | Q76: Tienda F | R76: =25/11 -> 2.2727273 | Z76: =SUM(S76:Y76) -> 0
A77: =+A76 -> 4204-01 | E77: Giro | O77: =SUM(H77:N77) -> 0 | Z77: =SUM(S77:Y77) -> 0
A78: =+A77 -> 4204-01 | E78: Giro | O78: =SUM(H78:N78) -> 0 | Q78: Mayor | R78: =500/10.2 -> 49.019608 | S78: =49*1.2 -> 58.8 | T78: =49*2.1 -> 102.9 | U78: =49*2.4 -> 117.6 | V78: =49*2.4 -> 117.6 | W78: =49*1.5 -> 73.5 | X78: =49*0.9 -> 44.1 | Z78: =SUM(S78:Y78) -> 514.5
A79: =+A78 -> 4204-01 | E79: Saldo | F79: =+B72 -> B2868-V3 | H79: =+H73-H74-H75-H76-H78+H77 -> 2 | I79: =+I73-I74-I75-I76-I78+I77 -> 0 | J79: =+J73-J74-J75-J76-J78-J77 -> 0 | K79: =+K73-K74-K75-K76-K78-K77 -> 0 | L79: =+L73-L74-L75-L76-L78-L77 -> 0 | M79: =+M73-M74-M75-M76-M78-M77 -> 0 | O79: =SUM(H79:N79) -> 2 | S79: =SUM(S75:S78) -> 58.8 | T79: =SUM(T75:T78) -> 102.9 | U79: =SUM(U75:U78) -> 117.6 | V79: =SUM(V75:V78) -> 117.6 | W79: =SUM(W75:W78) -> 73.5 | X79: =SUM(X75:X78) -> 44.1 | Z79: =SUM(S79:Y79) -> 514.5
A80: Art. | B80: TELA | E80: Obsv
A81: 4204-02 | B81: B2868-V3 | C81: Tiro | D81: Medio | F81: Tallas | G81: 34 | H81: 36 | I81: 38 | J81: 40 | K81: 42 | L81: 44 | M81: 46 | O81: TOTAL | Q81: Tallas | S81: 36 | T81: 38 | U81: 40 | V81: 42 | W81: 44 | X81: 46 | Z81: TOTAL
A82: =+A81 -> 4204-02 | B82: Fecha | D82: =+B81 -> B2868-V3 | F82: Venta | H82: ='BASE DATOS'!C12 -> 31 | I82: ='BASE DATOS'!D12 -> 78 | J82: ='BASE DATOS'!E12 -> 83 | K82: ='BASE DATOS'!F12 -> 80 | L82: ='BASE DATOS'!G12 -> 56 | M82: ='BASE DATOS'!H12 -> 48 | O82: =SUM(H82:N82) -> 376 | Z82: =SUBTOTAL(9,S82:Y82) -> 0
A83: =+A82 -> 4204-02 | C83: Bota | D83: Flared | E83: Giro | F83: 11542 | H83: 24 | I83: 57 | J83: 57 | K83: 48 | L83: 41 | M83: 22 | O83: =SUM(H83:N83) -> 249 | Q83: Corte Total | Z83: =SUM(S83:Y83) -> 0
A84: =+A83 -> 4204-02 | B84: 46086 | D84: EX 4112 | E84: Giro | F84: 11567 | H84: 10 | I84: 26 | J84: 31 | K84: 34 | L84: 16 | M84: 26 | O84: =SUM(H84:N84) -> 143 | Q84: Tienda K | R84: =78/19 -> 4.1052632 | Z84: =SUM(S84:Y84) -> 0
A85: =+A84 -> 4204-02 | E85: Giro | O85: =SUM(H85:N85) -> 0 | Q85: Tienda F | R85: =25/11 -> 2.2727273 | Z85: =SUM(S85:Y85) -> 0
A86: =+A85 -> 4204-02 | E86: Giro | O86: =SUM(H86:N86) -> 0 | Z86: =SUM(S86:Y86) -> 0
A87: =+A86 -> 4204-02 | E87: Giro | O87: =SUM(H87:N87) -> 0 | Q87: Mayor | R87: =500/10.2 -> 49.019608 | S87: =49*1.2 -> 58.8 | T87: =49*2.1 -> 102.9 | U87: =49*2.4 -> 117.6 | V87: =49*2.4 -> 117.6 | W87: =49*1.5 -> 73.5 | X87: =49*0.9 -> 44.1 | Z87: =SUM(S87:Y87) -> 514.5
A88: =+A87 -> 4204-02 | E88: Saldo | F88: =+B81 -> B2868-V3 | H88: =+H82-H83-H84-H85-H87+H86 -> -3 | I88: =+I82-I83-I84-I85-I87+I86 -> -5 | J88: =+J82-J83-J84-J85-J87-J86 -> -5 | K88: =+K82-K83-K84-K85-K87-K86 -> -2 | L88: =+L82-L83-L84-L85-L87-L86 -> -1 | M88: =+M82-M83-M84-M85-M87-M86 -> 0 | O88: =SUM(H88:N88) -> -16 | S88: =SUM(S84:S87) -> 58.8 | T88: =SUM(T84:T87) -> 102.9 | U88: =SUM(U84:U87) -> 117.6 | V88: =SUM(V84:V87) -> 117.6 | W88: =SUM(W84:W87) -> 73.5 | X88: =SUM(X84:X87) -> 44.1 | Z88: =SUM(S88:Y88) -> 514.5
A89: Art. | B89: TELA | E89: Obsv | AC89: Giro | AD89: 46094 | AE89: 36 | AF89: 38 | AG89: 40 | AH89: 42 | AI89: 44 | AJ89: 46 | AK89: Total
A90: 4205-00 | B90: Ayla | C90: Tiro | D90: Cintura | F90: Tallas | G90: 34 | H90: 36 | I90: 38 | J90: 40 | K90: 42 | L90: 44 | M90: 46 | O90: TOTAL | Q90: Tallas | S90: 36 | T90: 38 | U90: 40 | V90: 42 | W90: 44 | X90: 46 | Z90: TOTAL | AC90: O.Corte | AD90: 11572 | AE90: 36 | AF90: 76 | AG90: 90 | AH90: 88 | AI90: 64 | AJ90: 46 | AK90: =SUM(AE90:AJ90) -> 400
A91: =+A90 -> 4205-00 | B91: Fecha | D91: =+B90 -> Ayla | F91: Venta | H91: ='BASE DATOS'!C13 -> 60 | I91: ='BASE DATOS'!D13 -> 119 | J91: ='BASE DATOS'!E13 -> 124 | K91: ='BASE DATOS'!F13 -> 121 | L91: ='BASE DATOS'!G13 -> 80 | M91: ='BASE DATOS'!H13 -> 66 | O91: =SUM(H91:N91) -> 570 | Z91: =SUBTOTAL(9,S91:Y91) -> 0 | AC91: Artículo | AD91: 4205
A92: =+A91 -> 4205-00 | B92: 46058 | C92: Bota | D92: Oxford | E92: Giro | F92: 11555 | H92: =77-H101-H110 -> 47 | I92: =157-I101-I110 -> 84 | J92: =160-J101-J110 -> 78 | K92: =157-K101-K110 -> 78 | L92: =110-L101-L110 -> 52 | M92: =94-M101-M110 -> 43 | O92: =SUM(H92:N92) -> 382 | Q92: Corte Total | Z92: =SUM(S92:Y92) -> 0 | AC92: Tela | AD92: Ayla
A93: =+A92 -> 4205-00 | B93: 46094 | E93: Giro | F93: 11572 | H93: =38-H102 -> 32 | I93: =76-I102 -> 66 | J93: =90-J102 -> 76 | K93: =88-K102 -> 73 | L93: =64-L102 -> 52 | M93: =46-M102 -> 37 | O93: =SUM(H93:N93) -> 336 | Q93: Tienda K | R93: =78/19 -> 4.1052632 | Z93: =SUM(S93:Y93) -> 0 | AC93: Tiro | AD93: Cintura
A94: =+A93 -> 4205-00 | E94: Giro | O94: =SUM(H94:N94) -> 0 | Q94: Tienda F | R94: =25/11 -> 2.2727273 | Z94: =SUM(S94:Y94) -> 0 | AC94: Bota | AD94: Oxford
A95: =+A94 -> 4205-00 | E95: Giro | O95: =SUM(H95:N95) -> 0 | Z95: =SUM(S95:Y95) -> 0
A96: =+A95 -> 4205-00 | E96: Giro | O96: =SUM(H96:N96) -> 0 | Q96: Mayor | R96: =500/10.2 -> 49.019608 | S96: =49*1.2 -> 58.8 | T96: =49*2.1 -> 102.9 | U96: =49*2.4 -> 117.6 | V96: =49*2.4 -> 117.6 | W96: =49*1.5 -> 73.5 | X96: =49*0.9 -> 44.1 | Z96: =SUM(S96:Y96) -> 514.5
A97: =+A96 -> 4205-00 | E97: Saldo | F97: =+B90 -> Ayla | H97: =+H91-H92-H93-H94-H96+H95 -> -19 | I97: =+I91-I92-I93-I94-I96+I95 -> -31 | J97: =+J91-J92-J93-J94-J96-J95 -> -30 | K97: =+K91-K92-K93-K94-K96-K95 -> -30 | L97: =+L91-L92-L93-L94-L96-L95 -> -24 | M97: =+M91-M92-M93-M94-M96-M95 -> -14 | O97: =SUM(H97:N97) -> -148 | S97: =SUM(S93:S96) -> 58.8 | T97: =SUM(T93:T96) -> 102.9 | U97: =SUM(U93:U96) -> 117.6 | V97: =SUM(V93:V96) -> 117.6 | W97: =SUM(W93:W96) -> 73.5 | X97: =SUM(X93:X96) -> 44.1 | Z97: =SUM(S97:Y97) -> 514.5
A98: Art. | B98: TELA | E98: Obsv
A99: 4205-01 | B99: Ayla | C99: Tiro | D99: Cintura | F99: Tallas | G99: 34 | H99: 36 | I99: 38 | J99: 40 | K99: 42 | L99: 44 | M99: 46 | O99: TOTAL | Q99: Tallas | S99: 36 | T99: 38 | U99: 40 | V99: 42 | W99: 44 | X99: 46 | Z99: TOTAL
A100: =+A99 -> 4205-01 | B100: Fecha | D100: =+B99 -> Ayla | F100: Venta | H100: ='BASE DATOS'!C14 -> 35 | I100: ='BASE DATOS'!D14 -> 78 | J100: ='BASE DATOS'!E14 -> 87 | K100: ='BASE DATOS'!F14 -> 85 | L100: ='BASE DATOS'!G14 -> 62 | M100: ='BASE DATOS'!H14 -> 54 | O100: =SUM(H100:N100) -> 401 | Z100: =SUBTOTAL(9,S100:Y100) -> 0
A101: =+A100 -> 4205-01 | B101: 46058 | C101: Bota | D101: Oxford | E101: Giro | F101: 11555 | H101: 30 | I101: 69 | J101: 74 | K101: 71 | L101: 51 | M101: 46 | O101: =SUM(H101:N101) -> 341 | Q101: Corte Total | Z101: =SUM(S101:Y101) -> 0
A102: =+A101 -> 4205-01 | B102: 46066 | E102: Giro | F102: 11572 | H102: 6 | I102: 10 | J102: 14 | K102: 15 | L102: 12 | M102: 9 | O102: =SUM(H102:N102) -> 66 | Q102: Tienda K | R102: =78/19 -> 4.1052632 | Z102: =SUM(S102:Y102) -> 0
A103: =+A102 -> 4205-01 | E103: Giro | O103: =SUM(H103:N103) -> 0 | Q103: Tienda F | R103: =25/11 -> 2.2727273 | Z103: =SUM(S103:Y103) -> 0
...

Sheet BASE DATOS
A1: Venta | B1: 4200 | D1: S | E1: M | F1: L | G1: XL | J1: =$J$98 -> 21166
A2: Artículo | C2: 36 | D2: 38 | E2: 40 | F2: 42 | G2: 44 | H2: 46 | J2: Total | K2: Girar o | L2: Compra | M2: Girar
A3: c | B3: c2 | C3: c3 | D3: c4 | E3: c5 | F3: c6 | G3: c7 | H3: c8 | I3: c9 | J3: c10 | K3: Disponible | L3: Kennedy | P3: 46105 | Q3: 13,01 hrs | AC3: 46098 | AD3: 12,00 hrs | AP3: 46093 | AQ3: 15,25 hrs | BC3: 46092 | BD3: 12,2 hrs | BP3: 46090 | BQ3: 10,21 hrs | CC3: 46079 | CD3: 12,01 hrs | CP3: 46072 | CQ3: 0.55555556 | DC3: 46071 | DD3: 0.5 | DP3: 46070 | DQ3: 0.71597222 | EC3: 46066 | ED3: 0.57986111 | EP3: 46065 | EQ3: 0.58888889 | FC3: 46062 | FD3: 12,39 hrs | FP3: 46062 | FQ3: 10 hrs | GC3: 46048 | GP3: 46045
A4: 1420100 | B4: Ibiza Blue | C4: 72 | D4: 158 | E4: 165 | F4: 158 | G4: 108 | H4: 87 | J4: =SUM(C4:H4) -> 748 | K4: ='CORTE 4200'!$O$16 -> -291 | L4: 50 | O4: 1420100 | P4: J MHC CINTURA P | Q4: Ventas | S4: 72 | T4: 158 | U4: 165 | V4: 158 | W4: 108 | X4: 87 | Y4: 0 | Z4: =SUM(S4:Y4) -> 748 | AB4: 1420100 | AC4: J MHC CINTURA P | AD4: Ventas | AF4: 74 | AG4: 157 | AH4: 168 | AI4: 156 | AJ4: 106 | AK4: 80 | AL4: 0 | AM4: =SUM(AF4:AL4) -> 741 | AN4: =+Tabla15[[#This Row],[c10]]-AM4 -> 7 | AO4: 1420100 | AP4: J MHC CINTURA P | AQ4: Ventas | AS4: 72 | AT4: 155 | AU4: 166 | AV4: 154 | AW4: 105 | AX4: 79 | AY4: 0 | AZ4: =SUM(AS4:AY4) -> 731 | BB4: 1420100 | BC4: J MHC CINTURA P | BD4: Ventas | BF4: 64 | BG4: 143 | BH4: 154 | BI4: 142 | BJ4: 102 | BK4: 76 | BL4: 0 | BM4: 681 | BO4: 1420100 | BP4: J MHC CINTURA P | BQ4: Ventas | BS4: 66 | BT4: 146 | BU4: 157 | BV4: 144 | BW4: 103 | BX4: 76 | BY4: 0 | BZ4: =SUM(BS4:BY4) -> 692 | CB4: 1420100 | CC4: J MHC CINTURA P | CD4: Ventas | CF4: 64 | CG4: 143 | CH4: 155 | CI4: 142 | CJ4: 101 | CK4: 75 | CL4: 0 | CM4: =SUM(CF4:CL4) -> 680 | CO4: 1420100 | CP4: J MHC CINTURA P | CQ4: Ventas | CS4: 60 | CT4: 137 | CU4: 149 | CV4: 137 | CW4: 98 | CX4: 74 | CY4: 0 | CZ4: 655 | DB4: 1420100 | DC4: J MHC CINTURA P | DD4: Ventas | DF4: 57 | DG4: 132 | DH4: 141 | DI4: 131 | DJ4: 93 | DK4: 70 | DL4: 0 | DM4: 624 | DO4: 1420100 | DP4: J MHC CINTURA P | DQ4: Ventas | DS4: 49 | DT4: 117 | DU4: 123 | DV4: 117 | DW4: 83 | DX4: 66 | DY4: 0 | DZ4: 555 | EB4: 1420100 | EC4: J MHC CINTURA P | ED4: Ventas | EF4: 45 | EG4: 107 | EH4: 115 | EI4: 111 | EJ4: 80 | EK4: 64 | EL4: 0 | EM4: 522 | EO4: 1420100 | EP4: J MHC CINTURA P | EQ4: Ventas | ES4: 42 | ET4: 102 | EU4: 110 | EV4: 106 | EW4: 77 | EX4: 62 | EY4: 0 | EZ4: 499 | FB4: 1420100 | FC4: J MHC CINTURA P | FD4: Ventas | FF4: 38 | FG4: 92 | FH4: 99 | FI4: 97 | FJ4: 70 | FK4: 60 | FL4: 0 | FM4: 456 | FO4: 1420100 | FP4: J MHC CINTURA P | FQ4: Ventas | FS4: 36 | FT4: 86 | FU4: 93 | FV4: 91 | FW4: 66 | FX4: 56 | FY4: 0 | FZ4: 428 | GB4: 1420100 | GC4: J MHC CINTURA P | GD4: Ventas | GF4: 19 | GG4: 32 | GH4: 38 | GI4: 36 | GJ4: 29 | GK4: 20 | GL4: 0 | GM4: 174 | GO4: 1420100 | GP4: J MHC CINTURA P | GQ4: Ventas | GS4: 18 | GT4: 29 | GU4: 34 | GV4: 33 | GW4: 27 | GX4: 19 | GY4: 0 | GZ4: =SUM(GS4:GY4) -> 160
A5: 1420101 | B5: Ibiza Blue | C5: 34 | D5: 53 | E5: 60 | F5: 57 | G5: 41 | H5: 26 | J5: =SUM(C5:H5) -> 271 | K5: ='CORTE 4200'!$O$25 -> -57 | O5: 1420101 | P5: J MHC CINTURA P | Q5: Ventas | S5: 34 | T5: 53 | U5: 60 | V5: 57 | W5: 41 | X5: 26 | Y5: 0 | Z5: =SUM(S5:Y5) -> 271 | AB5: 1420101 | AC5: J MHC CINTURA P | AD5: Ventas | AF5: 34 | AG5: 53 | AH5: 60 | AI5: 57 | AJ5: 41 | AK5: 26 | AL5: 0 | AM5: =SUM(AF5:AL5) -> 271 | AO5: 1420101 | AP5: J MHC CINTURA P | AQ5: Ventas | AS5: 34 | AT5: 53 | AU5: 60 | AV5: 57 | AW5: 41 | AX5: 26 | AY5: 0 | AZ5: =SUM(AS5:AY5) -> 271 | BB5: 1420101 | BC5: J MHC CINTURA P | BD5: Ventas | BF5: 33 | BG5: 50 | BH5: 57 | BI5: 55 | BJ5: 40 | BK5: 26 | BL5: 0 | BM5: 261 | BO5: 1420101 | BP5: J MHC CINTURA P | BQ5: Ventas | BS5: 33 | BT5: 50 | BU5: 57 | BV5: 55 | BW5: 40 | BX5: 26 | BY5: 0 | BZ5: =SUM(BS5:BY5) -> 261 | CB5: 1420101 | CC5: J MHC CINTURA P | CD5: Ventas | CF5: 33 | CG5: 50 | CH5: 57 | CI5: 55 | CJ5: 40 | CK5: 26 | CL5: 0 | CM5: =SUM(CF5:CL5) -> 261 | CO5: 1420101 | CP5: J MHC CINTURA P | CQ5: Ventas | CS5: 33 | CT5: 48 | CU5: 55 | CV5: 52 | CW5: 37 | CX5: 24 | CY5: 0 | CZ5: 249 | DB5: 1420101 | DC5: J MHC CINTURA P | DD5: Ventas | DF5: 33 | DG5: 48 | DH5: 55 | DI5: 52 | DJ5: 37 | DK5: 24 | DL5: 0 | DM5: 249 | DO5: 1420101 | DP5: J MHC CINTURA P | DQ5: Ventas | DS5: 30 | DT5: 44 | DU5: 51 | DV5: 49 | DW5: 35 | DX5: 24 | DY5: 0 | DZ5: 233 | EB5: 1420101 | EC5: J MHC CINTURA P | ED5: Ventas | EF5: 30 | EG5: 44 | EH5: 51 | EI5: 49 | EJ5: 35 | EK5: 24 | EL5: 0 | EM5: 233 | EO5: 1420101 | EP5: J MHC CINTURA P | EQ5: Ventas | ES5: 28 | ET5: 41 | EU5: 48 | EV5: 46 | EW5: 33 | EX5: 23 | EY5: 0 | EZ5: 219 | FB5: 1420101 | FC5: J MHC CINTURA P | FD5: Ventas | FF5: 26 | FG5: 36 | FH5: 43 | FI5: 41 | FJ5: 30 | FK5: 21 | FL5: 0 | FM5: 197 | FO5: 1420101 | FP5: J MHC CINTURA P | FQ5: Ventas | FS5: 26 | FT5: 36 | FU5: 43 | FV5: 41 | FW5: 30 | FX5: 21 | FY5: 0 | FZ5: 197 | GB5: 1420101 | GC5: J MHC CINTURA P | GD5: Ventas | GF5: 21 | GG5: 27 | GH5: 32 | GI5: 31 | GJ5: 24 | GK5: 18 | GL5: 0 | GM5: 153 | GO5: 1420101 | GP5: J MHC CINTURA P | GQ5: Ventas | GS5: 18 | GT5: 22 | GU5: 25 | GV5: 25 | GW5: 20 | GX5: 15 | GY5: 0 | GZ5: =SUM(GS5:GY5) -> 125
A6: 1420160 | B6: Ibiza Blue | C6: 21 | D6: 38 | E6: 42 | F6: 40 | G6: 31 | H6: 22 | J6: =SUM(C6:H6) -> 194 | K6: ='CORTE 4200'!$O$34 -> -18 | O6: 1420160 | P6: J MHC CINTURA P | Q6: Ventas | S6: 21 | T6: 38 | U6: 42 | V6: 40 | W6: 31 | X6: 22 | Y6: 0 | Z6: =SUM(S6:Y6) -> 194 | AB6: 1420160 | AC6: J MHC CINTURA P | AD6: Ventas | AF6: 21 | AG6: 38 | AH6: 42 | AI6: 40 | AJ6: 31 | AK6: 22 | AL6: 0 | AM6: =SUM(AF6:AL6) -> 194 | AO6: 1420160 | AP6: J MHC CINTURA P | AQ6: Ventas | AS6: 21 | AT6: 36 | AU6: 40 | AV6: 38 | AW6: 29 | AX6: 20 | AY6: 0 | AZ6: =SUM(AS6:AY6) -> 184 | BB6: 1420160 | BC6: J MHC CINTURA P | BD6: Ventas | BF6: 21 | BG6: 36 | BH6: 40 | BI6: 38 | BJ6: 29 | BK6: 20 | BL6: 0 | BM6: =SUM(BF6:BL6) -> 184 | BO6: 1420160 | BP6: J MHC CINTURA P | BQ6: Ventas | BS6: 21 | BT6: 36 | BU6: 40 | BV6: 38 | BW6: 29 | BX6: 20 | BY6: 0 | BZ6: =SUM(BS6:BY6) -> 184 | CB6: 1420160 | CC6: J MHC CINTURA P | CD6: Ventas | CF6: 19 | CG6: 33 | CH6: 37 | CI6: 36 | CJ6: 27 | CK6: 19 | CL6: 0 | CM6: =SUM(CF6:CL6) -> 171 | CO6: 1420160 | CP6: J MHC CINTURA P | CQ6: Ventas | CS6: 19 | CT6: 33 | CU6: 37 | CV6: 36 | CW6: 27 | CX6: 19 | CY6: 0 | CZ6: 171 | DB6: 1420160 | DC6: J MHC CINTURA P | DD6: Ventas | DF6: 19 | DG6: 33 | DH6: 37 | DI6: 36 | DJ6: 27 | DK6: 19 | DL6: 0 | DM6: 171 | DO6: 1420160 | DP6: J MHC CINTURA P | DQ6: Ventas | DS6: 19 | DT6: 32 | DU6: 36 | DV6: 35 | DW6: 27 | DX6: 19 | DY6: 0 | DZ6: 168 | EB6: 1420160 | EC6: J MHC CINTURA P | ED6: Ventas | EF6: 19 | EG6: 32 | EH6: 36 | EI6: 35 | EJ6: 27 | EK6: 19 | EL6: 0 | EM6: 168 | EO6: 1420160 | EP6: J MHC CINTURA P | EQ6: Ventas | ES6: 17 | ET6: 29 | EU6: 33 | EV6: 32 | EW6: 25 | EX6: 18 | EY6: 0 | EZ6: 154 | FB6: 1420160 | FC6: J MHC CINTURA P | FD6: Ventas | FF6: 13 | FG6: 22 | FH6: 26 | FI6: 25 | FJ6: 19 | FK6: 14 | FL6: 0 | FM6: 119 | FO6: 1420160 | FP6: J MHC CINTURA P | FQ6: Ventas | FS6: 13 | FT6: 22 | FU6: 26 | FV6: 25 | FW6: 19 | FX6: 14 | FY6: 0 | FZ6: 119 | GB6: 1420160 | GC6: J MHC CINTURA P | GD6: Ventas | GF6: 9 | GG6: 14 | GH6: 19 | GI6: 19 | GJ6: 15 | GK6: 11 | GL6: 0 | GM6: 87 | GO6: 1420160 | GP6: J MHC CINTURA P | GQ6: Ventas | GS6: 9 | GT6: 14 | GU6: 19 | GV6: 19 | GW6: 15 | GX6: 11 | GY6: 0 | GZ6: =SUM(GS6:GY6) -> 87
A7: 1420200 | B7: Ibiza Blue | C7: 85 | D7: 181 | E7: 196 | F7: 188 | G7: 127 | H7: 99 | J7: =SUM(C7:H7) -> 876 | K7: ='CORTE 4200'!$O$43 -> -35 | L7: 50 | O7: 1420200 | P7: J MHC CINTURA R | Q7: Ventas | S7: 85 | T7: 181 | U7: 196 | V7: 188 | W7: 127 | X7: 99 | Y7: 0 | Z7: =SUM(S7:Y7) -> 876 | AB7: 1420200 | AC7: J MHC CINTURA R | AD7: Ventas | AF7: 84 | AG7: 178 | AH7: 193 | AI7: 185 | AJ7: 126 | AK7: 98 | AL7: 0 | AM7: =SUM(AF7:AL7) -> 864 | AO7: 1420200 | AP7: J MHC CINTURA R | AQ7: Ventas | AS7: 84 | AT7: 176 | AU7: 191 | AV7: 183 | AW7: 124 | AX7: 96 | AY7: 0 | AZ7: =SUM(AS7:AY7) -> 854 | BB7: 1420200 | BC7: J MHC CINTURA R | BD7: Ventas | BF7: 74 | BG7: 159 | BH7: 173 | BI7: 167 | BJ7: 119 | BK7: 92 | BL7: 0 | BM7: =SUM(BF7:BL7) -> 784 | BO7: 1420200 | BP7: J MHC CINTURA R | BQ7: Ventas | BS7: 72 | BT7: 156 | BU7: 170 | BV7: 165 | BW7: 118 | BX7: 92 | BY7: 0 | BZ7: =SUM(BS7:BY7) -> 773 | CB7: 1420200 | CC7: J MHC CINTURA R | CD7: Ventas | CF7: 68 | CG7: 151 | CH7: 165 | CI7: 160 | CJ7: 114 | CK7: 90 | CL7: 0 | CM7: =SUM(CF7:CL7) -> 748 | CO7: 1420200 | CP7: J MHC CINTURA R | CQ7: Ventas | CS7: 67 | CT7: 145 | CU7: 159 | CV7: 154 | CW7: 110 | CX7: 88 | CY7: 0 | CZ7: 723 | DB7: 1420200 | DC7: J MHC CINTURA R | DD7: Ventas | DF7: 63 | DG7: 138 | DH7: 148 | DI7: 141 | DJ7: 98 | DK7: 79 | DL7: 0 | DM7: 667 | DO7: 1420200 | DP7: J MHC CINTURA R | DQ7: Ventas | DS7: 56 | DT7: 123 | DU7: 128 | DV7: 126 | DW7: 87 | DX7: 73 | DY7: 0 | DZ7: 593 | EB7: 1420200 | EC7: J MHC CINTURA R | ED7: Ventas | EF7: 53 | EG7: 117 | EH7: 123 | EI7: 121 | EJ7: 83 | EK7: 70 | EL7: 0 | EM7: 567 | EO7: 1420200 | EP7: J MHC CINTURA R | EQ7: Ventas | ES7: 50 | ET7: 112 | EU7: 118 | EV7: 116 | EW7: 80 | EX7: 68 | EY7: 0 | EZ7: 544 | FB7: 1420200 | FC7: J MHC CINTURA R | FD7: Ventas | FF7: 41 | FG7: 97 | FH7: 103 | FI7: 101 | FJ7: 69 | FK7: 61 | FL7: 0 | FM7: 472 | FO7: 1420200 | FP7: J MHC CINTURA R | FQ7: Ventas | FS7: 39 | FT7: 91 | FU7: 97 | FV7: 95 | FW7: 65 | FX7: 57 | FY7: 0 | FZ7: 444 | GB7: 1420200 | GC7: J MHC CINTURA R | GD7: Ventas | GF7: 12 | GG7: 21 | GH7: 25 | GI7: 23 | GJ7: 18 | GK7: 13 | GL7: 0 | GM7: 112 | GO7: 1420200 | GP7: J MHC CINTURA R | GQ7: Ventas | GS7: 9 | GT7: 16 | GU7: 18 | GV7: 17 | GW7: 14 | GX7: 10 | GY7: 0 | GZ7: =SUM(GS7:GY7) -> 84
A8: 1420300 | B8: B2868-V3 | C8: 4 | D8: 9 | E8: 9 | F8: 7 | G8: 2 | H8: 1 | J8: =SUM(C8:H8) -> 32 | K8: ='CORTE 4200'!$O$52 -> -1 | O8: 1420300 | P8: J MHC MEDIO TOB | Q8: Ventas | S8: 4 | T8: 9 | U8: 9 | V8: 7 | W8: 2 | X8: 1 | Y8: 0 | Z8: =SUM(S8:Y8) -> 32 | AB8: 1420300 | AC8: J MHC MEDIO TOB | AD8: Ventas | AF8: 4 | AG8: 9 | AH8: 9 | AI8: 7 | AJ8: 2 | AK8: 1 | AL8: 0 | AM8: =SUM(AF8:AL8) -> 32 | AO8: 1420300 | AP8: J MHC MEDIO TOB | AQ8: Ventas | AS8: 4 | AT8: 9 | AU8: 9 | AV8: 7 | AW8: 2 | AX8: 1 | AY8: 0 | AZ8: =SUM(AS8:AY8) -> 32 | BB8: 1420300 | BC8: J MHC MEDIO TOB | BD8: Ventas | BF8: 4 | BG8: 9 | BH8: 9 | BI8: 7 | BJ8: 2 | BK8: 1 | BL8: 0 | BM8: =SUM(BF8:BL8) -> 32 | BO8: 1420300 | BP8: J MHC MEDIO TOB | BQ8: Ventas | BS8: 4 | BT8: 9 | BU8: 9 | BV8: 7 | BW8: 2 | BX8: 1 | BY8: 0 | BZ8: =SUM(BS8:BY8) -> 32 | CB8: 1420300 | CC8: J MHC MEDIO TOB | CD8: Ventas | CF8: 4 | CG8: 9 | CH8: 9 | CI8: 7 | CJ8: 2 | CK8: 1 | CL8: 0 | CM8: =SUM(CF8:CL8) -> 32 | CO8: 1420300 | CP8: J MHC MEDIO TOB | CQ8: Ventas | CS8: 4 | CT8: 9 | CU8: 9 | CV8: 7 | CW8: 2 | CX8: 1 | CY8: 0 | CZ8: 32 | DB8: 1420300 | DC8: J MHC MEDIO TOB | DD8: Ventas | DF8: 4 | DG8: 9 | DH8: 9 | DI8: 7 | DJ8: 2 | DK8: 1 | DL8: 0 | DM8: 32 | DO8: 1420300 | DP8: J MHC MEDIO TOB | DQ8: Ventas | DS8: 4 | DT8: 9 | DU8: 9 | DV8: 7 | DW8: 2 | DX8: 1 | DY8: 0 | DZ8: 32 | EB8: 1420300 | EC8: J MHC MEDIO TOB | ED8: Ventas | EF8: 4 | EG8: 9 | EH8: 9 | EI8: 7 | EJ8: 2 | EK8: 1 | EL8: 0 | EM8: 32 | EO8: 1420300 | EP8: J MHC MEDIO TOB | EQ8: Ventas | ES8: 4 | ET8: 9 | EU8: 9 | EV8: 7 | EW8: 2 | EX8: 1 | EY8: 0 | EZ8: 32 | FB8: 1420300 | FC8: J MHC MEDIO TOB | FD8: Ventas | FF8: 1 | FG8: 3 | FH8: 3 | FI8: 2 | FJ8: 1 | FK8: 1 | FL8: 0 | FM8: 11 | FO8: 1420300 | FP8: J MHC MEDIO TOB | FQ8: Ventas | FS8: 1 | FT8: 3 | FU8: 3 | FV8: 2 | FW8: 1 | FX8: 1 | FY8: 0 | FZ8: 11 | GB8: 1420300 | GC8: J MHC MEDIO TOB | GD8: Ventas | GF8: 1 | GG8: 3 | GH8: 3 | GI8: 2 | GJ8: 1 | GK8: 1 | GL8: 0 | GM8: 11 | GO8: 1420300 | GP8: J MHC MEDIO TOB | GQ8: Ventas | GS8: 1 | GT8: 3 | GU8: 3 | GV8: 2 | GW8: 1 | GX8: 1 | GY8: 0 | GZ8: =SUM(GS8:GY8) -> 11
A9: 1420301 | B9: B2868-V3 | C9: 31 | D9: 62 | E9: 59 | F9: 58 | G9: 40 | H9: 35 | J9: =SUM(C9:H9) -> 285 | K9: ='CORTE 4200'!$O$61 -> -88 | O9: 1420301 | P9: J MHC MEDIO TOB | Q9: Ventas | S9: 31 | T9: 62 | U9: 59 | V9: 58 | W9: 40 | X9: 35 | Y9: 0 | Z9: =SUM(S9:Y9) -> 285 | AB9: 1420301 | AC9: J MHC MEDIO TOB | AD9: Ventas | AF9: 31 | AG9: 62 | AH9: 59 | AI9: 58 | AJ9: 40 | AK9: 35 | AL9: 0 | AM9: =SUM(AF9:AL9) -> 285 | AO9: 1420301 | AP9: J MHC MEDIO TOB | AQ9: Ventas | AS9: 31 | AT9: 62 | AU9: 59 | AV9: 58 | AW9: 40 | AX9: 35 | AY9: 0 | AZ9: =SUM(AS9:AY9) -> 285 | BB9: 1420301 | BC9: J MHC MEDIO TOB | BD9: Ventas | BF9: 31 | BG9: 62 | BH9: 59 | BI9: 58 | BJ9: 40 | BK9: 35 | BL9: 0 | BM9: =SUM(BF9:BL9) -> 285 | BO9: 1420301 | BP9: J MHC MEDIO TOB | BQ9: Ventas | BS9: 31 | BT9: 62 | BU9: 59 | BV9: 58 | BW9: 40 | BX9: 35 | BY9: 0 | BZ9: =SUM(BS9:BY9) -> 285 | CB9: 1420301 | CC9: J MHC MEDIO TOB | CD9: Ventas | CF9: 31 | CG9: 62 | CH9: 59 | CI9: 58 | CJ9: 40 | CK9: 35 | CL9: 0 | CM9: =SUM(CF9:CL9) -> 285 | CO9: 1420301 | CP9: J MHC MEDIO TOB | CQ9: Ventas | CS9: 31 | CT9: 62 | CU9: 59 | CV9: 58 | CW9: 40 | CX9: 35 | CY9: 0 | CZ9: 285 | DB9: 1420301 | DC9: J MHC MEDIO TOB | DD9: Ventas | DF9: 31 | DG9: 62 | DH9: 59 | DI9: 58 | DJ9: 40 | DK9: 35 | DL9: 0 | DM9: 285 | DO9: 1420301 | DP9: J MHC MEDIO TOB | DQ9: Ventas | DS9: 31 | DT9: 62 | DU9: 59 | DV9: 58 | DW9: 40 | DX9: 35 | DY9: 0 | DZ9: 285 | EB9: 1420301 | EC9: J MHC MEDIO TOB | ED9: Ventas | EF9: 31 | EG9: 62 | EH9: 59 | EI9: 58 | EJ9: 40 | EK9: 35 | EL9: 0 | EM9: 285 | EO9: 1420301 | EP9: J MHC MEDIO TOB | EQ9: Ventas | ES9: 30 | ET9: 60 | EU9: 57 | EV9: 56 | EW9: 39 | EX9: 34 | EY9: 0 | EZ9: 276 | FB9: 1420301 | FC9: J MHC MEDIO TOB | FD9: Ventas | FF9: 26 | FG9: 54 | FH9: 51 | FI9: 50 | FJ9: 35 | FK9: 30 | FL9: 0 | FM9: 246 | FO9: 1420301 | FP9: J MHC MEDIO TOB | FQ9: Ventas | FS9: 26 | FT9: 54 | FU9: 51 | FV9: 50 | FW9: 35 | FX9: 30 | FY9: 0 | FZ9: 246 | GB9: 1420301 | GC9: J MHC MEDIO TOB | GD9: Ventas | GF9: 15 | GG9: 21 | GH9: 18 | GI9: 17 | GJ9: 13 | GK9: 8 | GL9: 0 | GM9: 92 | GO9: 1420301 | GP9: J MHC MEDIO TOB | GQ9: Ventas | GS9: 15 | GT9: 21 | GU9: 18 | GV9: 17 | GW9: 13 | GX9: 8 | GY9: 0 | GZ9: =SUM(GS9:GY9) -> 92
A10: 1420400 | B10: B2868-V3 | C10: 39 | D10: 82 | E10: 90 | F10: 81 | G10: 54 | H10: 40 | J10: =SUM(C10:H10) -> 386 | K10: ='CORTE 4200'!$O$70 -> -27 | L10: 50 | O10: 1420400 | P10: J MHC MEDIO FLA | Q10: Ventas | S10: 39 | T10: 82 | U10: 90 | V10: 81 | W10: 54 | X10: 40 | Y10: 0 | Z10: =SUM(S10:Y10) -> 386 | AB10: 1420400 | AC10: J MHC MEDIO FLA | AD10: Ventas | AF10: 39 | AG10: 82 | AH10: 90 | AI10: 81 | AJ10: 54 | AK10: 40 | AL10: 0 | AM10: =SUM(AF10:AL10) -> 386 | AO10: 1420400 | AP10: J MHC MEDIO FLA | AQ10: Ventas | AS10: 39 | AT10: 80 | AU10: 88 | AV10: 79 | AW10: 52 | AX10: 38 | AY10: 0 | AZ10: =SUM(AS10:AY10) -> 376 | BB10: 1420400 | BC10: J MHC MEDIO FLA | BD10: Ventas | BF10: 31 | BG10: 68 | BH10: 76 | BI10: 67 | BJ10: 49 | BK10: 35 | BL10: 0 | BM10: =SUM(BF10:BL10) -> 326 | BO10: 1420400 | BP10: J MHC MEDIO FLA | BQ10: Ventas | BS10: 31 | BT10: 68 | BU10: 76 | BV10: 67 | BW10: 49 | BX10: 35 | BY10: 0 | BZ10: =SUM(BS10:BY10) -> 326 | CB10: 1420400 | CC10: J MHC MEDIO FLA | CD10: Ventas | CF10: 29 | CG10: 66 | CH10: 74 | CI10: 65 | CJ10: 47 | CK10: 33 | CL10: 0 | CM10: =SUM(CF10:CL10) -> 314 | CO10: 1420400 | CP10: J MHC MEDIO FLA | CQ10: Ventas | CS10: 29 | CT10: 66 | CU10: 74 | CV10: 65 | CW10: 47 | CX10: 33 | CY10: 0 | CZ10: 314 | DB10: 1420400 | DC10: J MHC MEDIO FLA | DD10: Ventas | DF10: 28 | DG10: 64 | DH10: 72 | DI10: 63 | DJ10: 45 | DK10: 32 | DL10: 0 | DM10: 304 | DO10: 1420400 | DP10: J MHC MEDIO FLA | DQ10: Ventas | DS10: 21 | DT10: 51 | DU10: 55 | DV10: 52 | DW10: 39 | DX10: 28 | DY10: 0 | DZ10: 246 | EB10: 1420400 | EC10: J MHC MEDIO FLA | ED10: Ventas | EF10: 18 | EG10: 44 | EH10: 49 | EI10: 46 | EJ10: 35 | EK10: 25 | EL10: 0 | EM10: 217 | EO10: 1420400 | EP10: J MHC MEDIO FLA | EQ10: Ventas | ES10: 18 | ET10: 44 | EU10: 49 | EV10: 46 | EW10: 35 | EX10: 25 | EY10: 0 | EZ10: 217 | FB10: 1420400 | FC10: J MHC MEDIO FLA | FD10: Ventas | FF10: 15 | FG10: 39 | FH10: 44 | FI10: 41 | FJ10: 30 | FK10: 23 | FL10: 0 | FM10: 192 | FO10: 1420400 | FP10: J MHC MEDIO FLA | FQ10: Ventas | FS10: 15 | FT10: 39 | FU10: 44 | FV10: 41 | FW10: 30 | FX10: 23 | FY10: 0 | FZ10: 192 | GB10: 1420400 | GC10: J MHC MEDIO FLA | GD10: Ventas | GF10: 8 | GG10: 23 | GH10: 28 | GI10: 25 | GJ10: 19 | GK10: 12 | GL10: 0 | GM10: 115 | GO10: 1420400 | GP10: J MHC MEDIO FLA | GQ10: Ventas | GS10: 7 | GT10: 20 | GU10: 24 | GV10: 22 | GW10: 17 | GX10: 11 | GY10: 0 | GZ10: =SUM(GS10:GY10) -> 101
A11: 1420401 | B11: B2868-V3 | C11: 2 | D11: 6 | E11: 9 | F11: 8 | G11: 7 | H11: 5 | J11: =SUM(C11:H11) -> 37 | K11: ='CORTE 4200'!$O$79 -> 2 | O11: 1420401 | P11: J MHC MEDIO FLA | Q11: Ventas | S11: 2 | T11: 6 | U11: 9 | V11: 8 | W11: 7 | X11: 5 | Y11: 0 | Z11: =SUM(S11:Y11) -> 37 | AB11: 1420401 | AC11: J MHC MEDIO FLA | AD11: Ventas | AF11: 0 | AG11: 4 | AH11: 8 | AI11: 8 | AJ11: 7 | AK11: 5 | AL11: 0 | AM11: =SUM(AF11:AL11) -> 32 | AO11: 1420401 | AP11: J MHC MEDIO FLA | AQ11: Ventas | AS11: 0 | AT11: 4 | AU11: 8 | AV11: 8 | AW11: 7 | AX11: 5 | AY11: 0 | AZ11: =SUM(AS11:AY11) -> 32 | BB11: 1420401 | BC11: J MHC MEDIO FLA | BD11: Ventas | BF11: 0 | BG11: 4 | BH11: 8 | BI11: 8 | BJ11: 7 | BK11: 5 | BL11: 0 | BM11: =SUM(BF11:BL11) -> 32 | BO11: 1420401 | BP11: J MHC MEDIO FLA | BQ11: Ventas | BS11: 0 | BT11: 4 | BU11: 8 | BV11: 8 | BW11: 7 | BX11: 5 | BY11: 0 | BZ11: =SUM(BS11:BY11) -> 32 | CB11: 1420401 | CC11: J MHC MEDIO FLA | CD11: Ventas | CF11: 0 | CG11: 4 | CH11: 8 | CI11: 8 | CJ11: 7 | CK11: 5 | CL11: 0 | CM11: =SUM(CF11:CL11) -> 32 | CO11: 1420401 | CP11: J MHC MEDIO FLA | CQ11: Ventas | CS11: 0 | CT11: 4 | CU11: 8 | CV11: 8 | CW11: 7 | CX11: 5 | CY11: 0 | CZ11: 32 | DB11: 1420401 | DC11: J MHC MEDIO FLA | DD11: Ventas | DF11: 0 | DG11: 4 | DH11: 8 | DI11: 8 | DJ11: 7 | DK11: 5 | DL11: 0 | DM11: 32 | DO11: 1420401 | DP11: J MHC MEDIO FLA | DQ11: Ventas | DS11: 0 | DT11: 4 | DU11: 8 | DV11: 8 | DW11: 7 | DX11: 5 | DY11: 0 | DZ11: 32 | EB11: 1420401 | EC11: J MHC MEDIO FLA | ED11: Ventas | EF11: 0 | EG11: 4 | EH11: 8 | EI11: 8 | EJ11: 7 | EK11: 5 | EL11: 0 | EM11: 32 | EO11: 1420401 | EP11: J MHC MEDIO FLA | EQ11: Ventas | ES11: 0 | ET11: 4 | EU11: 8 | EV11: 8 | EW11: 7 | EX11: 5 | EY11: 0 | EZ11: 32 | FB11: 1420401 | FC11: J MHC MEDIO FLA | FD11: Ventas | FF11: 0 | FG11: 4 | FH11: 8 | FI11: 8 | FJ11: 7 | FK11: 5 | FL11: 0 | FM11: 32 | FO11: 1420401 | FP11: J MHC MEDIO FLA | FQ11: Ventas | FS11: 0 | FT11: 4 | FU11: 8 | FV11: 8 | FW11: 7 | FX11: 5 | FY11: 0 | FZ11: 32 | GB11: 1420401 | GC11: J MHC MEDIO FLA | GD11: Ventas | GF11: 0 | GG11: 4 | GH11: 8 | GI11: 8 | GJ11: 7 | GK11: 5 | GL11: 0 | GM11: 32 | GO11: 1420401 | GP11: J MHC MEDIO FLA | GQ11: Ventas | GS11: 0 | GT11: 4 | GU11: 8 | GV11: 8 | GW11: 7 | GX11: 5 | GY11: 0 | GZ11: =SUM(GS11:GY11) -> 32
A12: 1420402 | B12: B2868-V3 | C12: 31 | D12: 78 | E12: 83 | F12: 80 | G12: 56 | H12: 48 | J12: =SUM(C12:H12) -> 376 | K12: ='CORTE 4200'!$O$88 -> -16 | O12: 1420402 | P12: J MHC MEDIO FLA | Q12: Ventas | S12: 31 | T12: 78 | U12: 83 | V12: 80 | W12: 56 | X12: 48 | Y12: 0 | Z12: =SUM(S12:Y12) -> 376 | AB12: 1420402 | AC12: J MHC MEDIO FLA | AD12: Ventas | AF12: 33 | AG12: 83 | AH12: 88 | AI12: 82 | AJ12: 57 | AK12: 48 | AL12: 0 | AM12: =SUM(AF12:AL12) -> 391 | AO12: 1420402 | AP12: J MHC MEDIO FLA | AQ12: Ventas | AS12: 33 | AT12: 81 | AU12: 86 | AV12: 80 | AW12: 55 | AX12: 46 | AY12: 0 | AZ12: =SUM(AS12:AY12) -> 381 | BB12: 1420402 | BC12: J MHC MEDIO FLA | BD12: Ventas | BF12: 33 | BG12: 81 | BH12: 86 | BI12: 80 | BJ12: 55 | BK12: 46 | BL12: 0 | BM12: =SUM(BF12:BL12) -> 381 | BO12: 1420402 | BP12: J MHC MEDIO FLA | BQ12: Ventas | BS12: 33 | BT12: 81 | BU12: 86 | BV12: 80 | BW12: 55 | BX12: 46 | BY12: 0 | BZ12: =SUM(BS12:BY12) -> 381 | CB12: 1420402 | CC12: J MHC MEDIO FLA | CD12: Ventas | CF12: 33 | CG12: 81 | CH12: 86 | CI12: 80 | CJ12: 55 | CK12: 46 | CL12: 0 | CM12: =SUM(CF12:CL12) -> 381 | CO12: 1420402 | CP12: J MHC MEDIO FLA | CQ12: Ventas | CS12: 33 | CT12: 81 | CU12: 86 | CV12: 80 | CW12: 55 | CX12: 46 | CY12: 0 | CZ12: 381 | DB12: 1420402 | DC12: J MHC MEDIO FLA | DD12: Ventas | DF12: 31 | DG12: 78 | DH12: 83 | DI12: 77 | DJ12: 53 | DK12: 45 | DL12: 0 | DM12: 367 | DO12: 1420402 | DP12: J MHC MEDIO FLA | DQ12: Ventas | DS12: 28 | DT12: 74 | DU12: 79 | DV12: 74 | DW12: 51 | DX12: 45 | DY12: 0 | DZ12: 351 | EB12: 1420402 | EC12: J MHC MEDIO FLA | ED12: Ventas | EF12: 26 | EG12: 69 | EH12: 74 | EI12: 72 | EJ12: 50 | EK12: 45 | EL12: 0 | EM12: 336 | EO12: 1420402 | EP12: J MHC MEDIO FLA | EQ12: Ventas | ES12: 26 | ET12: 69 | EU12: 74 | EV12: 72 | EW12: 50 | EX12: 45 | EY12: 0 | EZ12: 336 | FB12: 1420402 | FC12: J MHC MEDIO FLA | FD12: Ventas | FF12: 24 | FG12: 66 | FH12: 71 | FI12: 69 | FJ12: 48 | FK12: 43 | FL12: 0 | FM12: 321 | FO12: 1420402 | FP12: J MHC MEDIO FLA | FQ12: Ventas | FS12: 22 | FT12: 60 | FU12: 65 | FV12: 63 | FW12: 44 | FX12: 39 | FY12: 0 | FZ12: 293 | GB12: 1420402 | GC12: J MHC MEDIO FLA | GD12: Ventas | GF12: 8 | GG12: 18 | GH12: 23 | GI12: 21 | GJ12: 16 | GK12: 11 | GL12: 0 | GM12: 97 | GO12: 1420402 | GP12: J MHC MEDIO FLA | GQ12: Ventas | GS12: 7 | GT12: 15 | GU12: 19 | GV12: 18 | GW12: 14 | GX12: 10 | GY12: 0 | GZ12: =SUM(GS12:GY12) -> 83
A13: 1420500 | B13: Ayla | C13: 60 | D13: 119 | E13: 124 | F13: 121 | G13: 80 | H13: 66 | J13: =SUM(C13:H13) -> 570 | K13: ='CORTE 4200'!$O$97 -> -148 | L13: 50 | O13: 1420500 | P13: J MHC CINTURA O | Q13: Ventas | S13: 60 | T13: 119 | U13: 124 | V13: 121 | W13: 80 | X13: 66 | Y13: 0 | Z13: =SUM(S13:Y13) -> 570 | AB13: 1420500 | AC13: J MHC CINTURA O | AD13: Ventas | AF13: 60 | AG13: 119 | AH13: 123 | AI13: 120 | AJ13: 80 | AK13: 66 | AL13: 0 | AM13: =SUM(AF13:AL13) -> 568 | AO13: 1420500 | AP13: J MHC CINTURA O | AQ13: Ventas | AS13: 60 | AT13: 117 | AU13: 121 | AV13: 118 | AW13: 78 | AX13: 64 | AY13: 0 | AZ13: =SUM(AS13:AY13) -> 558 | BB13: 1420500 | BC13: J MHC CINTURA O | BD13: Ventas | BF13: 52 | BG13: 105 | BH13: 109 | BI13: 106 | BJ13: 75 | BK13: 61 | BL13: 0 | BM13: =SUM(BF13:BL13) -> 508 | BO13: 1420500 | BP13: J MHC CINTURA O | BQ13: Ventas | BS13: 52 | BT13: 105 | BU13: 109 | BV13: 106 | BW13: 75 | BX13: 61 | BY13: 0 | BZ13: =SUM(BS13:BY13) -> 508 | CB13: 1420500 | CC13: J MHC CINTURA O | CD13: Ventas | CF13: 52 | CG13: 105 | CH13: 109 | CI13: 106 | CJ13: 75 | CK13: 61 | CL13: 0 | CM13: =SUM(CF13:CL13) -> 508 | CO13: 1420500 | CP13: J MHC CINTURA O | CQ13: Ventas | CS13: 52 | CT13: 104 | CU13: 108 | CV13: 105 | CW13: 74 | CX13: 61 | CY13: 0 | CZ13: 504 | DB13: 1420500 | DC13: J MHC CINTURA O | DD13: Ventas | DF13: 51 | DG13: 101 | DH13: 104 | DI13: 101 | DJ13: 70 | DK13: 59 | DL13: 0 | DM13: 486 | DO13: 1420500 | DP13: J MHC CINTURA O | DQ13: Ventas | DS13: 51 | DT13: 99 | DU13: 101 | DV13: 98 | DW13: 67 | DX13: 57 | DY13: 0 | DZ13: 473 | EB13: 1420500 | EC13: J MHC CINTURA O | ED13: Ventas | EF13: 51 | EG13: 99 | EH13: 101 | EI13: 98 | EJ13: 67 | EK13: 57 | EL13: 0 | EM13: 473 | EO13: 1420500 | EP13: J MHC CINTURA O | EQ13: Ventas | ES13: 46 | ET13: 93 | EU13: 95 | EV13: 93 | EW13: 64 | EX13: 54 | EY13: 0 | EZ13: 445 | FB13: 1420500 | FC13: J MHC CINTURA O | FD13: Ventas | FF13: 46 | FG13: 93 | FH13: 95 | FI13: 93 | FJ13: 64 | FK13: 54 | FL13: 0 | FM13: 445 | FO13: 1420500 | FP13: J MHC CINTURA O | FQ13: Ventas | FS13: 44 | FT13: 87 | FU13: 89 | FV13: 87 | FW13: 60 | FX13: 50 | FY13: 0 | FZ13: 417 | GB13: 1420500 | GC13: J MHC CINTURA O | GD13: Ventas | GF13: 21 | GG13: 31 | GH13: 33 | GI13: 30 | GJ13: 22 | GK13: 14 | GL13: 0 | GM13: 151 | GO13: 1420500 | GP13: J MHC CINTURA O | GQ13: Ventas | GS13: 18 | GT13: 26 | GU13: 26 | GV13: =14+10 -> 24 | GW13: =20-10+8 -> 18 | GX13: =13-8+6 -> 11 | GZ13: =SUM(GS13:GY13) -> 123
A14: 1420501 | B14: Ayla | C14: 35 | D14: 78 | E14: 87 | F14: 85 | G14: 62 | H14: 54 | J14: =SUM(C14:H14) -> 401 | K14: ='CORTE 4200'!$O$106 -> -6 | O14: 1420501 | P14: J MHC CINTURA O | Q14: Ventas | S14: 35 | T14: 78 | U14: 87 | V14: 85 | W14: 62 | X14: 54 | Y14: 0 | Z14: =SUM(S14:Y14) -> 401 | AB14: 1420501 | AC14: J MHC CINTURA O | AD14: Ventas | AF14: 35 | AG14: 78 | AH14: 87 | AI14: 85 | AJ14: 62 | AK14: 54 | AL14: 0 | AM14: =SUM(AF14:AL14) -> 401 | AO14: 1420501 | AP14: J MHC CINTURA O | AQ14: Ventas | AS14: 35 | AT14: 78 | AU14: 87 | AV14: 85 | AW14: 62 | AX14: 54 | AY14: 0 | AZ14: =SUM(AS14:AY14) -> 401 | BB14: 1420501 | BC14: J MHC CINTURA O | BD14: Ventas | BF14: 34 | BG14: 76 | BH14: 84 | BI14: 83 | BJ14: 61 | BK14: 53 | BL14: 0 | BM14: =SUM(BF14:BL14) -> 391 | BO14: 1420501 | BP14: J MHC CINTURA O | BQ14: Ventas | BS14: 32 | BT14: 72 | BU14: 80 | BV14: 80 | BW14: 59 | BX14: 52 | BY14: 0 | BZ14: =SUM(BS14:BY14) -> 375 | CB14: 1420501 | CC14: J MHC CINTURA O | CD14: Ventas | CF14: 30 | CG14: 70 | CH14: 78 | CI14: 77 | CJ14: 57 | CK14: 52 | CL14: 0 | CM14: =SUM(CF14:CL14) -> 364 | CO14: 1420501 | CP14: J MHC CINTURA O | CQ14: Ventas | CS14: 30 | CT14: 70 | CU14: 78 | CV14: 77 | CW14: 57 | CX14: 52 | CY14: 0 | CZ14: 364 | DB14: 1420501 | DC14: J MHC CINTURA O | DD14: Ventas | DF14: 30 | DG14: 69 | DH14: 74 | DI14: 71 | DJ14: 51 | DK14: 46 | DL14: 0 | DM14: 341 | DO14: 1420501 | DP14: J MHC CINTURA O | DQ14: Ventas | DS14: 30 | DT14: 69 | DU14: 74 | DV14: 71 | DW14: 51 | DX14: 46 | DY14: 0 | DZ14: 341 | EB14: 1420501 | EC14: J MHC CINTURA O | ED14: Ventas | EF14: 30 | EG14: 69 | EH14: 74 | EI14: 71 | EJ14: 51 | EK14: 46 | EL14: 0 | EM14: 341 | EO14: 1420501 | EP14: J MHC CINTURA O | EQ14: Ventas | ES14: 29 | ET14: 67 | EU14: 72 | EV14: 69 | EW14: 49 | EX14: 44 | EY14: 0 | EZ14: 330 | FB14: 1420501 | FC14: J MHC CINTURA O | FD14: Ventas | FF14: 22 | FG14: 56 | FH14: 60 | FI14: 59 | FJ14: 42 | FK14: 38 | FL14: 0 | FM14: 277 | FO14: 1420501 | FP14: J MHC CINTURA O | FQ14: Ventas | FS14: 22 | FT14: 56 | FU14: 60 | FV14: 59 | FW14: 42 | FX14: 38 | FY14: 0 | FZ14: 277 | GB14: 1420501 | GC14: J MHC CINTURA O | GD14: Ventas | GF14: 9 | GG14: 17 | GH14: 21 | GI14: 20 | GJ14: 16 | GK14: 12 | GL14: 0 | GM14: 95 | GO14: 1420501 | GP14: J MHC CINTURA O | GQ14: Ventas | GS14: 9 | GT14: 17 | GU14: 21 | GV14: 20 | GW14: 16 | GX14: 12 | GY14: 0 | GZ14: =SUM(GS14:GY14) -> 95
A15: 1420502 | B15: Ayla | C15: 0 | D15: 4 | E15: 8 | F15: 8 | G15: 7 | H15: 5 | J15: =SUM(C15:H15) -> 32 | K15: ='CORTE 4200'!$O$115 -> 0 | O15: 1420502 | P15: J MHC CINTURA O | Q15: Ventas | S15: 0 | T15: 4 | U15: 8 | V15: 8 | W15: 7 | X15: 5 | Y15: 0 | Z15: =SUM(S15:Y15) -> 32 | AB15: 1420502 | AC15: J MHC CINTURA O | AD15: Ventas | AF15: 0 | AG15: 4 | AH15: 8 | AI15: 8 | AJ15: 7 | AK15: 5 | AL15: 0 | AM15: =SUM(AF15:AL15) -> 32 | AO15: 1420502 | AP15: J MHC CINTURA O | AQ15: Ventas | AS15: 0 | AT15: 4 | AU15: 8 | AV15: 8 | AW15: 7 | AX15: 5 | AY15: 0 | AZ15: =SUM(AS15:AY15) -> 32 | BB15: 1420502 | BC15: J MHC CINTURA O | BD15: Ventas | BF15: 0 | BG15: 4 | BH15: 8 | BI15: 8 | BJ15: 7 | BK15: 5 | BL15: 0 | BM15: =SUM(BF15:BL15) -> 32 | BO15: 1420502 | BP15: J MHC CINTURA O | BQ15: Ventas | BS15: 0 | BT15: 4 | BU15: 8 | BV15: 8 | BW15: 7 | BX15: 5 | BY15: 0 | BZ15: =SUM(BS15:BY15) -> 32 | CB15: 1420502 | CC15: J MHC CINTURA O | CD15: Ventas | CF15: 0 | CG15: 4 | CH15: 8 | CI15: 8 | CJ15: 7 | CK15: 5 | CL15: 0 | CM15: =SUM(CF15:CL15) -> 32 | CO15: 1420502 | CP15: J MHC CINTURA O | CQ15: Ventas | CS15: 0 | CT15: 4 | CU15: 8 | CV15: 8 | CW15: 7 | CX15: 5 | CY15: 0 | CZ15: 32 | DB15: 1420502 | DC15: J MHC CINTURA O | DD15: Ventas | DF15: 0 | DG15: 4 | DH15: 8 | DI15: 8 | DJ15: 7 | DK15: 5 | DL15: 0 | DM15: 32 | DO15: 1420502 | DP15: J MHC CINTURA O | DQ15: Ventas | DS15: 0 | DT15: 4 | DU15: 8 | DV15: 8 | DW15: 7 | DX15: 5 | DY15: 0 | DZ15: 32 | EB15: 1420502 | EC15: J MHC CINTURA O | ED15: Ventas | EF15: 0 | EG15: 4 | EH15: 8 | EI15: 8 | EJ15: 7 | EK15: 5 | EL15: 0 | EM15: 32 | EO15: 1420502 | EP15: J MHC CINTURA O | EQ15: Ventas | ES15: 0 | ET15: 4 | EU15: 8 | EV15: 8 | EW15: 7 | EX15: 5 | EY15: 0 | EZ15: 32 | FB15: 1420502 | FC15: J MHC CINTURA O | FD15: Ventas | FF15: 0 | FG15: 4 | FH15: 8 | FI15: 8 | FJ15: 7 | FK15: 5 | FL15: 0 | FM15: 32 | FO15: 1420502 | FP15: J MHC CINTURA O | FQ15: Ventas | FS15: 0 | FT15: 4 | FU15: 8 | FV15: 8 | FW15: 7 | FX15: 5 | FY15: 0 | FZ15: 32 | GB15: 1420502 | GC15: J MHC CINTURA O | GD15: Ventas | GF15: 0 | GG15: 4 | GH15: 8 | GI15: 8 | GJ15: 7 | GK15: 5 | GL15: 0 | GM15: 32 | GO15: 1420502 | GP15: J MHC CINTURA O | GQ15: Ventas | GS15: 0 | GT15: 4 | GU15: 8 | GV15: 8 | GW15: 7 | GX15: 5 | GY15: 0 | GZ15: =SUM(GS15:GY15) -> 32
A16: 1420600 | B16: B2868-V3 | C16: 35 | D16: 71 | E16: 70 | F16: 63 | G16: 40 | H16: 26 | J16: =SUM(C16:H16) -> 305 | K16: ='CORTE 4200'!$O$124 -> -201 | L16: 50 | O16: 1420600 | P16: J MHC CINTURA P | Q16: Ventas | S16: 35 | T16: 71 | U16: 70 | V16: 63 | W16: 40 | X16: 26 | Y16: 0 | Z16: =SUM(S16:Y16) -> 305 | AB16: 1420600 | AC16: J MHC CINTURA P | AD16: Ventas | AF16: 35 | AG16: 69 | AH16: 68 | AI16: 62 | AJ16: 40 | AK16: 26 | AL16: 0 | AM16: =SUM(AF16:AL16) -> 300 | AO16: 1420600 | AP16: J MHC CINTURA P | AQ16: Ventas | AS16: 33 | AT16: 67 | AU16: 66 | AV16: 60 | AW16: 39 | AX16: 25 | AY16: 0 | AZ16: =SUM(AS16:AY16) -> 290 | BB16: 1420600 | BC16: J MHC CINTURA P | BD16: Ventas | BF16: 25 | BG16: 55 | BH16: 54 | BI16: 48 | BJ16: 36 | BK16: 22 | BL16: 0 | BM16: =SUM(BF16:BL16) -> 240 | BO16: 1420600 | BP16: J MHC CINTURA P | BQ16: Ventas | BS16: 25 | BT16: 55 | BU16: 54 | BV16: 48 | BW16: 36 | BX16: 22 | BY16: 0 | BZ16: =SUM(BS16:BY16) -> 240 | CB16: 1420600 | CC16: J MHC CINTURA P | CD16: Ventas | CF16: 21 | CG16: 50 | CH16: 49 | CI16: 42 | CJ16: 32 | CK16: 21 | CL16: 0 | CM16: =SUM(CF16:CL16) -> 215 | CO16: 1420600 | CP16: J MHC CINTURA P | CQ16: Ventas | CS16: 20 | CT16: 47 | CU16: 46 | CV16: 39 | CW16: 30 | CX16: 20 | CY16: 0 | CZ16: 202 | DB16: 1420600 | DC16: J MHC CINTURA P | DD16: Ventas | DF16: 18 | DG16: 43 | DH16: 40 | DI16: 35 | DJ16: 26 | DK16: 16 | DL16: 0 | DM16: 178 | DO16: 1420600 | DP16: J MHC CINTURA P | DQ16: Ventas | DS16: 15 | DT16: 37 | DU16: 35 | DV16: 32 | DW16: 24 | DX16: 16 | DY16: 0 | DZ16: 159 | EB16: 1420600 | EC16: J MHC CINTURA P | ED16: Ventas | EF16: 14 | EG16: 33 | EH16: 32 | EI16: 29 | EJ16: 22 | EK16: 14 | EL16: 0 | EM16: 144 | EO16: 1420600 | EP16: J MHC CINTURA P | EQ16: Ventas | ES16: 13 | ET16: 31 | EU16: 30 | EV16: 27 | EW16: 21 | EX16: 13 | EY16: 0 | EZ16: 135 | FB16: 1420600 | FC16: J MHC CINTURA P | FD16: Ventas | FF16: 9 | FG16: 23 | FH16: 22 | FI16: 20 | FJ16: 15 | FK16: 10 | FL16: 0 | FM16: 99 | FO16: 1420600 | FP16: J MHC CINTURA P | FQ16: Ventas | FS16: 9 | FT16: 23 | FU16: 22 | FV16: 20 | FW16: 15 | FX16: 10 | FY16: 0 | FZ16: 99 | GB16: 1420600 | GC16: J MHC CINTURA P | GD16: Ventas | GF16: 4 | GG16: 12 | GH16: 11 | GI16: 9 | GJ16: 6 | GK16: 2 | GL16: 0 | GM16: 44 | GO16: 1420600 | GP16: J MHC CINTURA P | GQ16: Ventas | GS16: 3 | GT16: 9 | GU16: 7 | GV16: 6 | GW16: 4 | GX16: 1 | GY16: 0 | GZ16: =SUM(GS16:GY16) -> 30
A17: 1420700 | B17: Ayla | C17: 0 | D17: 4 | E17: 8 | F17: 8 | G17: 7 | H17: 5 | J17: =SUM(C17:H17) -> 32 | K17: ='CORTE 4200'!$O$133 -> 32 | O17: 1420700 | P17: J MHC MEDIO OXF | Q17: Ventas | S17: 0 | T17: 4 | U17: 8 | V17: 8 | W17: 7 | X17: 5 | Y17: 0 | Z17: =SUM(S17:Y17) -> 32 | AB17: 1420700 | AC17: J MHC MEDIO OXF | AD17: Ventas | AF17: 0 | AG17: 4 | AH17: 8 | AI17: 8 | AJ17: 7 | AK17: 5 | AL17: 0 | AM17: =SUM(AF17:AL17) -> 32 | AO17: 1420700 | AP17: J MHC MEDIO OXF | AQ17: Ventas | AS17: 0 | AT17: 4 | AU17: 8 | AV17: 8 | AW17: 7 | AX17: 5 | AY17: 0 | AZ17: =SUM(AS17:AY17) -> 32 | BB17: 1420700 | BC17: J MHC MEDIO OXF | BD17: Ventas | BF17: 0 | BG17: 4 | BH17: 8 | BI17: 8 | BJ17: 7 | BK17: 5 | BL17: 0 | BM17: =SUM(BF17:BL17) -> 32 | BO17: 1420700 | BP17: J MHC MEDIO OXF | BQ17: Ventas | BS17: 0 | BT17: 4 | BU17: 8 | BV17: 8 | BW17: 7 | BX17: 5 | BY17: 0 | BZ17: =SUM(BS17:BY17) -> 32 | CB17: 1420700 | CC17: J MHC MEDIO OXF | CD17: Ventas | CF17: 0 | CG17: 4 | CH17: 8 | CI17: 8 | CJ17: 7 | CK17: 5 | CL17: 0 | CM17: =SUM(CF17:CL17) -> 32 | CO17: 1420700 | CP17: J MHC MEDIO OXF | CQ17: Ventas | CS17: 0 | CT17: 4 | CU17: 8 | CV17: 8 | CW17: 7 | CX17: 5 | CY17: 0 | CZ17: 32 | DB17: 1420700 | DC17: J MHC MEDIO OXF | DD17: Ventas | DF17: 0 | DG17: 4 | DH17: 8 | DI17: 8 | DJ17: 7 | DK17: 5 | DL17: 0 | DM17: 32 | DO17: 1420700 | DP17: J MHC MEDIO OXF | DQ17: Ventas | DS17: 0 | DT17: 4 | DU17: 8 | DV17: 8 | DW17: 7 | DX17: 5 | DY17: 0 | DZ17: 32 | EB17: 1420700 | EC17: J MHC MEDIO OXF | ED17: Ventas | EF17: 0 | EG17: 4 | EH17: 8 | EI17: 8 | EJ17: 7 | EK17: 5 | EL17: 0 | EM17: 32 | EO17: 1420700 | EP17: J MHC MEDIO OXF | EQ17: Ventas | ES17: 0 | ET17: 4 | EU17: 8 | EV17: 8 | EW17: 7 | EX17: 5 | EY17: 0 | EZ17: 32 | FB17: 1420700 | FC17: J MHC MEDIO OXF | FD17: Ventas | FF17: 0 | FG17: 4 | FH17: 8 | FI17: 8 | FJ17: 7 | FK17: 5 | FL17: 0 | FM17: 32 | FO17: 1420700 | FP17: J MHC MEDIO OXF | FQ17: Ventas | FS17: 0 | FT17: 4 | FU17: 8 | FV17: 8 | FW17: 7 | FX17: 5 | FY17: 0 | FZ17: 32 | GB17: 1420700 | GC17: J MHC MEDIO OXF | GD17: Ventas | GF17: 0 | GG17: 4 | GH17: 8 | GI17: 8 | GJ17: 7 | GK17: 5 | GL17: 0 | GM17: 32 | GO17: 1420700 | GP17: J MHC MEDIO OXF | GQ17: Ventas | GS17: 0 | GT17: 4 | GU17: 8 | GV17: 8 | GW17: 7 | GX17: 5 | GY17: 0 | GZ17: =SUM(GS17:GY17) -> 32
A18: 1420800 | B18: Ayla | C18: 10 | D18: 29 | E18: 38 | F18: 30 | G18: 22 | H18: 15 | J18: =SUM(C18:H18) -> 144 | K18: ='CORTE 4200'!$O$142 -> -44 | M18: Girar | O18: 1420800 | P18: J MHC CINTURA F | Q18: Ventas | S18: 10 | T18: 29 | U18: 38 | V18: 30 | W18: 22 | X18: 15 | Y18: 0 | Z18: =SUM(S18:Y18) -> 144 | AB18: 1420800 | AC18: J MHC CINTURA F | AD18: Ventas | AF18: 10 | AG18: 29 | AH18: 38 | AI18: 30 | AJ18: 22 | AK18: 15 | AL18: 0 | AM18: =SUM(AF18:AL18) -> 144 | AO18: 1420800 | AP18: J MHC CINTURA F | AQ18: Ventas | AS18: 10 | AT18: 27 | AU18: 36 | AV18: 28 | AW18: 20 | AX18: 13 | AY18: 0 | AZ18: =SUM(AS18:AY18) -> 134 | BB18: 1420800 | BC18: J MHC CINTURA F | BD18: Ventas | BF18: 9 | BG18: 25 | BH18: 33 | BI18: 26 | BJ18: 19 | BK18: 12 | BL18: 0 | BM18: =SUM(BF18:BL18) -> 124 | BO18: 1420800 | BP18: J MHC CINTURA F | BQ18: Ventas | BS18: 9 | BT18: 25 | BU18: 33 | BV18: 26 | BW18: 19 | BX18: 12 | BY18: 0 | BZ18: =SUM(BS18:BY18) -> 124 | CB18: 1420800 | CC18: J MHC CINTURA F | CD18: Ventas | CF18: 7 | CG18: 22 | CH18: 30 | CI18: 23 | CJ18: 16 | CK18: 10 | CL18: 0 | CM18: =SUM(CF18:CL18) -> 108 | CO18: 1420800 | CP18: J MHC CINTURA F | CQ18: Ventas | CS18: 7 | CT18: 22 | CU18: 30 | CV18: 23 | CW18: 16 | CX18: 10 | CY18: 0 | CZ18: 108 | DB18: 1420800 | DC18: J MHC CINTURA F | DD18: Ventas | DF18: 7 | DG18: 22 | DH18: 30 | DI18: 23 | DJ18: 16 | DK18: 10 | DL18: 0 | DM18: 108 | DO18: 1420800 | DP18: J MHC CINTURA F | DQ18: Ventas | DS18: 0 | DT18: 9 | DU18: 13 | DV18: 12 | DW18: 10 | DX18: 6 | DY18: 0 | DZ18: 50 | EB18: 1420800 | EC18: J MHC CINTURA F | ED18: Ventas | EF18: 0 | EG18: 9 | EH18: 13 | EI18: 12 | EJ18: 10 | EK18: 6 | EL18: 0 | EM18: 50 | EO18: 1420800 | EP18: J MHC CINTURA F | EQ18: Ventas | ES18: 0 | ET18: 9 | EU18: 13 | EV18: 12 | EW18: 10 | EX18: 6 | EY18: 0 | EZ18: 50 | FB18: 1420800 | FC18: J MHC CINTURA F | FD18: Ventas | FF18: 0 | FG18: 9 | FH18: 13 | FI18: 12 | FJ18: 10 | FK18: 6 | FL18: 0 | FM18: 50 | FO18: 1420800 | FP18: J MHC CINTURA F | FQ18: Ventas | FS18: 0 | FT18: 9 | FU18: 13 | FV18: 12 | FW18: 10 | FX18: 6 | FY18: 0 | FZ18: 50 | GB18: 1420800 | GC18: J MHC CINTURA F | GD18: Ventas | GF18: 0 | GG18: 4 | GH18: 8 | GI18: 8 | GJ18: 7 | GK18: 5 | GL18: 0 | GM18: 32 | GO18: 1420800 | GP18: J MHC CINTURA F | GQ18: Ventas | GS18: 0 | GT18: 4 | GU18: 8 | GV18: 8 | GW18: 7 | GX18: 5 | GY18: 0 | GZ18: =SUM(GS18:GY18) -> 32
A19: 1420801 | B19: Ayla | C19: 0 | D19: 4 | E19: 8 | F19: 8 | G19: 7 | H19: 5 | J19: =SUM(C19:H19) -> 32 | K19: ='CORTE 4200'!$O$151 -> 0 | M19: Girar | O19: 1420801 | P19: J MHC CINTURA F | Q19: Ventas | S19: 0 | T19: 4 | U19: 8 | V19: 8 | W19: 7 | X19: 5 | Y19: 0 | Z19: =SUM(S19:Y19) -> 32 | AB19: 1420801 | AC19: J MHC CINTURA F | AD19: Ventas | AF19: 0 | AG19: 4 | AH19: 8 | AI19: 8 | AJ19: 7 | AK19: 5 | AL19: 0 | AM19: =SUM(AF19:AL19) -> 32 | AO19: 1420801 | AP19: J MHC CINTURA F | AQ19: Ventas | AS19: 0 | AT19: 4 | AU19: 8 | AV19: 8 | AW19: 7 | AX19: 5 | AY19: 0 | AZ19: =SUM(AS19:AY19) -> 32 | BB19: 1420801 | BC19: J MHC CINTURA F | BD19: Ventas | BF19: 0 | BG19: 4 | BH19: 8 | BI19: 8 | BJ19: 7 | BK19: 5 | BL19: 0 | BM19: =SUM(BF19:BL19) -> 32 | BO19: 1420801 | BP19: J MHC CINTURA F | BQ19: Ventas | BS19: 0 | BT19: 4 | BU19: 8 | BV19: 8 | BW19: 7 | BX19: 5 | BY19: 0 | BZ19: =SUM(BS19:BY19) -> 32 | CB19: 1420801 | CC19: J MHC CINTURA F | CD19: Ventas | CF19: 0 | CG19: 4 | CH19: 8 | CI19: 8 | CJ19: 7 | CK19: 5 | CL19: 0 | CM19: =SUM(CF19:CL19) -> 32 | CO19: 1420801 | CP19: J MHC CINTURA F | CQ19: Ventas | CS19: 0 | CT19: 4 | CU19: 8 | CV19: 8 | CW19: 7 | CX19: 5 | CY19: 0 | CZ19: 32 | DB19: 1420801 | DC19: J MHC CINTURA F | DD19: Ventas | DF19: 0 | DG19: 4 | DH19: 8 | DI19: 8 | DJ19: 7 | DK19: 5 | DL19: 0 | DM19: 32 | DO19: 1420801 | DP19: J MHC CINTURA F | DQ19: Ventas | DS19: 0 | DT19: 4 | DU19: 8 | DV19: 8 | DW19: 7 | DX19: 5 | DY19: 0 | DZ19: 32 | EB19: 1420801 | EC19: J MHC CINTURA F | ED19: Ventas | EF19: 0 | EG19: 4 | EH19: 8 | EI19: 8 | EJ19: 7 | EK19: 5 | EL19: 0 | EM19: 32 | EO19: 1420801 | EP19: J MHC CINTURA F | EQ19: Ventas | ES19: 0 | ET19: 4 | EU19: 8 | EV19: 8 | EW19: 7 | EX19: 5 | EY19: 0 | EZ19: 32 | FB19: 1420801 | FC19: J MHC CINTURA F | FD19: Ventas | FF19: 0 | FG19: 4 | FH19: 8 | FI19: 8 | FJ19: 7 | FK19: 5 | FL19: 0 | FM19: 32 | FO19: 1420801 | FP19: J MHC CINTURA F | FQ19: Ventas | FS19: 0 | FT19: 4 | FU19: 8 | FV19: 8 | FW19: 7 | FX19: 5 | FY19: 0 | FZ19: 32 | GB19: 1420801 | GC19: J MHC CINTURA F | GD19: Ventas | GF19: 0 | GG19: 4 | GH19: 8 | GI19: 8 | GJ19: 7 | GK19: 5 | GL19: 0 | GM19: 32 | GO19: 1420801 | GP19: J MHC CINTURA F | GQ19: Ventas | GS19: 0 | GT19: 4 | GU19: 8 | GV19: 8 | GW19: 7 | GX19: 5 | GY19: 0 | GZ19: =SUM(GS19:GY19) -> 32
A20: 1420802 | B20: Ayla | C20: 0 | D20: 4 | E20: 8 | F20: 8 | G20: 7 | H20: 5 | J20: =SUM(C20:H20) -> 32 | K20: ='CORTE 4200'!$O$160 -> 0 | M20: Girar | O20: 1420802 | P20: J MHC CINTURA F | Q20: Ventas | S20: 0 | T20: 4 | U20: 8 | V20: 8 | W20: 7 | X20: 5 | Y20: 0 | Z20: =SUM(S20:Y20) -> 32 | AB20: 1420802 | AC20: J MHC CINTURA F | AD20: Ventas | AF20: 0 | AG20: 4 | AH20: 8 | AI20: 8 | AJ20: 7 | AK20: 5 | AL20: 0 | AM20: =SUM(AF20:AL20) -> 32 | AO20: 1420802 | AP20: J MHC CINTURA F | AQ20: Ventas | AS20: 0 | AT20: 4 | AU20: 8 | AV20: 8 | AW20: 7 | AX20: 5 | AY20: 0 | AZ20: =SUM(AS20:AY20) -> 32 | BB20: 1420802 | BC20: J MHC CINTURA F | BD20: Ventas | BF20: 0 | BG20: 4 | BH20: 8 | BI20: 8 | BJ20: 7 | BK20: 5 | BL20: 0 | BM20: =SUM(BF20:BL20) -> 32 | BO20: 1420802 | BP20: J MHC CINTURA F | BQ20: Ventas | BS20: 0 | BT20: 4 | BU20: 8 | BV20: 8 | BW20: 7 | BX20: 5 | BY20: 0 | BZ20: =SUM(BS20:BY20) -> 32 | CB20: 1420802 | CC20: J MHC CINTURA F | CD20: Ventas | CF20: 0 | CG20: 4 | CH20: 8 | CI20: 8 | CJ20: 7 | CK20: 5 | CL20: 0 | CM20: =SUM(CF20:CL20) -> 32 | CO20: 1420802 | CP20: J MHC CINTURA F | CQ20: Ventas | CS20: 0 | CT20: 4 | CU20: 8 | CV20: 8 | CW20: 7 | CX20: 5 | CY20: 0 | CZ20: 32 | DB20: 1420802 | DC20: J MHC CINTURA F | DD20: Ventas | DF20: 0 | DG20: 4 | DH20: 8 | DI20: 8 | DJ20: 7 | DK20: 5 | DL20: 0 | DM20: 32 | DO20: 1420802 | DP20: J MHC CINTURA F | DQ20: Ventas | DS20: 0 | DT20: 4 | DU20: 8 | DV20: 8 | DW20: 7 | DX20: 5 | DY20: 0 | DZ20: 32 | EB20: 1420802 | EC20: J MHC CINTURA F | ED20: Ventas | EF20: 0 | EG20: 4 | EH20: 8 | EI20: 8 | EJ20: 7 | EK20: 5 | EL20: 0 | EM20: 32 | EO20: 1420802 | EP20: J MHC CINTURA F | EQ20: Ventas | ES20: 0 | ET20: 4 | EU20: 8 | EV20: 8 | EW20: 7 | EX20: 5 | EY20: 0 | EZ20: 32 | FB20: 1420802 | FC20: J MHC CINTURA F | FD20: Ventas | FF20: 0 | FG20: 4 | FH20: 8 | FI20: 8 | FJ20: 7 | FK20: 5 | FL20: 0 | FM20: 32 | FO20: 1420802 | FP20: J MHC CINTURA F | FQ20: Ventas | FS20: 0 | FT20: 4 | FU20: 8 | FV20: 8 | FW20: 7 | FX20: 5 | FY20: 0 | FZ20: 32 | GB20: 1420802 | GC20: J MHC CINTURA F | GD20: Ventas | GF20: 0 | GG20: 4 | GH20: 8 | GI20: 8 | GJ20: 7 | GK20: 5 | GL20: 0 | GM20: 32 | GO20: 1420802 | GP20: J MHC CINTURA F | GQ20: Ventas | GS20: 0 | GT20: 4 | GU20: 8 | GV20: 8 | GW20: 7 | GX20: 5 | GY20: 0 | GZ20: =SUM(GS20:GY20) -> 32
A21: 1420900 | B21: B2868-V3 | C21: 55 | D21: 109 | E21: 112 | F21: 103 | G21: 78 | H21: 55 | J21: =SUM(C21:H21) -> 512 | K21: ='CORTE 4200'!$O$169 -> 10 | O21: 1420900 | P21: J MHC MEDIO PIT | Q21: Ventas | S21: 55 | T21: 109 | U21: 112 | V21: 103 | W21: 78 | X21: 55 | Y21: 0 | Z21: =SUM(S21:Y21) -> 512 | AB21: 1420900 | AC21: J MHC MEDIO PIT | AD21: Ventas | AF21: 54 | AG21: 107 | AH21: 110 | AI21: 101 | AJ21: 77 | AK21: 54 | AL21: 0 | AM21: =SUM(AF21:AL21) -> 503 | AO21: 1420900 | AP21: J MHC MEDIO PIT | AQ21: Ventas | AS21: 54 | AT21: 107 | AU21: 110 | AV21: 101 | AW21: 77 | AX21: 54 | AY21: 0 | AZ21: =SUM(AS21:AY21) -> 503 | BB21: 1420900 | BC21: J MHC MEDIO PIT | BD21: Ventas | BF21: 54 | BG21: 107 | BH21: 110 | BI21: 101 | BJ21: 77 | BK21: 54 | BL21: 0 | BM21: =SUM(BF21:BL21) -> 503 | BO21: 1420900 | BP21: J MHC MEDIO PIT | BQ21: Ventas | BS21: 54 | BT21: 107 | BU21: 110 | BV21: 101 | BW21: 77 | BX21: 54 | BY21: 0 | BZ21: =SUM(BS21:BY21) -> 503 | CB21: 1420900 | CC21: J MHC MEDIO PIT | CD21: Ventas | CF21: 52 | CG21: 104 | CH21: 107 | CI21: 98 | CJ21: 74 | CK21: 52 | CL21: 0 | CM21: =SUM(CF21:CL21) -> 487 | CO21: 1420900 | CP21: J MHC MEDIO PIT | CQ21: Ventas | CS21: 52 | CT21: 103 | CU21: 106 | CV21: 97 | CW21: 73 | CX21: 52 | CY21: 0 | CZ21: 483 | DB21: 1420900 | DC21: J MHC MEDIO PIT | DD21: Ventas | DF21: 47 | DG21: 92 | DH21: 94 | DI21: 86 | DJ21: 63 | DK21: 46 | DL21: 0 | DM21: 428 | DO21: 1420900 | DP21: J MHC MEDIO PIT | DQ21: Ventas | DS21: 46 | DT21: 88 | DU21: 92 | DV21: 85 | DW21: 62 | DX21: 46 | DY21: 0 | DZ21: 419 | EB21: 1420900 | EC21: J MHC MEDIO PIT | ED21: Ventas | EF21: 46 | EG21: 87 | EH21: 91 | EI21: 84 | EJ21: 62 | EK21: 46 | EL21: 0 | EM21: 416 | EO21: 1420900 | EP21: J MHC MEDIO PIT | EQ21: Ventas | ES21: 42 | ET21: 82 | EU21: 86 | EV21: 80 | EW21: 59 | EX21: 44 | EY21: 0 | EZ21: 393 | FB21: 1420900 | FC21: J MHC MEDIO PIT | FD21: Ventas | FF21: 36 | FG21: 69 | FH21: 73 | FI21: 67 | FJ21: 48 | FK21: 38 | FL21: 0 | FM21: 331 | FO21: 1420900 | FP21: J MHC MEDIO PIT | FQ21: Ventas | FS21: 36 | FT21: 69 | FU21: 73 | FV21: 67 | FW21: 48 | FX21: 38 | FY21: 0 | FZ21: 331 | GB21: 1420900 | GC21: J MHC MEDIO PIT | GD21: Ventas | GF21: 22 | GG21: 32 | GH21: 33 | GI21: 30 | GJ21: 23 | GK21: 16 | GL21: 0 | GM21: 156 | GO21: 1420900 | GP21: J MHC MEDIO PIT | GQ21: Ventas | GS21: 20 | GT21: 30 | GU21: 30 | GV21: 27 | GW21: 21 | GX21: 14 | GY21: 0 | GZ21: =SUM(GS21:GY21) -> 142
A22: 1421000 | B22: Ayla | C22: 7 | D22: 26 | E22: 30 | F22: 29 | G22: 21 | H22: 16 | J22: =SUM(C22:H22) -> 129 | K22: ='CORTE 4200'!$O$178 -> -20 | M22: Girar | O22: 1421000 | P22: J MHC MEDIO OXF | Q22: Ventas | S22: 7 | T22: 26 | U22: 30 | V22: 29 | W22: 21 | X22: 16 | Y22: 0 | Z22: =SUM(S22:Y22) -> 129 | AB22: 1421000 | AC22: J MHC MEDIO OXF | AD22: Ventas | AF22: 9 | AG22: 32 | AH22: 34 | AI22: 32 | AJ22: 22 | AK22: 16 | AL22: 0 | AM22: =SUM(AF22:AL22) -> 145 | AO22: 1421000 | AP22: J MHC MEDIO OXF | AQ22: Ventas | AS22: 9 | AT22: 32 | AU22: 34 | AV22: 32 | AW22: 22 | AX22: 16 | AY22: 0 | AZ22: =SUM(AS22:AY22) -> 145 | BB22: 1421000 | BC22: J MHC MEDIO OXF | BD22: Ventas | BF22: 9 | BG22: 32 | BH22: 34 | BI22: 32 | BJ22: 22 | BK22: 16 | BL22: 0 | BM22: =SUM(BF22:BL22) -> 145 | BO22: 1421000 | BP22: J MHC MEDIO OXF | BQ22: Ventas | BS22: 9 | BT22: 32 | BU22: 34 | BV22: 32 | BW22: 22 | BX22: 16 | BY22: 0 | BZ22: =SUM(BS22:BY22) -> 145 | CB22: 1421000 | CC22: J MHC MEDIO OXF | CD22: Ventas | CF22: 9 | CG22: 32 | CH22: 34 | CI22: 32 | CJ22: 22 | CK22: 16 | CL22: 0 | CM22: =SUM(CF22:CL22) -> 145 | CO22: 1421000 | CP22: J MHC MEDIO OXF | CQ22: Ventas | CS22: 9 | CT22: 32 | CU22: 34 | CV22: 32 | CW22: 22 | CX22: 16 | CY22: 0 | CZ22: 145 | DB22: 1421000 | DC22: J MHC MEDIO OXF | DD22: Ventas | DF22: 9 | DG22: 32 | DH22: 34 | DI22: 32 | DJ22: 22 | DK22: 16 | DL22: 0 | DM22: 145 | DO22: 1421000 | DP22: J MHC MEDIO OXF | DQ22: Ventas | DS22: 9 | DT22: 32 | DU22: 34 | DV22: 32 | DW22: 22 | DX22: 16 | DY22: 0 | DZ22: 145 | EB22: 1421000 | EC22: J MHC MEDIO OXF | ED22: Ventas | EF22: 7 | EG22: 26 | EH22: 30 | EI22: 29 | EJ22: 21 | EK22: 16 | EL22: 0 | EM22: 129 | EO22: 1421000 | EP22: J MHC MEDIO OXF | EQ22: Ventas | ES22: 7 | ET22: 26 | EU22: 30 | EV22: 29 | EW22: 21 | EX22: 16 | EY22: 0 | EZ22: 129 | FB22: 1421000 | FC22: J MHC MEDIO OXF | FD22: Ventas | FF22: 7 | FG22: 26 | FH22: 30 | FI22: 29 | FJ22: 21 | FK22: 16 | FL22: 0 | FM22: 129 | FO22: 1421000 | FP22: J MHC MEDIO OXF | FQ22: Ventas | FS22: 5 | FT22: 20 | FU22: 24 | FV22: 23 | FW22: 17 | FX22: 12 | FY22: 0 | FZ22: 101 | GB22: 1421000 | GC22: J MHC MEDIO OXF | GD22: Ventas | GF22: 2 | GG22: 11 | GH22: 15 | GI22: 14 | GJ22: 11 | GK22: 6 | GL22: 0 | GM22: 59 | GO22: 1421000 | GP22: J MHC MEDIO OXF | GQ22: Ventas | GS22: 2 | GT22: 11 | GU22: 15 | GV22: 14 | GW22: 11 | GX22: 6 | GY22: 0 | GZ22: =SUM(GS22:GY22) -> 59
A23: 1421001 | B23: Ayla | C23: 5 | D23: 14 | E23: 15 | F23: 12 | G23: 8 | H23: 4 | J23: =SUM(C23:H23) -> 58 | K23: ='CORTE 4200'!$O$187 -> -23 | M23: Girar | O23: 1421001 | P23: J MHC MEDIO REC | Q23: Ventas | S23: 5 | T23: 14 | U23: 15 | V23: 12 | W23: 8 | X23: 4 | Y23: 0 | Z23: =SUM(S23:Y23) -> 58 | AB23: 1421001 | AC23: J MHC MEDIO REC | AD23: Ventas | AF23: 8 | AG23: 21 | AH23: 22 | AI23: 15 | AJ23: 10 | AK23: 5 | AL23: 0 | AM23: =SUM(AF23:AL23) -> 81 | AO23: 1421001 | AP23: J MHC MEDIO REC | AQ23: Ventas | AS23: 8 | AT23: 21 | AU23: 22 | AV23: 15 | AW23: 10 | AX23: 5 | AY23: 0 | AZ23: =SUM(AS23:AY23) -> 81 | BB23: 1421001 | BC23: J MHC MEDIO REC | BD23: Ventas | BF23: 8 | BG23: 21 | BH23: 22 | BI23: 15 | BJ23: 10 | BK23: 5 | BL23: 0 | BM23: =SUM(BF23:BL23) -> 81 | BO23: 1421001 | BP23: J MHC MEDIO REC | BQ23: Ventas | BS23: 6 | BT23: 18 | BU23: 19 | BV23: 13 | BW23: 9 | BX23: 5 | BY23: 0 | BZ23: =SUM(BS23:BY23) -> 70 | CB23: 1421001 | CC23: J MHC MEDIO REC | CD23: Ventas | CF23: 6 | CG23: 18 | CH23: 19 | CI23: 13 | CJ23: 9 | CK23: 5 | CL23: 0 | CM23: =SUM(CF23:CL23) -> 70 | CO23: 1421001 | CP23: J MHC MEDIO REC | CQ23: Ventas | CS23: 6 | CT23: 18 | CU23: 19 | CV23: 13 | CW23: 9 | CX23: 5 | CY23: 0 | CZ23: 70 | DB23: 1421001 | DC23: J MHC MEDIO REC | DD23: Ventas | DF23: 6 | DG23: 18 | DH23: 19 | DI23: 13 | DJ23: 9 | DK23: 5 | DL23: 0 | DM23: 70 | DO23: 1421001 | DP23: J MHC MEDIO REC | DQ23: Ventas | DS23: 6 | DT23: 18 | DU23: 19 | DV23: 13 | DW23: 9 | DX23: 5 | DY23: 0 | DZ23: 70 | EB23: 1421001 | EC23: J MHC MEDIO REC | ED23: Ventas | EF23: 3 | EG23: 11 | EH23: 12 | EI23: 10 | EJ23: 7 | EK23: 4 | EL23: 0 | EM23: 47 | EO23: 1421001 | EP23: J MHC MEDIO REC | EQ23: Ventas | ES23: 3 | ET23: 11 | EU23: 12 | EV23: 10 | EW23: 7 | EX23: 4 | EY23: 0 | EZ23: 47 | FB23: 1421001 | FC23: J MHC MEDIO REC | FD23: Ventas | FF23: 1 | FG23: 8 | FH23: 9 | FI23: 7 | FJ23: 5 | FK23: 2 | FL23: 0 | FM23: 32 | FO23: 1421001 | FP23: J MHC MEDIO REC | FQ23: Ventas | FS23: 1 | FT23: 8 | FU23: 9 | FV23: 7 | FW23: 5 | FX23: 2 | FY23: 0 | FZ23: 32 | GB23: 1421001 | GC23: J MHC MEDIO REC | GD23: Ventas | GF23: 1 | GG23: 8 | GH23: 9 | GI23: 7 | GJ23: 5 | GK23: 2 | GL23: 0 | GM23: 32 | GO23: 1421001 | GP23: J MHC MEDIO REC | GQ23: Ventas | GS23: 0 | GT23: 5 | GU23: 5 | GV23: 4 | GW23: 3 | GX23: 1 | GY23: 0 | GZ23: =SUM(GS23:GY23) -> 18
A24: 1421100 | B24: Ayla | C24: 11 | D24: 21 | E24: 29 | F24: 25 | G24: 20 | H24: 11 | J24: =SUM(C24:H24) -> 117 | K24: ='CORTE 4200'!$O$196 -> -110 | O24: 1421100 | P24: J MHC CINTURA F | Q24: Ventas | S24: 11 | T24: 21 | U24: 29 | V24: 25 | W24: 20 | X24: 11 | Y24: 0 | Z24: =SUM(S24:Y24) -> 117 | AB24: 1421100 | AC24: J MHC CINTURA F | AD24: Ventas | AF24: 11 | AG24: 21 | AH24: 29 | AI24: 25 | AJ24: 20 | AK24: 11 | AL24: 0 | AM24: =SUM(AF24:AL24) -> 117 | AO24: 1421100 | AP24: J MHC CINTURA F | AQ24: Ventas | AS24: 11 | AT24: 21 | AU24: 29 | AV24: 25 | AW24: 20 | AX24: 11 | AY24: 0 | AZ24: =SUM(AS24:AY24) -> 117 | BB24: 1421100 | BC24: J MHC CINTURA F | BD24: Ventas | BF24: 11 | BG24: 21 | BH24: 29 | BI24: 25 | BJ24: 20 | BK24: 11 | BL24: 0 | BM24: =SUM(BF24:BL24) -> 117 | BO24: 1421100 | BP24: J MHC CINTURA F | BQ24: Ventas | BS24: 11 | BT24: 21 | BU24: 29 | BV24: 25 | BW24: 20 | BX24: 11 | BY24: 0 | BZ24: =SUM(BS24:BY24) -> 117 | CB24: 1421100 | CC24: J MHC CINTURA F | CD24: Ventas | CF24: 11 | CG24: 21 | CH24: 29 | CI24: 25 | CJ24: 20 | CK24: 11 | CL24: 0 | CM24: =SUM(CF24:CL24) -> 117 | CO24: 1421100 | CP24: J MHC CINTURA F | CQ24: Ventas | CS24: 11 | CT24: 21 | CU24: 29 | CV24: 25 | CW24: 20 | CX24: 11 | CY24: 0 | CZ24: 117 | DB24: 1421100 | DC24: J MHC CINTURA F | DD24: Ventas | DF24: 9 | DG24: 17 | DH24: 24 | DI24: 21 | DJ24: 17 | DK24: 10 | DL24: 0 | DM24: 98 | DO24: 1421100 | DP24: J MHC CINTURA F | DQ24: Ventas | DS24: 9 | DT24: 17 | DU24: 24 | DV24: 21 | DW24: 17 | DX24: 10 | DY24: 0 | DZ24: 98 | EB24: 1421100 | EC24: J MHC CINTURA F | ED24: Ventas | EF24: 9 | EG24: 17 | EH24: 24 | EI24: 21 | EJ24: 17 | EK24: 10 | EL24: 0 | EM24: 98 | EO24: 1421100 | EP24: J MHC CINTURA F | EQ24: Ventas | ES24: 9 | ET24: 17 | EU24: 24 | EV24: 21 | EW24: 17 | EX24: 10 | EY24: 0 | EZ24: 98 | FB24: 1421100 | FC24: J MHC CINTURA F | FD24: Ventas | FF24: 6 | FG24: 12 | FH24: 19 | FI24: 16 | FJ24: 12 | FK24: 8 | FL24: 0 | FM24: 73 | FO24: 1421100 | FP24: J MHC CINTURA F | FQ24: Ventas | FS24: 6 | FT24: 12 | FU24: 19 | FV24: 16 | FW24: 12 | FX24: 8 | FY24: 0 | FZ24: 73 | GB24: 1421100 | GC24: J MHC CINTURA F | GD24: Ventas | GF24: 3 | GG24: 9 | GH24: 15 | GI24: 14 | GJ24: 11 | GK24: 8 | GL24: 0 | GM24: 60 | GO24: 1421100 | GP24: J MHC CINTURA F | GQ24: Ventas | GS24: 0 | GT24: 4 | GU24: 8 | GV24: 8 | GW24: 7 | GX24: 5 | GY24: 0 | GZ24: =SUM(GS24:GY24) -> 32
A25: 1421101 | B25: Ayla | C25: 19 | D25: 53 | E25: 57 | F25: 54 | G25: 36 | H25: 34 | J25: =SUM(C25:H25) -> 253 | K25: ='CORTE 4200'!$O$205 -> 34 | O25: 1421101 | P25: J MHC CINTURA F | Q25: Ventas | S25: 19 | T25: 53 | U25: 57 | V25: 54 | W25: 36 | X25: 34 | Y25: 0 | Z25: =SUM(S25:Y25) -> 253 | AB25: 1421101 | AC25: J MHC CINTURA F | AD25: Ventas | AF25: 19 | AG25: 53 | AH25: 57 | AI25: 54 | AJ25: 36 | AK25: 34 | AL25: 0 | AM25: =SUM(AF25:AL25) -> 253 | AO25: 1421101 | AP25: J MHC CINTURA F | AQ25: Ventas | AS25: 16 | AT25: 48 | AU25: 52 | AV25: 50 | AW25: 32 | AX25: 30 | AY25: 0 | AZ25: =SUM(AS25:AY25) -> 228 | BB25: 1421101 | BC25: J MHC CINTURA F | BD25: Ventas | BF25: 16 | BG25: 48 | BH25: 52 | BI25: 50 | BJ25: 32 | BK25: 30 | BL25: 0 | BM25: =SUM(BF25:BL25) -> 228 | BO25: 1421101 | BP25: J MHC CINTURA F | BQ25: Ventas | BS25: 16 | BT25: 48 | BU25: 52 | BV25: 50 | BW25: 32 | BX25: 30 | BY25: 0 | BZ25: =SUM(BS25:BY25) -> 228 | CB25: 1421101 | CC25: J MHC CINTURA F | CD25: Ventas | CF25: 15 | CG25: 46 | CH25: 50 | CI25: 48 | CJ25: 31 | CK25: 29 | CL25: 0 | CM25: =SUM(CF25:CL25) -> 219 | CO25: 1421101 | CP25: J MHC CINTURA F | CQ25: Ventas | CS25: 15 | CT25: 46 | CU25: 50 | CV25: 48 | CW25: 31 | CX25: 29 | CY25: 0 | CZ25: 219 | DB25: 1421101 | DC25: J MHC CINTURA F | DD25: Ventas | DF25: 15 | DG25: 46 | DH25: 50 | DI25: 48 | DJ25: 31 | DK25: 29 | DL25: 0 | DM25: 219 | DO25: 1421101 | DP25: J MHC CINTURA F | DQ25: Ventas | DS25: 12 | DT25: 41 | DU25: 45 | DV25: 45 | DW25: 31 | DX25: 29 | DY25: 0 | DZ25: 203 | EB25: 1421101 | EC25: J MHC CINTURA F | ED25: Ventas | EF25: 12 | EG25: 40 | EH25: 44 | EI25: 44 | EJ25: 31 | EK25: 29 | EL25: 0 | EM25: 200 | EO25: 1421101 | EP25: J MHC CINTURA F | EQ25: Ventas | ES25: 12 | ET25: 40 | EU25: 44 | EV25: 44 | EW25: 31 | EX25: 29 | EY25: 0 | EZ25: 200 | FB25: 1421101 | FC25: J MHC CINTURA F | FD25: Ventas | FF25: 12 | FG25: 40 | FH25: 44 | FI25: 44 | FJ25: 31 | FK25: 29 | FL25: 0 | FM25: 200 | FO25: 1421101 | FP25: J MHC CINTURA F | FQ25: Ventas | FS25: 10 | FT25: 34 | FU25: 38 | FV25: 38 | FW25: 27 | FX25: 25 | FY25: 0 | FZ25: 172 | GB25: 1421101 | GC25: J MHC CINTURA F | GD25: Ventas | GF25: 0 | GG25: 4 | GH25: 8 | GI25: 8 | GJ25: 7 | GK25: 5 | GL25: 0 | GM25: 32 | GO25: 1421101 | GP25: J MHC CINTURA F | GQ25: Ventas | GS25: 0 | GT25: 4 | GU25: 8 | GV25: 8 | GW25: 7 | GX25: 5 | GY25: 0 | GZ25: =SUM(GS25:GY25) -> 32
A26: 1421200 | B26: Blain Light | C26: 2 | D26: 3 | E26: 3 | F26: 3 | G26: 2 | H26: 1 | J26: =SUM(C26:H26) -> 14 | K26: ='CORTE 4200'!$O$214 -> 14 | O26: 1421200 | P26: J MHC CINTURA P | Q26: Ventas | S26: 2 | T26: 3 | U26: 3 | V26: 3 | W26: 2 | X26: 1 | Y26: 0 | Z26: =SUM(S26:Y26) -> 14 | AB26: 1421200 | AC26: J MHC CINTURA P | AD26: Ventas | AF26: 2 | AG26: 3 | AH26: 3 | AI26: 3 | AJ26: 2 | AK26: 1 | AL26: 0 | AM26: =SUM(AF26:AL26) -> 14 | AO26: 1421200 | AP26: J MHC CINTURA P | AQ26: Ventas | AS26: 2 | AT26: 3 | AU26: 3 | AV26: 3 | AW26: 2 | AX26: 1 | AY26: 0 | AZ26: =SUM(AS26:AY26) -> 14 | BB26: 1421200 | BC26: J MHC CINTURA P | BD26: Ventas | BF26: 2 | BG26: 3 | BH26: 3 | BI26: 3 | BJ26: 2 | BK26: 1 | BL26: 0 | BM26: =SUM(BF26:BL26) -> 14 | BO26: 1421200 | BP26: J MHC CINTURA P | BQ26: Ventas | BS26: 2 | BT26: 3 | BU26: 3 | BV26: 3 | BW26: 2 | BX26: 1 | BY26: 0 | BZ26: =SUM(BS26:BY26) -> 14 | CB26: 1421200 | CC26: J MHC CINTURA P | CD26: Ventas | CF26: 2 | CG26: 3 | CH26: 3 | CI26: 3 | CJ26: 2 | CK26: 1 | CL26: 0 | CM26: =SUM(CF26:CL26) -> 14 | CO26: 1421200 | CP26: J MHC CINTURA P | CQ26: Ventas | CS26: 2 | CT26: 3 | CU26: 3 | CV26: 3 | CW26: 2 | CX26: 1 | CY26: 0 | CZ26: 14 | DB26: 1421200 | DC26: J MHC CINTURA P | DD26: Ventas | DF26: 2 | DG26: 3 | DH26: 3 | DI26: 3 | DJ26: 2 | DK26: 1 | DL26: 0 | DM26: 14 | DO26: 1421200 | DP26: J MHC CINTURA P | DQ26: Ventas | DS26: 2 | DT26: 3 | DU26: 3 | DV26: 3 | DW26: 2 | DX26: 1 | DY26: 0 | DZ26: 14 | EB26: 1421200 | EC26: J MHC CINTURA P | ED26: Ventas | EF26: 2 | EG26: 3 | EH26: 3 | EI26: 3 | EJ26: 2 | EK26: 1 | EL26: 0 | EM26: 14 | EO26: 1421300 | EP26: J MHC CINTURA O | EQ26: Ventas | ES26: 15 | ET26: 45 | EU26: 51 | EV26: 50 | EW26: 36 | EX26: 32 | EY26: 0 | EZ26: 229 | GO26: 4213-00
A27: 1421300 | B27: B2868-V3 | C27: 15 | D27: 45 | E27: 51 | F27: 50 | G27: 36 | H27: 32 | J27: =SUM(C27:H27) -> 229 | K27: ='CORTE 4200'!$O$223 -> 29 | O27: 1421300 | P27: J MHC CINTURA O | Q27: Ventas | S27: 15 | T27: 45 | U27: 51 | V27: 50 | W27: 36 | X27: 32 | Y27: 0 | Z27: =SUM(S27:Y27) -> 229 | AB27: 1421300 | AC27: J MHC CINTURA O | AD27: Ventas | AF27: 15 | AG27: 45 | AH27: 51 | AI27: 50 | AJ27: 36 | AK27: 32 | AL27: 0 | AM27: =SUM(AF27:AL27) -> 229 | AO27: 1421300 | AP27: J MHC CINTURA O | AQ27: Ventas | AS27: 15 | AT27: 45 | AU27: 51 | AV27: 50 | AW27: 36 | AX27: 32 | AY27: 0 | AZ27: =SUM(AS27:AY27) -> 229 | BB27: 1421300 | BC27: J MHC CINTURA O | BD27: Ventas | BF27: 15 | BG27: 45 | BH27: 51 | BI27: 50 | BJ27: 36 | BK27: 32 | BL27: 0 | BM27: =SUM(BF27:BL27) -> 229 | BO27: 1421300 | BP27: J MHC CINTURA O | BQ27: Ventas | BS27: 15 | BT27: 45 | BU27: 51 | BV27: 50 | BW27: 36 | BX27: 32 | BY27: 0 | BZ27: =SUM(BS27:BY27) -> 229 | CB27: 1421300 | CC27: J MHC CINTURA O | CD27: Ventas | CF27: 15 | CG27: 45 | CH27: 51 | CI27: 50 | CJ27: 36 | CK27: 32 | CL27: 0 | CM27: =SUM(CF27:CL27) -> 229 | CO27: 1421300 | CP27: J MHC CINTURA O | CQ27: Ventas | CS27: 15 | CT27: 45 | CU27: 51 | CV27: 50 | CW27: 36 | CX27: 32 | CY27: 0 | CZ27: 229 | DB27: 1421300 | DC27: J MHC CINTURA O | DD27: Ventas | DF27: 15 | DG27: 45 | DH27: 51 | DI27: 50 | DJ27: 36 | DK27: 32 | DL27: 0 | DM27: 229 | DO27: 1421300 | DP27: J MHC CINTURA O | DQ27: Ventas | DS27: 15 | DT27: 45 | DU27: 51 | DV27: 50 | DW27: 36 | DX27: 32 | DY27: 0 | DZ27: 229 | EB27: 1421300 | EC27: J MHC CINTURA O | ED27: Ventas | EF27: 15 | EG27: 45 | EH27: 51 | EI27: 50 | EJ27: 36 | EK27: 32 | EL27: 0 | EM27: 229 | EO27: 1421301 | EP27: J MHC CINTURA O | EQ27: Ventas | ES27: 20 | ET27: 36 | EU27: 39 | EV27: 39 | EW27: 28 | EX27: 24 | EY27: 0 | EZ27: 186 | GO27: 4213-01
A28: 1421301 | B28: B2868-V3 | C28: 31 | D28: 57 | E28: 64 | F28: 59 | G28: 40 | H28: 31 | J28: =SUM(C28:H28) -> 282 | K28: ='CORTE 4200'!$O$232 -> -18 | O28: 1421301 | P28: J MHC CINTURA O | Q28: Ventas | S28: 31 | T28: 57 | U28: 64 | V28: 59 | W28: 40 | X28: 31 | Y28: 0 | Z28: =SUM(S28:Y28) -> 282 | AB28: 1421301 | AC28: J MHC CINTURA O | AD28: Ventas | AF28: 31 | AG28: 57 | AH28: 64 | AI28: 59 | AJ28: 40 | AK28: 31 | AL28: 0 | AM28: =SUM(AF28:AL28) -> 282 | AO28: 1421301 | AP28: J MHC CINTURA O | AQ28: Ventas | AS28: 31 | AT28: 57 | AU28: 64 | AV28: 59 | AW28: 40 | AX28: 31 | AY28: 0 | AZ28: =SUM(AS28:AY28) -> 282 | BB28: 1421301 | BC28: J MHC CINTURA O | BD28: Ventas | BF28: 30 | BG28: 54 | BH28: 61 | BI28: 57 | BJ28: 39 | BK28: 31 | BL28: 0 | BM28: =SUM(BF28:BL28) -> 272 | BO28: 1421301 | BP28: J MHC CINTURA O | BQ28: Ventas | BS28: 30 | BT28: 54 | BU28: 61 | BV28: 57 | BW28: 39 | BX28: 31 | BY28: 0 | BZ28: =SUM(BS28:BY28) -> 272 | CB28: 1421301 | CC28: J MHC CINTURA O | CD28: Ventas | CF28: 30 | CG28: 54 | CH28: 61 | CI28: 57 | CJ28: 39 | CK28: 31 | CL28: 0 | CM28: =SUM(CF28:CL28) -> 272 | CO28: 1421301 | CP28: J MHC CINTURA O | CQ28: Ventas | CS28: 26 | CT28: 48 | CU28: 55 | CV28: 52 | CW28: 36 | CX28: 30 | CY28: 0 | CZ28: 247 | DB28: 1421301 | DC28: J MHC CINTURA O | DD28: Ventas | DF28: 26 | DG28: 48 | DH28: 55 | DI28: 52 | DJ28: 36 | DK28: 30 | DL28: 0 | DM28: 247 | DO28: 1421301 | DP28: J MHC CINTURA O | DQ28: Ventas | DS28: 26 | DT28: 47 | DU28: 51 | DV28: 48 | DW28: 34 | DX28: 29 | DY28: 0 | DZ28: 235 | EB28: 1421301 | EC28: J MHC CINTURA O | ED28: Ventas | EF28: 22 | EG28: 40 | EH28: 43 | EI28: 43 | EJ28: 31 | EK28: 27 | EL28: 0 | EM28: 206 | EO28: 1421302 | EP28: J MHC CINTURA O | EQ28: Ventas | ES28: 2 | ET28: 3 | EU28: 3 | EV28: 3 | EW28: 2 | EX28: 2 | EY28: 0 | EZ28: 15 | FB28: 1421400 | FC28: J MHC CINTURA O | FD28: Ventas | FF28: 30 | FG28: 79 | FH28: 84 | FI28: 83 | FJ28: 57 | FK28: 52 | FL28: 0 | FM28: 385 | FO28: 1421400 | FP28: J MHC CINTURA O | FQ28: Ventas | FS28: 28 | FT28: 73 | FU28: 78 | FV28: 77 | FW28: 53 | FX28: 48 | FY28: 0 | FZ28: 357 | GB28: 1421400 | GC28: J MHC CINTURA O | GD28: Ventas | GF28: 10 | GG28: 19 | GH28: 24 | GI28: 23 | GJ28: 17 | GK28: 12 | GL28: 0 | GM28: 105 | GO28: 1421400 | GP28: J MHC CINTURA O | GQ28: Ventas | GS28: 8 | GT28: 17 | GU28: 21 | GV28: 20 | GW28: 15 | GX28: 10 | GY28: 0 | GZ28: =SUM(GS28:GY28) -> 91
A29: 1421302 | B29: B2868-V3 | C29: 2 | D29: 3 | E29: 3 | F29: 3 | G29: 2 | H29: 2 | J29: =SUM(C29:H29) -> 15 | K29: ='CORTE 4200'!$O$241 -> 15 | O29: 1421302 | P29: J MHC CINTURA O | Q29: Ventas | S29: 2 | T29: 3 | U29: 3 | V29: 3 | W29: 2 | X29: 2 | Y29: 0 | Z29: =SUM(S29:Y29) -> 15 | AB29: 1421302 | AC29: J MHC CINTURA O | AD29: Ventas | AF29: 2 | AG29: 3 | AH29: 3 | AI29: 3 | AJ29: 2 | AK29: 2 | AL29: 0 | AM29: =SUM(AF29:AL29) -> 15 | AO29: 1421302 | AP29: J MHC CINTURA O | AQ29: Ventas | AS29: 2 | AT29: 3 | AU29: 3 | AV29: 3 | AW29: 2 | AX29: 2 | AY29: 0 | AZ29: =SUM(AS29:AY29) -> 15 | BB29: 1421302 | BC29: J MHC CINTURA O | BD29: Ventas | BF29: 2 | BG29: 3 | BH29: 3 | BI29: 3 | BJ29: 2 | BK29: 2 | BL29: 0 | BM29: =SUM(BF29:BL29) -> 15 | BO29: 1421302 | BP29: J MHC CINTURA O | BQ29: Ventas | BS29: 2 | BT29: 3 | BU29: 3 | BV29: 3 | BW29: 2 | BX29: 2 | BY29: 0 | BZ29: =SUM(BS29:BY29) -> 15 | CB29: 1421302 | CC29: J MHC CINTURA O | CD29: Ventas | CF29: 2 | CG29: 3 | CH29: 3 | CI29: 3 | CJ29: 2 | CK29: 2 | CL29: 0 | CM29: =SUM(CF29:CL29) -> 15 | CO29: 1421302 | CP29: J MHC CINTURA O | CQ29: Ventas | CS29: 2 | CT29: 3 | CU29: 3 | CV29: 3 | CW29: 2 | CX29: 2 | CY29: 0 | CZ29: 15 | DB29: 1421302 | DC29: J MHC CINTURA O | DD29: Ventas | DF29: 2 | DG29: 3 | DH29: 3 | DI29: 3 | DJ29: 2 | DK29: 2 | DL29: 0 | DM29: 15 | DO29: 1421302 | DP29: J MHC CINTURA O | DQ29: Ventas | DS29: 2 | DT29: 3 | DU29: 3 | DV29: 3 | DW29: 2 | DX29: 2 | DY29: 0 | DZ29: 15 | EB29: 1421302 | EC29: J MHC CINTURA O | ED29: Ventas | EF29: 2 | EG29: 3 | EH29: 3 | EI29: 3 | EJ29: 2 | EK29: 2 | EL29: 0 | EM29: 15 | EO29: 1421400 | EP29: J MHC CINTURA O | EQ29: Ventas | ES29: 31 | ET29: 85 | EU29: 90 | EV29: 89 | EW29: 62 | EX29: 55 | EY29: 0 | EZ29: 412 | FB29: 1421401 | FC29: J MHC CINTURA O | FD29: Ventas | FF29: 8 | FG29: 17 | FH29: 22 | FI29: 21 | FJ29: 16 | FK29: 11 | FL29: 0 | FM29: 95 | FO29: 1421401 | FP29: J MHC CINTURA O | FQ29: Ventas | FS29: 8 | FT29: 17 | FU29: 22 | FV29: 21 | FW29: 16 | FX29: 11 | FY29: 0 | FZ29: 95 | GB29: 1421401 | GC29: J MHC CINTURA O | GD29: Ventas | GF29: 2 | GG29: 9 | GH29: 14 | GI29: 13 | GJ29: 11 | GK29: 8 | GL29: 0 | GM29: 57 | GO29: 1421401 | GP29: J MHC CINTURA O | GQ29: Ventas | GS29: 0 | GT29: 7 | GU29: 11 | GV29: 10 | GW29: 9 | GX29: 6 | GY29: 0 | GZ29: =SUM(GS29:GY29) -> 43
A30: 1421400 | B30: B2868-V3 | C30: 58 | D30: 127 | E30: 133 | F30: 131 | G30: 84 | H30: 69 | J30: =SUM(C30:H30) -> 602 | K30: ='CORTE 4200'!$O$250 -> 42 | L30: 50 | O30: 1421400 | P30: J MHC CINTURA O | Q30: Ventas | S30: 58 | T30: 127 | U30: 133 | V30: 131 | W30: 84 | X30: 69 | Y30: 0 | Z30: =SUM(S30:Y30) -> 602 | AB30: 1421400 | AC30: J MHC CINTURA O | AD30: Ventas | AF30: 58 | AG30: 127 | AH30: 133 | AI30: 131 | AJ30: 84 | AK30: 69 | AL30: 0 | AM30: =SUM(AF30:AL30) -> 602 | AO30: 1421400 | AP30: J MHC CINTURA O | AQ30: Ventas | AS30: 56 | AT30: 124 | AU30: 130 | AV30: 129 | AW30: 82 | AX30: 67 | AY30: 0 | AZ30: =SUM(AS30:AY30) -> 588 | BB30: 1421400 | BC30: J MHC CINTURA O | BD30: Ventas | BF30: 48 | BG30: 112 | BH30: 118 | BI30: 117 | BJ30: 79 | BK30: 64 | BL30: 0 | BM30: =SUM(BF30:BL30) -> 538 | BO30: 1421400 | BP30: J MHC CINTURA O | BQ30: Ventas | BS30: 48 | BT30: 112 | BU30: 118 | BV30: 117 | BW30: 79 | BX30: 64 | BY30: 0 | BZ30: =SUM(BS30:BY30) -> 538 | CB30: 1421400 | CC30: J MHC CINTURA O | CD30: Ventas | CF30: 46 | CG30: 109 | CH30: 115 | CI30: 114 | CJ30: 77 | CK30: 63 | CL30: 0 | CM30: =SUM(CF30:CL30) -> 524 | CO30: 1421400 | CP30: J MHC CINTURA O | CQ30: Ventas | CS30: 46 | CT30: 109 | CU30: 115 | CV30: 114 | CW30: 77 | CX30: 63 | CY30: 0 | CZ30: 524 | DB30: 1421400 | DC30: J MHC CINTURA O | DD30: Ventas | DF30: 43 | DG30: 104 | DH30: 108 | DI30: 105 | DJ30: 71 | DK30: 58 | DL30: 0 | DM30: 489 | DO30: 1421400 | DP30: J MHC CINTURA O | DQ30: Ventas | DS30: 40 | DT30: 100 | DU30: 104 | DV30: 101 | DW30: 69 | DX30: 58 | DY30: 0 | DZ30: 472 | EB30: 1421400 | EC30: J MHC CINTURA O | ED30: Ventas | EF30: 35 | EG30: 90 | EH30: 95 | EI30: 94 | EJ30: 65 | EK30: 57 | EL30: 0 | EM30: 436 | EO30: 1421401 | EP30: J MHC CINTURA O | EQ30: Ventas | ES30: 11 | ET30: 23 | EU30: 29 | EV30: 27 | EW30: 20 | EX30: 15 | EY30: 0 | EZ30: 125 | FB30: 1421402 | FC30: J MHC CINTURA O | FD30: Ventas | FF30: 16 | FG30: 42 | FH30: 43 | FI30: 41 | FJ30: 29 | FK30: 26 | FL30: 0 | FM30: 197 | FO30: 1421402 | FP30: J MHC CINTURA O | FQ30: Ventas | FS30: 16 | FT30: 42 | FU30: 43 | FV30: 41 | FW30: 29 | FX30: 26 | FY30: 0 | FZ30: 197 | GB30: 1421402 | GC30: J MHC CINTURA O | GD30: Ventas | GF30: 6 | GG30: 12 | GH30: 13 | GI30: 11 | GJ30: 9 | GK30: 6 | GL30: 0 | GM30: 57 | GO30: 1421402 | GP30: J MHC CINTURA O | GQ30: Ventas | GS30: 5 | GT30: 9 | GU30: 9 | GV30: 8 | GW30: 7 | GX30: 5 | GY30: 0 | GZ30: =SUM(GS30:GY30) -> 43
A31: 1421401 | B31: B2868-V3 | C31: 18 | D31: 37 | E31: 47 | F31: 40 | G31: 30 | H31: 23 | J31: =SUM(C31:H31) -> 195 | K31: ='CORTE 4200'!$O$259 -> 22 | O31: 1421401 | P31: J MHC CINTURA O | Q31: Ventas | S31: 18 | T31: 37 | U31: 47 | V31: 40 | W31: 30 | X31: 23 | Y31: 0 | Z31: =SUM(S31:Y31) -> 195 | AB31: 1421401 | AC31: J MHC CINTURA O | AD31: Ventas | AF31: 17 | AG31: 35 | AH31: 45 | AI31: 38 | AJ31: 29 | AK31: 22 | AL31: 0 | AM31: =SUM(AF31:AL31) -> 186 | AO31: 1421401 | AP31: J MHC CINTURA O | AQ31: Ventas | AS31: 17 | AT31: 33 | AU31: 43 | AV31: 36 | AW31: 27 | AX31: 20 | AY31: 0 | AZ31: =SUM(AS31:AY31) -> 176 | BB31: 1421401 | BC31: J MHC CINTURA O | BD31: Ventas | BF31: 17 | BG31: 33 | BH31: 43 | BI31: 36 | BJ31: 27 | BK31: 20 | BL31: 0 | BM31: =SUM(BF31:BL31) -> 176 | BO31: 1421401 | BP31: J MHC CINTURA O | BQ31: Ventas | BS31: 17 | BT31: 33 | BU31: 43 | BV31: 36 | BW31: 27 | BX31: 20 | BY31: 0 | BZ31: =SUM(BS31:BY31) -> 176 | CB31: 1421401 | CC31: J MHC CINTURA O | CD31: Ventas | CF31: 17 | CG31: 33 | CH31: 43 | CI31: 36 | CJ31: 27 | CK31: 20 | CL31: 0 | CM31: =SUM(CF31:CL31) -> 176 | CO31: 1421401 | CP31: J MHC CINTURA O | CQ31: Ventas | CS31: 17 | CT31: 33 | CU31: 43 | CV31: 36 | CW31: 27 | CX31: 20 | CY31: 0 | CZ31: 176 | DB31: 1421401 | DC31: J MHC CINTURA O | DD31: Ventas | DF31: 17 | DG31: 33 | DH31: 43 | DI31: 36 | DJ31: 27 | DK31: 20 | DL31: 0 | DM31: 176 | DO31: 1421401 | DP31: J MHC CINTURA O | DQ31: Ventas | DS31: 13 | DT31: 25 | DU31: 31 | DV31: 28 | DW31: 21 | DX31: 16 | DY31: 0 | DZ31: 134 | EB31: 1421401 | EC31: J MHC CINTURA O | ED31: Ventas | EF31: 13 | EG31: 25 | EH31: 31 | EI31: 28 | EJ31: 21 | EK31: 16 | EL31: 0 | EM31: 134 | EO31: 1421402 | EP31: J MHC CINTURA O | EQ31: Ventas | ES31: 16 | ET31: 42 | EU31: 43 | EV31: 41 | EW31: 29 | EX31: 26 | EY31: 0 | EZ31: 197 | FB31: 1421460 | FC31: J MHC CINTURA O | FD31: Ventas | FF31: 7 | FG31: 15 | FH31: 16 | FI31: 11 | FJ31: 7 | FK31: 4 | FL31: 0 | FM31: 60 | FO31: 1421460 | FP31: J MHC CINTURA O | FQ31: Ventas | FS31: 7 | FT31: 15 | FU31: 16 | FV31: 11 | FW31: 7 | FX31: 4 | FY31: 0 | FZ31: 60 | GB31: 1421460 | GC31: J MHC CINTURA O | GD31: Ventas | GF31: 4 | GG31: 10 | GH31: 9 | GI31: 6 | GJ31: 4 | GK31: 2 | GL31: 0 | GM31: 35 | GO31: 1421460 | GP31: J MHC CINTURA O | GQ31: Ventas | GS31: 4 | GT31: 10 | GU31: 9 | GV31: 6 | GW31: 4 | GX31: 2 | GY31: 0 | GZ31: =SUM(GS31:GY31) -> 35
A32: 1421402 | B32: B2868-V3 | C32: 20 | D32: 49 | E32: 50 | F32: 48 | G32: 35 | H32: 29 | J32: =SUM(C32:H32) -> 231 | K32: ='CORTE 4200'!$O$268 -> 6 | O32: 1421402 | P32: J MHC CINTURA O | Q32: Ventas | S32: 20 | T32: 49 | U32: 50 | V32: 48 | W32: 35 | X32: 29 | Y32: 0 | Z32: =SUM(S32:Y32) -> 231 | AB32: 1421402 | AC32: J MHC CINTURA O | AD32: Ventas | AF32: 20 | AG32: 49 | AH32: 50 | AI32: 48 | AJ32: 35 | AK32: 29 | AL32: 0 | AM32: =SUM(AF32:AL32) -> 231 | AO32: 1421402 | AP32: J MHC CINTURA O | AQ32: Ventas | AS32: 20 | AT32: 49 | AU32: 50 | AV32: 48 | AW32: 35 | AX32: 29 | AY32: 0 | AZ32: =SUM(AS32:AY32) -> 231 | BB32: 1421402 | BC32: J MHC CINTURA O | BD32: Ventas | BF32: 20 | BG32: 49 | BH32: 50 | BI32: 48 | BJ32: 35 | BK32: 29 | BL32: 0 | BM32: =SUM(BF32:BL32) -> 231 | BO32: 1421402 | BP32: J MHC CINTURA O | BQ32: Ventas | BS32: 20 | BT32: 49 | BU32: 50 | BV32: 48 | BW32: 35 | BX32: 29 | BY32: 0 | BZ32: =SUM(BS32:BY32) -> 231 | CB32: 1421402 | CC32: J MHC CINTURA O | CD32: Ventas | CF32: 20 | CG32: 49 | CH32: 50 | CI32: 48 | CJ32: 35 | CK32: 29 | CL32: 0 | CM32: =SUM(CF32:CL32) -> 231 | CO32: 1421402 | CP32: J MHC CINTURA O | CQ32: Ventas | CS32: 20 | CT32: 49 | CU32: 50 | CV32: 48 | CW32: 35 | CX32: 29 | CY32: 0 | CZ32: 231 | DB32: 1421402 | DC32: J MHC CINTURA O | DD32: Ventas | DF32: 18 | DG32: 45 | DH32: 46 | DI32: 44 | DJ32: 31 | DK32: 27 | DL32: 0 | DM32: 211 | DO32: 1421402 | DP32: J MHC CINTURA O | DQ32: Ventas | DS32: 18 | DT32: 45 | DU32: 46 | DV32: 44 | DW32: 31 | DX32: 27 | DY32: 0 | DZ32: 211 | EB32: 1421402 | EC32: J MHC CINTURA O | ED32: Ventas | EF32: 16 | EG32: 42 | EH32: 43 | EI32: 41 | EJ32: 29 | EK32: 26 | EL32: 0 | EM32: 197 | EO32: 1421460 | EP32: J MHC CINTURA O | EQ32: Ventas | ES32: 9 | ET32: 18 | EU32: 19 | EV32: 14 | EW32: 9 | EX32: 6 | EY32: 0 | EZ32: 75 | FB32: 1421600 | FC32: J MHC CINTURA P | FD32: Ventas | FF32: 0 | FG32: 5 | FH32: 5 | FI32: 4 | FJ32: 3 | FK32: 1 | FL32: 0 | FM32: 18 | FO32: 1421600 | FP32: J MHC CINTURA P | FQ32: Ventas | FS32: 0 | FT32: 5 | FU32: 5 | FV32: 4 | FW32: 3 | FX32: 1 | FY32: 0 | FZ32: 18 | GB32: 1421600 | GC32: J MHC CINTURA P | GD32: Ventas | GF32: 0 | GG32: 5 | GH32: 5 | GI32: 4 | GJ32: 3 | GK32: 1 | GL32: 0 | GM32: 18 | GO32: 1421600 | GP32: J MHC CINTURA P | GQ32: Ventas | GS32: 0 | GT32: 5 | GU32: 5 | GV32: 4 | GW32: 3 | GX32: 1 | GY32: 0 | GZ32: =SUM(GS32:GY32) -> 18
A33: 1421460 | B33: B2868-V3 | C33: 19 | D33: 30 | E33: 28 | F33: 22 | G33: 11 | H33: 6 | J33: =SUM(C33:H33) -> 116 | K33: ='CORTE 4200'!$O$277 -> 6 | O33: 1421460 | P33: J MHC CINTURA O | Q33: Ventas | S33: 19 | T33: 30 | U33: 28 | V33: 22 | W33: 11 | X33: 6 | Y33: 0 | Z33: =SUM(S33:Y33) -> 116 | AB33: 1421460 | AC33: J MHC CINTURA O | AD33: Ventas | AF33: 16 | AG33: 29 | AH33: 30 | AI33: 22 | AJ33: 12 | AK33: 7 | AL33: 0 | AM33: =SUM(AF33:AL33) -> 116 | AO33: 1421460 | AP33: J MHC CINTURA O | AQ33: Ventas | AS33: 16 | AT33: 29 | AU33: 30 | AV33: 22 | AW33: 12 | AX33: 7 | AY33: 0 | AZ33: =SUM(AS33:AY33) -> 116 | BB33: 1421460 | BC33: J MHC CINTURA O | BD33: Ventas | BF33: 16 | BG33: 29 | BH33: 30 | BI33: 22 | BJ33: 12 | BK33: 7 | BL33: 0 | BM33: =SUM(BF33:BL33) -> 116 | BO33: 1421460 | BP33: J MHC CINTURA O | BQ33: Ventas | BS33: 16 | BT33: 29 | BU33: 30 | BV33: 22 | BW33: 12 | BX33: 7 | BY33: 0 | BZ33: =SUM(BS33:BY33) -> 116 | CB33: 1421460 | CC33: J MHC CINTURA O | CD33: Ventas | CF33: 16 | CG33: 29 | CH33: 30 | CI33: 22 | CJ33: 12 | CK33: 7 | CL33: 0 | CM33: =SUM(CF33:CL33) -> 116 | CO33: 1421460 | CP33: J MHC CINTURA O | CQ33: Ventas | CS33: 16 | CT33: 29 | CU33: 30 | CV33: 22 | CW33: 12 | CX33: 7 | CY33: 0 | CZ33: 116 | DB33: 1421460 | DC33: J MHC CINTURA O | DD33: Ventas | DF33: 16 | DG33: 29 | DH33: 30 | DI33: 22 | DJ33: 12 | DK33: 7 | DL33: 0 | DM33: 116 | DO33: 1421460 | DP33: J MHC CINTURA O | DQ33: Ventas | DS33: 11 | DT33: 21 | DU33: 22 | DV33: 17 | DW33: 11 | DX33: 7 | DY33: 0 | DZ33: 89 | EB33: 1421460 | EC33: J MHC CINTURA O | ED33: Ventas | EF33: 11 | EG33: 21 | EH33: 22 | EI33: 17 | EJ33: 11 | EK33: 7 | EL33: 0 | EM33: 89 | EO33: 1421600 | EP33: J MHC CINTURA P | EQ33: Ventas | ES33: 0 | ET33: 5 | EU33: 5 | EV33: 4 | EW33: 3 | EX33: 1 | EY33: 0 | EZ33: 18 | FB33: 1421800 | FC33: J MHC CINTURA F | FD33: Ventas | FF33: 45 | FG33: 105 | FH33: 119 | FI33: 112 | FJ33: 81 | FK33: 69 | FL33: 0 | FM33: 531 | FO33: 1421800 | FP33: J MHC CINTURA F | FQ33: Ventas | FS33: 43 | FT33: 99 | FU33: 113 | FV33: 106 | FW33: 77 | FX33: 65 | FY33: 0 | FZ33: 503 | GB33: 1421800 | GC33: J MHC CINTURA F | GD33: Ventas | GF33: 21 | GG33: 36 | GH33: 44 | GI33: 39 | GJ33: 31 | GK33: 23 | GL33: 0 | GM33: 194 | GO33: 1421800 | GP33: J MHC CINTURA F | GQ33: Ventas | GS33: 18 | GT33: 31 | GU33: 37 | GV33: 33 | GW33: 27 | GX33: 20 | GY33: 0 | GZ33: =SUM(GS33:GY33) -> 166
A34: 1421600 | B34: Missy Plus | C34: 0 | D34: 5 | E34: 5 | F34: 4 | G34: 3 | H34: 1 | J34: =SUM(C34:H34) -> 18 | K34: ='CORTE 4200'!$O$286 -> 18 | O34: 1421600 | P34: J MHC CINTURA P | Q34: Ventas | S34: 0 | T34: 5 | U34: 5 | V34: 4 | W34: 3 | X34: 1 | Y34: 0 | Z34: =SUM(S34:Y34) -> 18 | AB34: 1421600 | AC34: J MHC CINTURA P | AD34: Ventas | AF34: 0 | AG34: 5 | AH34: 5 | AI34: 4 | AJ34: 3 | AK34: 1 | AL34: 0 | AM34: =SUM(AF34:AL34) -> 18 | AO34: 1421600 | AP34: J MHC CINTURA P | AQ34: Ventas | AS34: 0 | AT34: 5 | AU34: 5 | AV34: 4 | AW34: 3 | AX34: 1 | AY34: 0 | AZ34: =SUM(AS34:AY34) -> 18 | BB34: 1421600 | BC34: J MHC CINTURA P | BD34: Ventas | BF34: 0 | BG34: 5 | BH34: 5 | BI34: 4 | BJ34: 3 | BK34: 1 | BL34: 0 | BM34: =SUM(BF34:BL34) -> 18 | BO34: 1421600 | BP34: J MHC CINTURA P | BQ34: Ventas | BS34: 0 | BT34: 5 | BU34: 5 | BV34: 4 | BW34: 3 | BX34: 1 | BY34: 0 | BZ34: =SUM(BS34:BY34) -> 18 | CB34: 1421600 | CC34: J MHC CINTURA P | CD34: Ventas | CF34: 0 | CG34: 5 | CH34: 5 | CI34: 4 | CJ34: 3 | CK34: 1 | CL34: 0 | CM34: =SUM(CF34:CL34) -> 18 | CO34: 1421600 | CP34: J MHC CINTURA P | CQ34: Ventas | CS34: 0 | CT34: 5 | CU34: 5 | CV34: 4 | CW34: 3 | CX34: 1 | CY34: 0 | CZ34: 18 | DB34: 1421600 | DC34: J MHC CINTURA P | DD34: Ventas | DF34: 0 | DG34: 5 | DH34: 5 | DI34: 4 | DJ34: 3 | DK34: 1 | DL34: 0 | DM34: 18 | DO34: 1421600 | DP34: J MHC CINTURA P | DQ34: Ventas | DS34: 0 | DT34: 5 | DU34: 5 | DV34: 4 | DW34: 3 | DX34: 1 | DY34: 0 | DZ34: 18 | EB34: 1421600 | EC34: J MHC CINTURA P | ED34: Ventas | EF34: 0 | EG34: 5 | EH34: 5 | EI34: 4 | EJ34: 3 | EK34: 1 | EL34: 0 | EM34: 18 | EO34: 1421700 | EP34: J MHC CINTURA F | EQ34: Ventas | ES34: 0 | ET34: 2 | EU34: 3 | EV34: 2 | EW34: 1 | EX34: 0 | EY34: 0 | EZ34: 8 | FB34: 1421801 | FC34: J MHC CINTURA F | FD34: Ventas | FF34: 29 | FG34: 60 | FH34: 61 | FI34: 57 | FJ34: 41 | FK34: 31 | FL34: 0 | FM34: 279 | FO34: 1421801 | FP34: J MHC CINTURA F | FQ34: Ventas | FS34: 29 | FT34: 60 | FU34: 61 | FV34: 57 | FW34: 41 | FX34: 31 | FY34: 0 | FZ34: 279 | GB34: 1421801 | GC34: J MHC CINTURA F | GD34: Ventas | GF34: 17 | GG34: 30 | GH34: 31 | GI34: 27 | GJ34: 21 | GK34: 13 | GL34: 0 | GM34: 139 | GO34: 1421801 | GP34: J MHC CINTURA F | GQ34: Ventas | GS34: 16 | GT34: 27 | GU34: 27 | GV34: 24 | GW34: 19 | GX34: 12 | GY34: 0 | GZ34: =SUM(GS34:GY34) -> 125
A35: 1421700 | B35: B2868-V3 | C35: 3 | D35: 7 | E35: 9 | F35: 6 | G35: 3 | H35: 1 | J35: =SUM(C35:H35) -> 29 | K35: ='CORTE 4200'!$O$295 -> 29 | O35: 1421700 | P35: J MHC CINTURA F | Q35: Ventas | S35: 3 | T35: 7 | U35: 9 | V35: 6 | W35: 3 | X35: 1 | Y35: 0 | Z35: =SUM(S35:Y35) -> 29 | AB35: 1421700 | AC35: J MHC CINTURA F | AD35: Ventas | AF35: 3 | AG35: 7 | AH35: 9 | AI35: 6 | AJ35: 3 | AK35: 1 | AL35: 0 | AM35: =SUM(AF35:AL35) -> 29 | AO35: 1421700 | AP35: J MHC CINTURA F | AQ35: Ventas | AS35: 3 | AT35: 7 | AU35: 9 | AV35: 6 | AW35: 3 | AX35: 1 | AY35: 0 | AZ35: =SUM(AS35:AY35) -> 29 | BB35: 1421700 | BC35: J MHC CINTURA F | BD35: Ventas | BF35: 2 | BG35: 5 | BH35: 6 | BI35: 4 | BJ35: 2 | BK35: 0 | BL35: 0 | BM35: =SUM(BF35:BL35) -> 19 | BO35: 1421700 | BP35: J MHC CINTURA F | BQ35: Ventas | BS35: 2 | BT35: 5 | BU35: 6 | BV35: 4 | BW35: 2 | BX35: 0 | BY35: 0 | BZ35: =SUM(BS35:BY35) -> 19 | CB35: 1421700 | CC35: J MHC CINTURA F | CD35: Ventas | CF35: 2 | CG35: 5 | CH35: 6 | CI35: 4 | CJ35: 2 | CK35: 0 | CL35: 0 | CM35: =SUM(CF35:CL35) -> 19 | CO35: 1421700 | CP35: J MHC CINTURA F | CQ35: Ventas | CS35: 2 | CT35: 5 | CU35: 6 | CV35: 4 | CW35: 2 | CX35: 0 | CY35: 0 | CZ35: 19 | DB35: 1421700 | DC35: J MHC CINTURA F | DD35: Ventas | DF35: 2 | DG35: 5 | DH35: 6 | DI35: 4 | DJ35: 2 | DK35: 0 | DL35: 0 | DM35: 19 | DO35: 1421700 | DP35: J MHC CINTURA F | DQ35: Ventas | DS35: 0 | DT35: 2 | DU35: 3 | DV35: 2 | DW35: 1 | DX35: 0 | DY35: 0 | DZ35: 8 | EB35: 1421700 | EC35: J MHC CINTURA F | ED35: Ventas | EF35: 0 | EG35: 2 | EH35: 3 | EI35: 2 | EJ35: 1 | EK35: 0 | EL35: 0 | EM35: 8 | EO35: 1421800 | EP35: J MHC CINTURA F | EQ35: Ventas | ES35: 51 | ET35: 114 | EU35: 128 | EV35: 121 | EW35: 86 | EX35: 71 | EY35: 0 | EZ35: 571 | FB35: 1421802 | FC35: J MHC CINTURA F | FD35: Ventas | FF35: 0 | FG35: 4 | FH35: 8 | FI35: 8 | FJ35: 7 | FK35: 5 | FL35: 0 | FM35: 32 | FO35: 1421802 | FP35: J MHC CINTURA F | FQ35: Ventas | FS35: 0 | FT35: 4 | FU35: 8 | FV35: 8 | FW35: 7 | FX35: 5 | FY35: 0 | FZ35: 32 | GB35: 1421802 | GC35: J MHC CINTURA F | GD35: Ventas | GF35: 0 | GG35: 4 | GH35: 8 | GI35: 8 | GJ35: 7 | GK35: 5 | GL35: 0 | GM35: 32 | GO35: 1421802 | GP35: J MHC CINTURA F | GQ35: Ventas | GS35: 0 | GT35: 4 | GU35: 8 | GV35: 8 | GW35: 7 | GX35: 5 | GY35: 0 | GZ35: =SUM(GS35:GY35) -> 32
A36: 1421800 | B36: New Glue | C36: 71 | D36: 152 | E36: 171 | F36: 160 | G36: 111 | H36: 87 | J36: =SUM(C36:H36) -> 752 | K36: ='CORTE 4200'!$O$304 -> -76 | L36: 50 | O36: 1421800 | P36: J MHC CINTURA F | Q36: Ventas | S36: 71 | T36: 152 | U36: 171 | V36: 160 | W36: 111 | X36: 87 | Y36: 0 | Z36: =SUM(S36:Y36) -> 752 | AB36: 1421800 | AC36: J MHC CINTURA F | AD36: Ventas | AF36: 71 | AG36: 152 | AH36: 171 | AI36: 160 | AJ36: 111 | AK36: 87 | AL36: 0 | AM36: =SUM(AF36:AL36) -> 752 | AO36: 1421800 | AP36: J MHC CINTURA F | AQ36: Ventas | AS36: 71 | AT36: 152 | AU36: 171 | AV36: 160 | AW36: 111 | AX36: 87 | AY36: 0 | AZ36: =SUM(AS36:AY36) -> 752 | BB36: 1421800 | BC36: J MHC CINTURA F | BD36: Ventas | BF36: 63 | BG36: 140 | BH36: 159 | BI36: 148 | BJ36: 108 | BK36: 84 | BL36: 0 | BM36: =SUM(BF36:BL36) -> 702 | BO36: 1421800 | BP36: J MHC CINTURA F | BQ36: Ventas | BS36: 63 | BT36: 140 | BU36: 159 | BV36: 148 | BW36: 108 | BX36: 84 | BY36: 0 | BZ36: =SUM(BS36:BY36) -> 702 | CB36: 1421800 | CC36: J MHC CINTURA F | CD36: Ventas | CF36: 63 | CG36: 140 | CH36: 159 | CI36: 148 | CJ36: 108 | CK36: 84 | CL36: 0 | CM36: =SUM(CF36:CL36) -> 702 | CO36: 1421800 | CP36: J MHC CINTURA F | CQ36: Ventas | CS36: 63 | CT36: 135 | CU36: 154 | CV36: 142 | CW36: 103 | CX36: 81 | CY36: 0 | CZ36: 678 | DB36: 1421800 | DC36: J MHC CINTURA F | DD36: Ventas | DF36: 56 | DG36: 124 | DH36: 142 | DI36: 131 | DJ36: 93 | DK36: 76 | DL36: 0 | DM36: 622 | DO36: 1421800 | DP36: J MHC CINTURA F | DQ36: Ventas | DS36: 52 | DT36: 116 | DU36: 130 | DV36: 123 | DW36: 87 | DX36: 72 | DY36: 0 | DZ36: 580 | EB36: 1421800 | EC36: J MHC CINTURA F | ED36: Ventas | EF36: 52 | EG36: 116 | EH36: 130 | EI36: 123 | EJ36: 87 | EK36: 72 | EL36: 0 | EM36: 580 | EO36: 1421801 | EP36: J MHC CINTURA F | EQ36: Ventas | ES36: 33 | ET36: 68 | EU36: 69 | EV36: 65 | EW36: 47 | EX36: 34 | EY36: 0 | EZ36: 316 | FB36: 1421900 | FC36: J MHC CINTURA P | FD36: Ventas | FF36: 0 | FG36: 2 | FH36: 4 | FI36: 4 | FJ36: 4 | FK36: 3 | FL36: 0 | FM36: 17 | FO36: 1421900 | FP36: J MHC CINTURA P | FQ36: Ventas | FS36: 0 | FT36: 2 | FU36: 4 | FV36: 4 | FW36: 4 | FX36: 3 | FY36: 0 | FZ36: 17 | GB36: 1421900 | GC36: J MHC CINTURA P | GD36: Ventas | GF36: 0 | GG36: 2 | GH36: 4 | GI36: 4 | GJ36: 4 | GK36: 3 | GL36: 0 | GM36: 17 | GO36: 1421900 | GP36: J MHC CINTURA P | GQ36: Ventas | GS36: 0 | GT36: 2 | GU36: 4 | GV36: 4 | GW36: 4 | GX36: 3 | GY36: 0 | GZ36: =SUM(GS36:GY36) -> 17
A37: 1421801 | B37: New Glue | C37: 42 | D37: 84 | E37: 86 | F37: 79 | G37: 57 | H37: 40 | J37: =SUM(C37:H37) -> 388 | K37: ='CORTE 4200'!$O$313 -> -34 | O37: 1421801 | P37: J MHC CINTURA F | Q37: Ventas | S37: 42 | T37: 84 | U37: 86 | V37: 79 | W37: 57 | X37: 40 | Y37: 0 | Z37: =SUM(S37:Y37) -> 388 | AB37: 1421801 | AC37: J MHC CINTURA F | AD37: Ventas | AF37: 42 | AG37: 84 | AH37: 86 | AI37: 79 | AJ37: 57 | AK37: 40 | AL37: 0 | AM37: =SUM(AF37:AL37) -> 388 | AO37: 1421801 | AP37: J MHC CINTURA F | AQ37: Ventas | AS37: 40 | AT37: 79 | AU37: 81 | AV37: 75 | AW37: 53 | AX37: 36 | AY37: 0 | AZ37: =SUM(AS37:AY37) -> 364 | BB37: 1421801 | BC37: J MHC CINTURA F | BD37: Ventas | BF37: 39 | BG37: 77 | BH37: 78 | BI37: 73 | BJ37: 52 | BK37: 35 | BL37: 0 | BM37: =SUM(BF37:BL37) -> 354 | BO37: 1421801 | BP37: J MHC CINTURA F | BQ37: Ventas | BS37: 39 | BT37: 77 | BU37: 78 | BV37: 73 | BW37: 52 | BX37: 35 | BY37: 0 | BZ37: =SUM(BS37:BY37) -> 354 | CB37: 1421801 | CC37: J MHC CINTURA F | CD37: Ventas | CF37: 39 | CG37: 77 | CH37: 78 | CI37: 73 | CJ37: 52 | CK37: 35 | CL37: 0 | CM37: =SUM(CF37:CL37) -> 354 | CO37: 1421801 | CP37: J MHC CINTURA F | CQ37: Ventas | CS37: 39 | CT37: 77 | CU37: 78 | CV37: 73 | CW37: 52 | CX37: 35 | CY37: 0 | CZ37: 354 | DB37: 1421801 | DC37: J MHC CINTURA F | DD37: Ventas | DF37: 38 | DG37: 75 | DH37: 76 | DI37: 71 | DJ37: 51 | DK37: 35 | DL37: 0 | DM37: 346 | DO37: 1421801 | DP37: J MHC CINTURA F | DQ37: Ventas | DS37: 35 | DT37: 71 | DU37: 72 | DV37: 68 | DW37: 49 | DX37: 35 | DY37: 0 | DZ37: 330 | EB37: 1421801 | EC37: J MHC CINTURA F | ED37: Ventas | EF37: 35 | EG37: 71 | EH37: 72 | EI37: 68 | EJ37: 49 | EK37: 35 | EL37: 0 | EM37: 330 | EO37: 1421802 | EP37: J MHC CINTURA F | EQ37: Ventas | ES37: 0 | ET37: 4 | EU37: 8 | EV37: 8 | EW37: 7 | EX37: 5 | EY37: 0 | EZ37: 32 | FB37: 1421901 | FC37: J MHC CINTURA P | FD37: Ventas | FF37: 1 | FG37: 4 | FH37: 6 | FI37: 6 | FJ37: 6 | FK37: 5 | FL37: 0 | FM37: 28 | FO37: 1421901 | FP37: J MHC CINTURA P | FQ37: Ventas | FS37: 1 | FT37: 4 | FU37: 6 | FV37: 6 | FW37: 6 | FX37: 5 | FY37: 0 | FZ37: 28 | GB37: 1421901 | GC37: J MHC CINTURA P | GD37: Ventas | GF37: 0 | GG37: 2 | GH37: 4 | GI37: 4 | GJ37: 4 | GK37: 3 | GL37: 0 | GM37: 17 | GO37: 1421901 | GP37: J MHC CINTURA P | GQ37: Ventas | GS37: 0 | GT37: 2 | GU37: 4 | GV37: 4 | GW37: 4 | GX37: 3 | GY37: 0 | GZ37: =SUM(GS37:GY37) -> 17
A38: 1421802 | B38: New Glue | C38: 0 | D38: 4 | E38: 8 | F38: 8 | G38: 7 | H38: 5 | J38: =SUM(C38:H38) -> 32 | K38: ='CORTE 4200'!$O$322 -> 0 | O38: 1421802 | P38: J MHC CINTURA F | Q38: Ventas | S38: 0 | T38: 4 | U38: 8 | V38: 8 | W38: 7 | X38: 5 | Y38: 0 | Z38: =SUM(S38:Y38) -> 32 | AB38: 1421802 | AC38: J MHC CINTURA F | AD38: Ventas | AF38: 0 | AG38: 4 | AH38: 8 | AI38: 8 | AJ38: 7 | AK38: 5 | AL38: 0 | AM38: =SUM(AF38:AL38) -> 32 | AO38: 1421802 | AP38: J MHC CINTURA F | AQ38: Ventas | AS38: 0 | AT38: 4 | AU38: 8 | AV38: 8 | AW38: 7 | AX38: 5 | AY38: 0 | AZ38: =SUM(AS38:AY38) -> 32 | BB38: 1421802 | BC38: J MHC CINTURA F | BD38: Ventas | BF38: 0 | BG38: 4 | BH38: 8 | BI38: 8 | BJ38: 7 | BK38: 5 | BL38: 0 | BM38: =SUM(BF38:BL38) -> 32 | BO38: 1421802 | BP38: J MHC CINTURA F | BQ38: Ventas | BS38: 0 | BT38: 4 | BU38: 8 | BV38: 8 | BW38: 7 | BX38: 5 | BY38: 0 | BZ38: =SUM(BS38:BY38) -> 32 | CB38: 1421802 | CC38: J MHC CINTURA F | CD38: Ventas | CF38: 0 | CG38: 4 | CH38: 8 | CI38: 8 | CJ38: 7 | CK38: 5 | CL38: 0 | CM38: =SUM(CF38:CL38) -> 32 | CO38: 1421802 | CP38: J MHC CINTURA F | CQ38: Ventas | CS38: 0 | CT38: 4 | CU38: 8 | CV38: 8 | CW38: 7 | CX38: 5 | CY38: 0 | CZ38: 32 | DB38: 1421802 | DC38: J MHC CINTURA F | DD38: Ventas | DF38: 0 | DG38: 4 | DH38: 8 | DI38: 8 | DJ38: 7 | DK38: 5 | DL38: 0 | DM38: 32 | DO38: 1421802 | DP38: J MHC CINTURA F | DQ38: Ventas | DS38: 0 | DT38: 4 | DU38: 8 | DV38: 8 | DW38: 7 | DX38: 5 | DY38: 0 | DZ38: 32 | EB38: 1421802 | EC38: J MHC CINTURA F | ED38: Ventas | EF38: 0 | EG38: 4 | EH38: 8 | EI38: 8 | EJ38: 7 | EK38: 5 | EL38: 0 | EM38: 32 | EO38: 1421900 | EP38: J MHC CINTURA P | EQ38: Ventas | ES38: 0 | ET38: 4 | EU38: 7 | EV38: 6 | EW38: 5 | EX38: 3 | EY38: 0 | EZ38: 25 | FB38: 1421902 | FC38: J MHC CINTURA P | FD38: Ventas | FF38: 3 | FG38: 4 | FH38: 2 | FI38: 2 | FJ38: 1 | FK38: 0 | FL38: 0 | FM38: 12 | FO38: 1421902 | FP38: J MHC CINTURA P | FQ38: Ventas | FS38: 3 | FT38: 4 | FU38: 2 | FV38: 2 | FW38: 1 | FX38: 0 | FY38: 0 | FZ38: 12 | GB38: 1421902 | GC38: J MHC CINTURA P | GD38: Ventas | GF38: 3 | GG38: 4 | GH38: 2 | GI38: 2 | GJ38: 1 | GK38: 0 | GL38: 0 | GM38: 12 | GO38: 1421902 | GP38: J MHC CINTURA P | GQ38: Ventas | GS38: 3 | GT38: 4 | GU38: 2 | GV38: 2 | GW38: 1 | GX38: 0 | GY38: 0 | GZ38: =SUM(GS38:GY38) -> 12
A39: 1421900 | B39: Ayla | C39: 7 | D39: 19 | E39: 21 | F39: 17 | G39: 12 | H39: 8 | J39: =SUM(C39:H39) -> 84 | K39: ='CORTE 4200'!$O$331 -> -510 | O39: 1421900 | P39: J MHC CINTURA P | Q39: Ventas | S39: 7 | T39: 19 | U39: 21 | V39: 17 | W39: 12 | X39: 8 | Y39: 0 | Z39: =SUM(S39:Y39) -> 84 | AB39: 1421900 | AC39: J MHC CINTURA P | AD39: Ventas | AF39: 7 | AG39: 19 | AH39: 21 | AI39: 17 | AJ39: 12 | AK39: 8 | AL39: 0 | AM39: =SUM(AF39:AL39) -> 84 | AO39: 1421900 | AP39: J MHC CINTURA P | AQ39: Ventas | AS39: 7 | AT39: 19 | AU39: 21 | AV39: 17 | AW39: 12 | AX39: 8 | AY39: 0 | AZ39: =SUM(AS39:AY39) -> 84 | BB39: 1421900 | BC39: J MHC CINTURA P | BD39: Ventas | BF39: 7 | BG39: 19 | BH39: 21 | BI39: 17 | BJ39: 12 | BK39: 8 | BL39: 0 | BM39: =SUM(BF39:BL39) -> 84 | BO39: 1421900 | BP39: J MHC CINTURA P | BQ39: Ventas | BS39: 5 | BT39: 15 | BU39: 18 | BV39: 15 | BW39: 11 | BX39: 8 | BY39: 0 | BZ39: =SUM(BS39:BY39) -> 72 | CB39: 1421900 | CC39: J MHC CINTURA P | CD39: Ventas | CF39: 5 | CG39: 15 | CH39: 18 | CI39: 15 | CJ39: 11 | CK39: 8 | CL39: 0 | CM39: =SUM(CF39:CL39) -> 72 | CO39: 1421900 | CP39: J MHC CINTURA P | CQ39: Ventas | CS39: 5 | CT39: 15 | CU39: 18 | CV39: 15 | CW39: 11 | CX39: 8 | CY39: 0 | CZ39: 72 | DB39: 1421900 | DC39: J MHC CINTURA P | DD39: Ventas | DF39: 3 | DG39: 11 | DH39: 13 | DI39: 11 | DJ39: 8 | DK39: 4 | DL39: 0 | DM39: 50 | DO39: 1421900 | DP39: J MHC CINTURA P | DQ39: Ventas | DS39: 2 | DT39: 8 | DU39: 11 | DV39: 10 | DW39: 7 | DX39: 4 | DY39: 0 | DZ39: 42 | EB39: 1421900 | EC39: J MHC CINTURA P | ED39: Ventas | EF39: 2 | EG39: 7 | EH39: 10 | EI39: 9 | EJ39: 7 | EK39: 4 | EL39: 0 | EM39: 39 | EO39: 1421901 | EP39: J MHC CINTURA P | EQ39: Ventas | ES39: 1 | ET39: 4 | EU39: 6 | EV39: 6 | EW39: 6 | EX39: 5 | EY39: 0 | EZ39: 28 | FB39: 1422000 | FC39: J MHC CINTURA P | FD39: Ventas | FF39: 11 | FG39: 23 | FH39: 26 | FI39: 26 | FJ39: 18 | FK39: 16 | FL39: 0 | FM39: 120 | FO39: 1422000 | FP39: J MHC CINTURA P | FQ39: Ventas | FS39: 9 | FT39: 17 | FU39: 20 | FV39: 20 | FW39: 14 | FX39: 12 | FY39: 0 | FZ39: 92 | GB39: 1422000 | GC39: J MHC CINTURA P | GD39: Ventas | GF39: 6 | GG39: 8 | GH39: 11 | GI39: 11 | GJ39: 8 | GK39: 6 | GL39: 0 | GM39: 50 | GO39: 1422000 | GP39: J MHC CINTURA P | GQ39: Ventas | GS39: 4 | GT39: 6 | GU39: 8 | GV39: 8 | GW39: 6 | GX39: 4 | GY39: 0 | GZ39: =SUM(GS39:GY39) -> 36
A40: 1421901 | B40: Ayla | C40: 4 | D40: 9 | E40: 12 | F40: 11 | G40: 10 | H40: 7 | J40: =SUM(C40:H40) -> 53 | K40: ='CORTE 4200'!$O$340 -> 16 | O40: 1421901 | P40: J MHC CINTURA P | Q40: Ventas | S40: 4 | T40: 9 | U40: 12 | V40: 11 | W40: 10 | X40: 7 | Y40: 0 | Z40: =SUM(S40:Y40) -> 53 | AB40: 1421901 | AC40: J MHC CINTURA P | AD40: Ventas | AF40: 4 | AG40: 9 | AH40: 12 | AI40: 11 | AJ40: 10 | AK40: 7 | AL40: 0 | AM40: =SUM(AF40:AL40) -> 53 | AO40: 1421901 | AP40: J MHC CINTURA P | AQ40: Ventas | AS40: 4 | AT40: 9 | AU40: 12 | AV40: 11 | AW40: 10 | AX40: 7 | AY40: 0 | AZ40: =SUM(AS40:AY40) -> 53 | BB40: 1421901 | BC40: J MHC CINTURA P | BD40: Ventas | BF40: 4 | BG40: 9 | BH40: 12 | BI40: 11 | BJ40: 10 | BK40: 7 | BL40: 0 | BM40: =SUM(BF40:BL40) -> 53 | BO40: 1421901 | BP40: J MHC CINTURA P | BQ40: Ventas | BS40: 2 | BT40: 5 | BU40: 8 | BV40: 8 | BW40: 8 | BX40: 6 | BY40: 0 | BZ40: =SUM(BS40:BY40) -> 37 | CB40: 1421901 | CC40: J MHC CINTURA P | CD40: Ventas | CF40: 2 | CG40: 5 | CH40: 8 | CI40: 8 | CJ40: 8 | CK40: 6 | CL40: 0 | CM40: =SUM(CF40:CL40) -> 37 | CO40: 1421901 | CP40: J MHC CINTURA P | CQ40: Ventas | CS40: 2 | CT40: 5 | CU40: 8 | CV40: 8 | CW40: 8 | CX40: 6 | CY40: 0 | CZ40: 37 | DB40: 1421901 | DC40: J MHC CINTURA P | DD40: Ventas | DF40: 1 | DG40: 4 | DH40: 6 | DI40: 6 | DJ40: 6 | DK40: 5 | DL40: 0 | DM40: 28 | DO40: 1421901 | DP40: J MHC CINTURA P | DQ40: Ventas | DS40: 1 | DT40: 4 | DU40: 6 | DV40: 6 | DW40: 6 | DX40: 5 | DY40: 0 | DZ40: 28 | EB40: 1421901 | EC40: J MHC CINTURA P | ED40: Ventas | EF40: 1 | EG40: 4 | EH40: 6 | EI40: 6 | EJ40: 6 | EK40: 5 | EL40: 0 | EM40: 28 | EO40: 1421902 | EP40: J MHC CINTURA P | EQ40: Ventas | ES40: 3 | ET40: 4 | EU40: 2 | EV40: 2 | EW40: 1 | EX40: 0 | EY40: 0 | EZ40: 12 | FB40: 1422100 | FC40: J MHC CINTURA T | FD40: Ventas | FF40: 36 | FG40: 90 | FH40: 93 | FI40: 92 | FJ40: 63 | FK40: 59 | FL40: 0 | FM40: 433 | FO40: 1422100 | FP40: J MHC CINTURA T | FQ40: Ventas | FS40: 34 | FT40: 84 | FU40: 87 | FV40: 86 | FW40: 59 | FX40: 55 | FY40: 0 | FZ40: 405 | GB40: 1422100 | GC40: J MHC CINTURA T | GD40: Ventas | GF40: 6 | GG40: 15 | GH40: 19 | GI40: 18 | GJ40: 15 | GK40: 10 | GL40: 0 | GM40: 83 | GO40: 1422100 | GP40: J MHC CINTURA T | GQ40: Ventas | GS40: 6 | GT40: 15 | GU40: 19 | GV40: 18 | GW40: 15 | GX40: 10 | GY40: 0 | GZ40: =SUM(GS40:GY40) -> 83
A41: 1421902 | B41: Ayla | C41: 3 | D41: 6 | E41: 4 | F41: 4 | G41: 3 | H41: 2 | J41: =SUM(C41:H41) -> 22 | K41: ='CORTE 4200'!$O$349 -> 10 | O41: 1421902 | P41: J MHC CINTURA P | Q41: Ventas | S41: 3 | T41: 6 | U41: 4 | V41: 4 | W41: 3 | X41: 2 | Y41: 0 | Z41: =SUM(S41:Y41) -> 22 | AB41: 1421902 | AC41: J MHC CINTURA P | AD41: Ventas | AF41: 3 | AG41: 6 | AH41: 4 | AI41: 4 | AJ41: 3 | AK41: 2 | AL41: 0 | AM41: =SUM(AF41:AL41) -> 22 | AO41: 1421902 | AP41: J MHC CINTURA P | AQ41: Ventas | AS41: 3 | AT41: 4 | AU41: 2 | AV41: 2 | AW41: 1 | AX41: 0 | AY41: 0 | AZ41: =SUM(AS41:AY41) -> 12 | BB41: 1421902 | BC41: J MHC CINTURA P | BD41: Ventas | BF41: 3 | BG41: 4 | BH41: 2 | BI41: 2 | BJ41: 1 | BK41: 0 | BL41: 0 | BM41: =SUM(BF41:BL41) -> 12 | BO41: 1421902 | BP41: J MHC CINTURA P | BQ41: Ventas | BS41: 3 | BT41: 4 | BU41: 2 | BV41: 2 | BW41: 1 | BX41: 0 | BY41: 0 | BZ41: =SUM(BS41:BY41) -> 12 | CB41: 1421902 | CC41: J MHC CINTURA P | CD41: Ventas | CF41: 3 | CG41: 4 | CH41: 2 | CI41: 2 | CJ41: 1 | CK41: 0 | CL41: 0 | CM41: =SUM(CF41:CL41) -> 12 | CO41: 1421902 | CP41: J MHC CINTURA P | CQ41: Ventas | CS41: 3 | CT41: 4 | CU41: 2 | CV41: 2 | CW41: 1 | CX41: 0 | CY41: 0 | CZ41: 12 | DB41: 1421902 | DC41: J MHC CINTURA P | DD41: Ventas | DF41: 3 | DG41: 4 | DH41: 2 | DI41: 2 | DJ41: 1 | DK41: 0 | DL41: 0 | DM41: 12 | DO41: 1421902 | DP41: J MHC CINTURA P | DQ41: Ventas | DS41: 3 | DT41: 4 | DU41: 2 | DV41: 2 | DW41: 1 | DX41: 0 | DY41: 0 | DZ41: 12 | EB41: 1421902 | EC41: J MHC CINTURA P | ED41: Ventas | EF41: 3 | EG41: 4 | EH41: 2 | EI41: 2 | EJ41: 1 | EK41: 0 | EL41: 0 | EM41: 12 | EO41: 1422000 | EP41: J MHC CINTURA P | EQ41: Ventas | ES41: 16 | ET41: 30 | EU41: 34 | EV41: 33 | EW41: 25 | EX41: 19 | EY41: 0 | EZ41: 157 | FB41: 1422101 | FC41: J MHC CINTURA T | FD41: Ventas | FF41: 21 | FG41: 30 | FH41: 33 | FI41: 31 | FJ41: 25 | FK41: 19 | FL41: 0 | FM41: 159 | FO41: 1422101 | FP41: J MHC CINTURA T | FQ41: Ventas | FS41: 21 | FT41: 30 | FU41: 33 | FV41: 31 | FW41: 25 | FX41: 19 | FY41: 0 | FZ41: 159 | GB41: 1422101 | GC41: J MHC CINTURA T | GD41: Ventas | GF41: 20 | GG41: 28 | GH41: 31 | GI41: 29 | GJ41: 23 | GK41: 17 | GL41: 0 | GM41: 148 | GO41: 1422101 | GP41: J MHC CINTURA T | GQ41: Ventas | GS41: 17 | GT41: 23 | GU41: 24 | GV41: 23 | GW41: 19 | GX41: 14 | GY41: 0 | GZ41: =SUM(GS41:GY41) -> 120
A42: 1422000 | B42: Ayla | C42: 40 | D42: 73 | E42: 75 | F42: 70 | G42: 47 | H42: 32 | J42: =SUM(C42:H42) -> 337 | K42: ='CORTE 4200'!$O$358 -> 12 | L42: 50 | O42: 1422000 | P42: J MHC CINTURA P | Q42: Ventas | S42: 40 | T42: 73 | U42: 75 | V42: 70 | W42: 47 | X42: 32 | Y42: 0 | Z42: =SUM(S42:Y42) -> 337 | AB42: 1422000 | AC42: J MHC CINTURA P | AD42: Ventas | AF42: 39 | AG42: 72 | AH42: 74 | AI42: 70 | AJ42: 47 | AK42: 32 | AL42: 0 | AM42: =SUM(AF42:AL42) -> 334 | AO42: 1422000 | AP42: J MHC CINTURA P | AQ42: Ventas | AS42: 37 | AT42: 67 | AU42: 70 | AV42: 66 | AW42: 43 | AX42: 29 | AY42: 0 | AZ42: =SUM(AS42:AY42) -> 312 | BB42: 1422000 | BC42: J MHC CINTURA P | BD42: Ventas | BF42: 28 | BG42: 53 | BH42: 55 | BI42: 52 | BJ42: 39 | BK42: 25 | BL42: 0 | BM42: =SUM(BF42:BL42) -> 252 | BO42: 1422000 | BP42: J MHC CINTURA P | BQ42: Ventas | BS42: 28 | BT42: 53 | BU42: 55 | BV42: 52 | BW42: 39 | BX42: 25 | BY42: 0 | BZ42: =SUM(BS42:BY42) -> 252 | CB42: 1422000 | CC42: J MHC CINTURA P | CD42: Ventas | CF42: 26 | CG42: 50 | CH42: 52 | CI42: 49 | CJ42: 37 | CK42: 24 | CL42: 0 | CM42: =SUM(CF42:CL42) -> 238 | CO42: 1422000 | CP42: J MHC CINTURA P | CQ42: Ventas | CS42: 26 | CT42: 49 | CU42: 51 | CV42: 48 | CW42: 36 | CX42: 24 | CY42: 0 | CZ42: 234 | DB42: 1422000 | DC42: J MHC CINTURA P | DD42: Ventas | DF42: 24 | DG42: 45 | DH42: 47 | DI42: 44 | DJ42: 33 | DK42: 24 | DL42: 0 | DM42: 217 | DO42: 1422000 | DP42: J MHC CINTURA P | DQ42: Ventas | DS42: 19 | DT42: 37 | DU42: 40 | DV42: 39 | DW42: 29 | DX42: 22 | DY42: 0 | DZ42: 186 | EB42: 1422000 | EC42: J MHC CINTURA P | ED42: Ventas | EF42: 18 | EG42: 33 | EH42: 37 | EI42: 36 | EJ42: 27 | EK42: 20 | EL42: 0 | EM42: 171 | EO42: 1422100 | EP42: J MHC CINTURA T | EQ42: Ventas | ES42: 40 | ET42: 96 | EU42: 99 | EV42: 98 | EW42: 68 | EX42: 62 | EY42: 0 | EZ42: 463 | FB42: 1422190 | FC42: J MHC CINTURA | FD42: Ventas | FF42: 3 | FG42: 6 | FH42: 8 | FI42: 8 | FJ42: 7 | FK42: 6 | FL42: 0 | FM42: 38 | FO42: 1422190 | FP42: J MHC CINTURA | FQ42: Ventas | FS42: 3 | FT42: 6 | FU42: 8 | FV42: 8 | FW42: 7 | FX42: 6 | FY42: 0 | FZ42: 38 | GB42: 1422190 | GC42: J MHC CINTURA | GD42: Ventas | GF42: 0 | GG42: 2 | GH42: 4 | GI42: 4 | GJ42: 4 | GK42: 3 | GL42: 0 | GM42: 17 | GO42: 1422190 | GP42: J MHC CINTURA | GQ42: Ventas | GS42: 0 | GT42: 2 | GU42: 4 | GV42: 4 | GW42: 4 | GX42: 3 | GY42: 0 | GZ42: =SUM(GS42:GY42) -> 17
A43: 1422100 | B43: New Glue | C43: 43 | D43: 105 | E43: 108 | F43: 103 | G43: 72 | H43: 65 | J43: =SUM(C43:H43) -> 496 | K43: ='CORTE 4200'!$O$367 -> -75 | O43: 1422100 | P43: J MHC CINTURA T | Q43: Ventas | S43: 43 | T43: 105 | U43: 108 | V43: 103 | W43: 72 | X43: 65 | Y43: 0 | Z43: =SUM(S43:Y43) -> 496 | AB43: 1422100 | AC43: J MHC CINTURA T | AD43: Ventas | AF43: 43 | AG43: 105 | AH43: 108 | AI43: 103 | AJ43: 72 | AK43: 66 | AL43: 0 | AM43: =SUM(AF43:AL43) -> 497 | AO43: 1422100 | AP43: J MHC CINTURA T | AQ43: Ventas | AS43: 43 | AT43: 105 | AU43: 108 | AV43: 103 | AW43: 72 | AX43: 66 | AY43: 0 | AZ43: =SUM(AS43:AY43) -> 497 | BB43: 1422100 | BC43: J MHC CINTURA T | BD43: Ventas | BF43: 43 | BG43: 105 | BH43: 108 | BI43: 103 | BJ43: 72 | BK43: 66 | BL43: 0 | BM43: =SUM(BF43:BL43) -> 497 | BO43: 1422100 | BP43: J MHC CINTURA T | BQ43: Ventas | BS43: 43 | BT43: 105 | BU43: 108 | BV43: 103 | BW43: 72 | BX43: 66 | BY43: 0 | BZ43: =SUM(BS43:BY43) -> 497 | CB43: 1422100 | CC43: J MHC CINTURA T | CD43: Ventas | CF43: 43 | CG43: 105 | CH43: 108 | CI43: 103 | CJ43: 72 | CK43: 66 | CL43: 0 | CM43: =SUM(CF43:CL43) -> 497 | CO43: 1422100 | CP43: J MHC CINTURA T | CQ43: Ventas | CS43: 43 | CT43: 105 | CU43: 108 | CV43: 103 | CW43: 72 | CX43: 66 | CY43: 0 | CZ43: 497 | DB43: 1422100 | DC43: J MHC CINTURA T | DD43: Ventas | DF43: 42 | DG43: 101 | DH43: 104 | DI43: 100 | DJ43: 69 | DK43: 63 | DL43: 0 | DM43: 479 | DO43: 1422100 | DP43: J MHC CINTURA T | DQ43: Ventas | DS43: 42 | DT43: 101 | DU43: 104 | DV43: 100 | DW43: 69 | DX43: 63 | DY43: 0 | DZ43: 479 | EB43: 1422100 | EC43: J MHC CINTURA T | ED43: Ventas | EF43: 40 | EG43: 96 | EH43: 99 | EI43: 98 | EJ43: 68 | EK43: 62 | EL43: 0 | EM43: 463 | EO43: 1422101 | EP43: J MHC CINTURA T | EQ43: Ventas | ES43: 22 | ET43: 33 | EU43: 36 | EV43: 33 | EW43: 26 | EX43: 19 | EY43: 0 | EZ43: 169 | FB43: 1422200 | FC43: J MHC CADERA PI | FD43: Ventas | FF43: 36 | FG43: 71 | FH43: 75 | FI43: 73 | FJ43: 50 | FK43: 42 | FL43: 0 | FM43: 347 | FO43: 1422200 | FP43: J MHC CADERA PI | FQ43: Ventas | FS43: 34 | FT43: 65 | FU43: 69 | FV43: 67 | FW43: 46 | FX43: 38 | FY43: 0 | FZ43: 319 | GB43: 1422200 | GC43: J MHC CADERA PI | GD43: Ventas | GF43: 18 | GG43: 26 | GH43: 30 | GI43: 28 | GJ43: 21 | GK43: 16 | GL43: 0 | GM43: 139 | GO43: 1422200 | GP43: J MHC CADERA PI | GQ43: Ventas | GS43: 15 | GT43: 21 | GU43: 23 | GV43: 22 | GW43: 17 | GX43: 13 | GY43: 0 | GZ43: =SUM(GS43:GY43) -> 111
A44: 1422101 | B44: New Glue | C44: 24 | D44: 39 | E44: 42 | F44: 36 | G44: 28 | H44: 21 | J44: =SUM(C44:H44) -> 190 | K44: ='CORTE 4200'!$O$376 -> -50 | O44: 1422101 | P44: J MHC CINTURA T | Q44: Ventas | S44: 24 | T44: 39 | U44: 42 | V44: 36 | W44: 28 | X44: 21 | Y44: 0 | Z44: =SUM(S44:Y44) -> 190 | AB44: 1422101 | AC44: J MHC CINTURA T | AD44: Ventas | AF44: 24 | AG44: 39 | AH44: 42 | AI44: 36 | AJ44: 28 | AK44: 21 | AL44: 0 | AM44: =SUM(AF44:AL44) -> 190 | AO44: 1422101 | AP44: J MHC CINTURA T | AQ44: Ventas | AS44: 24 | AT44: 39 | AU44: 42 | AV44: 36 | AW44: 28 | AX44: 21 | AY44: 0 | AZ44: =SUM(AS44:AY44) -> 190 | BB44: 1422101 | BC44: J MHC CINTURA T | BD44: Ventas | BF44: 24 | BG44: 39 | BH44: 42 | BI44: 36 | BJ44: 28 | BK44: 21 | BL44: 0 | BM44: =SUM(BF44:BL44) -> 190 | BO44: 1422101 | BP44: J MHC CINTURA T | BQ44: Ventas | BS44: 24 | BT44: 39 | BU44: 42 | BV44: 36 | BW44: 28 | BX44: 21 | BY44: 0 | BZ44: =SUM(BS44:BY44) -> 190 | CB44: 1422101 | CC44: J MHC CINTURA T | CD44: Ventas | CF44: 24 | CG44: 39 | CH44: 42 | CI44: 36 | CJ44: 28 | CK44: 21 | CL44: 0 | CM44: =SUM(CF44:CL44) -> 190 | CO44: 1422101 | CP44: J MHC CINTURA T | CQ44: Ventas | CS44: 24 | CT44: 39 | CU44: 42 | CV44: 36 | CW44: 28 | CX44: 21 | CY44: 0 | CZ44: 190 | DB44: 1422101 | DC44: J MHC CINTURA T | DD44: Ventas | DF44: 24 | DG44: 39 | DH44: 42 | DI44: 36 | DJ44: 28 | DK44: 21 | DL44: 0 | DM44: 190 | DO44: 1422101 | DP44: J MHC CINTURA T | DQ44: Ventas | DS44: 24 | DT44: 35 | DU44: 38 | DV44: 34 | DW44: 27 | DX44: 20 | DY44: 0 | DZ44: 178 | EB44: 1422101 | EC44: J MHC CINTURA T | ED44: Ventas | EF44: 24 | EG44: 35 | EH44: 38 | EI44: 34 | EJ44: 27 | EK44: 20 | EL44: 0 | EM44: 178 | EO44: 1422190 | EP44: J MHC CINTURA | EQ44: Ventas | ES44: 3 | ET44: 6 | EU44: 8 | EV44: 8 | EW44: 7 | EX44: 6 | EY44: 0 | EZ44: 38 | FB44: 1422300 | FC44: J MHC MEDIO FL | FD44: Ventas | FF44: 16 | FG44: 39 | FH44: 44 | FI44: 43 | FJ44: 30 | FK44: 25 | FL44: 0 | FM44: 197 | FO44: 1422300 | FP44: J MHC MEDIO FL | FQ44: Ventas | FS44: 16 | FT44: 39 | FU44: 44 | FV44: 43 | FW44: 30 | FX44: 25 | FY44: 0 | FZ44: 197 | GB44: 1422300 | GC44: J MHC MEDIO FL | GD44: Ventas | GF44: 2 | GG44: 6 | GH44: 11 | GI44: 11 | GJ44: 9 | GK44: 7 | GL44: 0 | GM44: 46 | GO44: 1422300 | GP44: J MHC MEDIO FL | GQ44: Ventas | GS44: 0 | GT44: 4 | GU44: 8 | GV44: 8 | GW44: 7 | GX44: 5 | GY44: 0 | GZ44: =SUM(GS44:GY44) -> 32
A45: 1422190 | B45: New Glue | C45: 5 | D45: 12 | E45: 14 | F45: 14 | G45: 11 | H45: 9 | J45: =SUM(C45:H45) -> 65 | K45: ='CORTE 4200'!$O$385 -> 0 | O45: 1422190 | P45: J MHC CINTURA | Q45: Ventas | S45: 5 | T45: 12 | U45: 14 | V45: 14 | W45: 11 | X45: 9 | Y45: 0 | Z45: =SUM(S45:Y45) -> 65 | AB45: 1422190 | AC45: J MHC CINTURA | AD45: Ventas | AF45: 5 | AG45: 12 | AH45: 14 | AI45: 14 | AJ45: 11 | AK45: 9 | AL45: 0 | AM45: =SUM(AF45:AL45) -> 65 | AO45: 1422190 | AP45: J MHC CINTURA | AQ45: Ventas | AS45: 5 | AT45: 10 | AU45: 12 | AV45: 12 | AW45: 9 | AX45: 7 | AY45: 0 | AZ45: =SUM(AS45:AY45) -> 55 | BB45: 1422190 | BC45: J MHC CINTURA | BD45: Ventas | BF45: 5 | BG45: 10 | BH45: 12 | BI45: 12 | BJ45: 9 | BK45: 7 | BL45: 0 | BM45: =SUM(BF45:BL45) -> 55 | BO45: 1422190 | BP45: J MHC CINTURA | BQ45: Ventas | BS45: 5 | BT45: 10 | BU45: 12 | BV45: 12 | BW45: 9 | BX45: 7 | BY45: 0 | BZ45: =SUM(BS45:BY45) -> 55 | CB45: 1422190 | CC45: J MHC CINTURA | CD45: Ventas | CF45: 3 | CG45: 7 | CH45: 9 | CI45: 9 | CJ45: 7 | CK45: 6 | CL45: 0 | CM45: =SUM(CF45:CL45) -> 41 | CO45: 1422190 | CP45: J MHC CINTURA | CQ45: Ventas | CS45: 3 | CT45: 7 | CU45: 9 | CV45: 9 | CW45: 7 | CX45: 6 | CY45: 0 | CZ45: 41 | DB45: 1422190 | DC45: J MHC CINTURA | DD45: Ventas | DF45: 3 | DG45: 7 | DH45: 9 | DI45: 9 | DJ45: 7 | DK45: 6 | DL45: 0 | DM45: 41 | DO45: 1422190 | DP45: J MHC CINTURA | DQ45: Ventas | DS45: 3 | DT45: 6 | DU45: 8 | DV45: 8 | DW45: 7 | DX45: 6 | DY45: 0 | DZ45: 38 | EB45: 1422190 | EC45: J MHC CINTURA | ED45: Ventas | EF45: 3 | EG45: 6 | EH45: 8 | EI45: 8 | EJ45: 7 | EK45: 6 | EL45: 0 | EM45: 38 | EO45: 1422200 | EP45: J MHC CADERA PI | EQ45: Ventas | ES45: 41 | ET45: 78 | EU45: 83 | EV45: 80 | EW45: 53 | EX45: 44 | EY45: 0 | EZ45: 379 | FB45: 1422400 | FC45: J MHC MEDIO OXF | FD45: Ventas | FF45: 4 | FG45: 8 | FH45: 11 | FI45: 10 | FJ45: 8 | FK45: 5 | FL45: 0 | FM45: 46 | FO45: 1422400 | FP45: J MHC MEDIO OXF | FQ45: Ventas | FS45: 4 | FT45: 8 | FU45: 11 | FV45: 10 | FW45: 8 | FX45: 5 | FY45: 0 | FZ45: 46 | GB45: 1422400 | GC45: J MHC MEDIO OXF | GD45: Ventas | GF45: 0 | GG45: 4 | GH45: 8 | GI45: 8 | GJ45: 7 | GK45: 5 | GL45: 0 | GM45: 32 | GO45: 1422400 | GP45: J MHC MEDIO OXF | GQ45: Ventas | GS45: 0 | GT45: 4 | GU45: 8 | GV45: 8 | GW45: 7 | GX45: 5 | GY45: 0 | GZ45: =SUM(GS45:GY45) -> 32
A46: 1422200 | B46: Ayla | C46: 53 | D46: 97 | E46: 107 | F46: 103 | G46: 67 | H46: 50 | J46: =SUM(C46:H46) -> 477 | K46: ='CORTE 4200'!$O$394 -> -150 | O46: 1422200 | P46: J MHC CADERA PI | Q46: Ventas | S46: 53 | T46: 97 | U46: 107 | V46: 103 | W46: 67 | X46: 50 | Y46: 0 | Z46: =SUM(S46:Y46) -> 477 | AB46: 1422200 | AC46: J MHC CADERA PI | AD46: Ventas | AF46: 54 | AG46: 99 | AH46: 109 | AI46: 103 | AJ46: 67 | AK46: 50 | AL46: 0 | AM46: =SUM(AF46:AL46) -> 482 | AO46: 1422200 | AP46: J MHC CADERA PI | AQ46: Ventas | AS46: 54 | AT46: 99 | AU46: 109 | AV46: 103 | AW46: 67 | AX46: 50 | AY46: 0 | AZ46: =SUM(AS46:AY46) -> 482 | BB46: 1422200 | BC46: J MHC CADERA PI | BD46: Ventas | BF46: 53 | BG46: 97 | BH46: 106 | BI46: 101 | BJ46: 66 | BK46: 49 | BL46: 0 | BM46: =SUM(BF46:BL46) -> 472 | BO46: 1422200 | BP46: J MHC CADERA PI | BQ46: Ventas | BS46: 53 | BT46: 97 | BU46: 106 | BV46: 101 | BW46: 66 | BX46: 49 | BY46: 0 | BZ46: =SUM(BS46:BY46) -> 472 | CB46: 1422200 | CC46: J MHC CADERA PI | CD46: Ventas | CF46: 51 | CG46: 95 | CH46: 104 | CI46: 98 | CJ46: 64 | CK46: 49 | CL46: 0 | CM46: =SUM(CF46:CL46) -> 461 | CO46: 1422200 | CP46: J MHC CADERA PI | CQ46: Ventas | CS46: 51 | CT46: 95 | CU46: 104 | CV46: 98 | CW46: 64 | CX46: 49 | CY46: 0 | CZ46: 461 | DB46: 1422200 | DC46: J MHC CADERA PI | DD46: Ventas | DF46: 48 | DG46: 91 | DH46: 99 | DI46: 93 | DJ46: 60 | DK46: 47 | DL46: 0 | DM46: 438 | DO46: 1422200 | DP46: J MHC CADERA PI | DQ46: Ventas | DS46: 45 | DT46: 86 | DU46: 91 | DV46: 86 | DW46: 56 | DX46: 46 | DY46: 0 | DZ46: 410 | EB46: 1422200 | EC46: J MHC CADERA PI | ED46: Ventas | EF46: 43 | EG46: 81 | EH46: 86 | EI46: 83 | EJ46: 55 | EK46: 45 | EL46: 0 | EM46: 393 | EO46: 1422300 | EP46: J MHC MEDIO FL | EQ46: Ventas | ES46: 22 | ET46: 47 | EU46: 52 | EV46: 50 | EW46: 34 | EX46: 28 | EY46: 0 | EZ46: 233 | FB46: 1422401 | FC46: J MHC MEDIO OXF | FD46: Ventas | FF46: 2 | FG46: 6 | FH46: 10 | FI46: 10 | FJ46: 8 | FK46: 5 | FL46: 0 | FM46: 41 | FO46: 1422401 | FP46: J MHC MEDIO OXF | FQ46: Ventas | FS46: 2 | FT46: 6 | FU46: 10 | FV46: 10 | FW46: 8 | FX46: 5 | FY46: 0 | FZ46: 41 | GB46: 1422401 | GC46: J MHC MEDIO OXF | GD46: Ventas | GF46: 0 | GG46: 4 | GH46: 8 | GI46: 8 | GJ46: 7 | GK46: 5 | GL46: 0 | GM46: 32 | GO46: 1422401 | GP46: J MHC MEDIO OXF | GQ46: Ventas | GS46: 0 | GT46: 4 | GU46: 8 | GV46: 8 | GW46: 7 | GX46: 5 | GY46: 0 | GZ46: =SUM(GS46:GY46) -> 32
A47: 1422300 | B47: B2868-V3 | C47: 46 | D47: 84 | E47: 92 | F47: 83 | G47: 50 | H47: 42 | J47: =SUM(C47:H47) -> 397 | K47: ='CORTE 4200'!$O$403 -> -169 | L47: 50 | O47: 1422300 | P47: J MHC MEDIO FL | Q47: Ventas | S47: 46 | T47: 84 | U47: 92 | V47: 83 | W47: 50 | X47: 42 | Y47: 0 | Z47: =SUM(S47:Y47) -> 397 | AB47: 1422300 | AC47: J MHC MEDIO FL | AD47: Ventas | AF47: 46 | AG47: 84 | AH47: 92 | AI47: 83 | AJ47: 50 | AK47: 42 | AL47: 0 | AM47: =SUM(AF47:AL47) -> 397 | AO47: 1422300 | AP47: J MHC MEDIO FL | AQ47: Ventas | AS47: 44 | AT47: 81 | AU47: 89 | AV47: 81 | AW47: 48 | AX47: 40 | AY47: 0 | AZ47: =SUM(AS47:AY47) -> 383 | BB47: 1422300 | BC47: J MHC MEDIO FL | BD47: Ventas | BF47: 43 | BG47: 79 | BH47: 86 | BI47: 79 | BJ47: 47 | BK47: 39 | BL47: 0 | BM47: =SUM(BF47:BL47) -> 373 | BO47: 1422300 | BP47: J MHC MEDIO FL | BQ47: Ventas | BS47: 35 | BT47: 67 | BU47: 74 | BV47: 67 | BW47: 44 | BX47: 36 | BY47: 0 | BZ47: =SUM(BS47:BY47) -> 323 | CB47: 1422300 | CC47: J MHC MEDIO FL | CD47: Ventas | CF47: 34 | CG47: 65 | CH47: 72 | CI47: 65 | CJ47: 43 | CK47: 35 | CL47: 0 | CM47: =SUM(CF47:CL47) -> 314 | CO47: 1422300 | CP47: J MHC MEDIO FL | CQ47: Ventas | CS47: 34 | CT47: 65 | CU47: 72 | CV47: 65 | CW47: 43 | CX47: 35 | CY47: 0 | CZ47: 314 | DB47: 1422300 | DC47: J MHC MEDIO FL | DD47: Ventas | DF47: 32 | DG47: 61 | DH47: 66 | DI47: 61 | DJ47: 39 | DK47: 32 | DL47: 0 | DM47: 291 | DO47: 1422300 | DP47: J MHC MEDIO FL | DQ47: Ventas | DS47: 29 | DT47: 56 | DU47: 61 | DV47: 58 | DW47: 39 | DX47: 32 | DY47: 0 | DZ47: 275 | EB47: 1422300 | EC47: J MHC MEDIO FL | ED47: Ventas | EF47: 29 | EG47: 56 | EH47: 61 | EI47: 58 | EJ47: 39 | EK47: 32 | EL47: 0 | EM47: 275 | EO47: 1422400 | EP47: J MHC MEDIO OXF | EQ47: Ventas | ES47: 8 | ET47: 14 | EU47: 17 | EV47: 15 | EW47: 13 | EX47: 8 | EY47: 0 | EZ47: 75 | FB47: 1422500 | FC47: J MHC CINTURA F | FD47: Ventas | FF47: 26 | FG47: 59 | FH47: 61 | FI47: 59 | FJ47: 41 | FK47: 38 | FL47: 0 | FM47: 284 | FO47: 1422500 | FP47: J MHC CINTURA F | FQ47: Ventas | FS47: 24 | FT47: 53 | FU47: 55 | FV47: 53 | FW47: 37 | FX47: 34 | FY47: 0 | FZ47: 256 | GB47: 1422500 | GC47: J MHC CINTURA F | GD47: Ventas | GF47: 10 | GG47: 14 | GH47: 16 | GI47: 15 | GJ47: 12 | GK47: 10 | GL47: 0 | GM47: 77 | GO47: 1422500 | GP47: J MHC CINTURA F | GQ47: Ventas | GS47: 8 | GT47: 12 | GU47: 14 | GV47: 13 | GW47: 10 | GX47: 8 | GY47: 0 | GZ47: =SUM(GS47:GY47) -> 65
A48: 1422400 | B48: Ayla | C48: 10 | D48: 21 | E48: 24 | F48: 20 | G48: 17 | H48: 11 | J48: =SUM(C48:H48) -> 103 | K48: ='CORTE 4200'!$O$412 -> -35 | M48: Girar | O48: 1422400 | P48: J MHC MEDIO OXF | Q48: Ventas | S48: 10 | T48: 21 | U48: 24 | V48: 20 | W48: 17 | X48: 11 | Y48: 0 | Z48: =SUM(S48:Y48) -> 103 | AB48: 1422400 | AC48: J MHC MEDIO OXF | AD48: Ventas | AF48: 10 | AG48: 21 | AH48: 24 | AI48: 20 | AJ48: 17 | AK48: 11 | AL48: 0 | AM48: =SUM(AF48:AL48) -> 103 | AO48: 1422400 | AP48: J MHC MEDIO OXF | AQ48: Ventas | AS48: 10 | AT48: 21 | AU48: 24 | AV48: 20 | AW48: 17 | AX48: 11 | AY48: 0 | AZ48: =SUM(AS48:AY48) -> 103 | BB48: 1422400 | BC48: J MHC MEDIO OXF | BD48: Ventas | BF48: 10 | BG48: 21 | BH48: 24 | BI48: 20 | BJ48: 17 | BK48: 11 | BL48: 0 | BM48: =SUM(BF48:BL48) -> 103 | BO48: 1422400 | BP48: J MHC MEDIO OXF | BQ48: Ventas | BS48: 10 | BT48: 21 | BU48: 24 | BV48: 20 | BW48: 17 | BX48: 11 | BY48: 0 | BZ48: =SUM(BS48:BY48) -> 103 | CB48: 1422400 | CC48: J MHC MEDIO OXF | CD48: Ventas | CF48: 10 | CG48: 21 | CH48: 24 | CI48: 20 | CJ48: 17 | CK48: 11 | CL48: 0 | CM48: =SUM(CF48:CL48) -> 103 | CO48: 1422400 | CP48: J MHC MEDIO OXF | CQ48: Ventas | CS48: 10 | CT48: 21 | CU48: 24 | CV48: 20 | CW48: 17 | CX48: 11 | CY48: 0 | CZ48: 103 | DB48: 1422400 | DC48: J MHC MEDIO OXF | DD48: Ventas | DF48: 8 | DG48: 15 | DH48: 18 | DI48: 16 | DJ48: 13 | DK48: 8 | DL48: 0 | DM48: 78 | DO48: 1422400 | DP48: J MHC MEDIO OXF | DQ48: Ventas | DS48: 8 | DT48: 14 | DU48: 17 | DV48: 15 | DW48: 13 | DX48: 8 | DY48: 0 | DZ48: 75 | EB48: 1422400 | EC48: J MHC MEDIO OXF | ED48: Ventas | EF48: 8 | EG48: 14 | EH48: 17 | EI48: 15 | EJ48: 13 | EK48: 8 | EL48: 0 | EM48: 75 | EO48: 1422401 | EP48: J MHC MEDIO OXF | EQ48: Ventas | ES48: 5 | ET48: 9 | EU48: 13 | EV48: 12 | EW48: 10 | EX48: 7 | EY48: 0 | EZ48: 56 | FB48: 1422501 | FC48: J MHC CINTURA F | FD48: Ventas | FF48: 0 | FG48: 4 | FH48: 8 | FI48: 8 | FJ48: 7 | FK48: 5 | FL48: 0 | FM48: 32 | FO48: 1422501 | FP48: J MHC CINTURA F | FQ48: Ventas | FS48: 0 | FT48: 4 | FU48: 8 | FV48: 8 | FW48: 7 | FX48: 5 | FY48: 0 | FZ48: 32 | GB48: 1422501 | GC48: J MHC CINTURA F | GD48: Ventas | GF48: 0 | GG48: 4 | GH48: 8 | GI48: 8 | GJ48: 7 | GK48: 5 | GL48: 0 | GM48: 32 | GO48: 1422501 | GP48: J MHC CINTURA F | GQ48: Ventas | GS48: 0 | GT48: 4 | GU48: 8 | GV48: 8 | GW48: 7 | GX48: 5 | GY48: 0 | GZ48: =SUM(GS48:GY48) -> 32
A49: 1422401 | B49: Ayla | C49: 5 | D49: 9 | E49: 13 | F49: 12 | G49: 10 | H49: 7 | J49: =SUM(C49:H49) -> 56 | K49: ='CORTE 4200'!$O$421 -> -6 | M49: Girar | O49: 1422401 | P49: J MHC MEDIO OXF | Q49: Ventas | S49: 5 | T49: 9 | U49: 13 | V49: 12 | W49: 10 | X49: 7 | Y49: 0 | Z49: =SUM(S49:Y49) -> 56 | AB49: 1422401 | AC49: J MHC MEDIO OXF | AD49: Ventas | AF49: 5 | AG49: 9 | AH49: 13 | AI49: 12 | AJ49: 10 | AK49: 7 | AL49: 0 | AM49: =SUM(AF49:AL49) -> 56 | AO49: 1422401 | AP49: J MHC MEDIO OXF | AQ49: Ventas | AS49: 5 | AT49: 9 | AU49: 13 | AV49: 12 | AW49: 10 | AX49: 7 | AY49: 0 | AZ49: =SUM(AS49:AY49) -> 56 | BB49: 1422401 | BC49: J MHC MEDIO OXF | BD49: Ventas | BF49: 5 | BG49: 9 | BH49: 13 | BI49: 12 | BJ49: 10 | BK49: 7 | BL49: 0 | BM49: =SUM(BF49:BL49) -> 56 | BO49: 1422401 | BP49: J MHC MEDIO OXF | BQ49: Ventas | BS49: 5 | BT49: 9 | BU49: 13 | BV49: 12 | BW49: 10 | BX49: 7 | BY49: 0 | BZ49: =SUM(BS49:BY49) -> 56 | CB49: 1422401 | CC49: J MHC MEDIO OXF | CD49: Ventas | CF49: 5 | CG49: 9 | CH49: 13 | CI49: 12 | CJ49: 10 | CK49: 7 | CL49: 0 | CM49: =SUM(CF49:CL49) -> 56 | CO49: 1422401 | CP49: J MHC MEDIO OXF | CQ49: Ventas | CS49: 5 | CT49: 9 | CU49: 13 | CV49: 12 | CW49: 10 | CX49: 7 | CY49: 0 | CZ49: 56 | DB49: 1422401 | DC49: J MHC MEDIO OXF | DD49: Ventas | DF49: 5 | DG49: 9 | DH49: 13 | DI49: 12 | DJ49: 10 | DK49: 7 | DL49: 0 | DM49: 56 | DO49: 1422401 | DP49: J MHC MEDIO OXF | DQ49: Ventas | DS49: 5 | DT49: 9 | DU49: 13 | DV49: 12 | DW49: 10 | DX49: 7 | DY49: 0 | DZ49: 56 | EB49: 1422401 | EC49: J MHC MEDIO OXF | ED49: Ventas | EF49: 5 | EG49: 9 | EH49: 13 | EI49: 12 | EJ49: 10 | EK49: 7 | EL49: 0 | EM49: 56 | EO49: 1422500 | EP49: J MHC CINTURA F | EQ49: Ventas | ES49: 27 | ET49: 63 | EU49: 66 | EV49: 64 | EW49: 44 | EX49: 40 | EY49: 0 | EZ49: 304 | FB49: 1422600 | FC49: J MHC MEDIO PIT | FD49: Ventas | FF49: 35 | FG49: 79 | FH49: 86 | FI49: 81 | FJ49: 59 | FK49: 47 | FL49: 0 | FM49: 387 | FO49: 1422600 | FP49: J MHC MEDIO PIT | FQ49: Ventas | FS49: 33 | FT49: 73 | FU49: 80 | FV49: 75 | FW49: 55 | FX49: 43 | FY49: 0 | FZ49: 359 | GB49: 1422600 | GC49: J MHC MEDIO PIT | GD49: Ventas | GF49: 19 | GG49: 36 | GH49: 43 | GI49: 38 | GJ49: 30 | GK49: 21 | GL49: 0 | GM49: 187 | GO49: 1422600 | GP49: J MHC MEDIO PIT | GQ49: Ventas | GS49: 18 | GT49: 33 | GU49: 39 | GV49: 35 | GW49: 28 | GX49: 20 | GY49: 0 | GZ49: =SUM(GS49:GY49) -> 173
A50: 1422500 | B50: B2868-V3 | C50: 50 | D50: 99 | E50: 103 | F50: 102 | G50: 65 | H50: 57 | J50: =SUM(C50:H50) -> 476 | K50: ='CORTE 4200'!$O$430 -> -269 | L50: 50 | O50: 1422500 | P50: J MHC CINTURA F | Q50: Ventas | S50: 50 | T50: 99 | U50: 103 | V50: 102 | W50: 65 | X50: 57 | Y50: 0 | Z50: =SUM(S50:Y50) -> 476 | AB50: 1422500 | AC50: J MHC CINTURA F | AD50: Ventas | AF50: 48 | AG50: 95 | AH50: 99 | AI50: 98 | AJ50: 63 | AK50: 55 | AL50: 0 | AM50: =SUM(AF50:AL50) -> 458 | AO50: 1422500 | AP50: J MHC CINTURA F | AQ50: Ventas | AS50: 45 | AT50: 90 | AU50: 94 | AV50: 93 | AW50: 59 | AX50: 51 | AY50: 0 | AZ50: =SUM(AS50:AY50) -> 432 | BB50: 1422500 | BC50: J MHC CINTURA F | BD50: Ventas | BF50: 45 | BG50: 90 | BH50: 94 | BI50: 93 | BJ50: 59 | BK50: 51 | BL50: 0 | BM50: =SUM(BF50:BL50) -> 432 | BO50: 1422500 | BP50: J MHC CINTURA F | BQ50: Ventas | BS50: 37 | BT50: 78 | BU50: 82 | BV50: 81 | BW50: 56 | BX50: 48 | BY50: 0 | BZ50: =SUM(BS50:BY50) -> 382 | CB50: 1422500 | CC50: J MHC CINTURA F | CD50: Ventas | CF50: 37 | CG50: 78 | CH50: 82 | CI50: 81 | CJ50: 56 | CK50: 48 | CL50: 0 | CM50: =SUM(CF50:CL50) -> 382 | CO50: 1422500 | CP50: J MHC CINTURA F | CQ50: Ventas | CS50: 37 | CT50: 76 | CU50: 80 | CV50: 78 | CW50: 53 | CX50: 46 | CY50: 0 | CZ50: 370 | DB50: 1422500 | DC50: J MHC CINTURA F | DD50: Ventas | DF50: 34 | DG50: 71 | DH50: 74 | DI50: 70 | DJ50: 48 | DK50: 42 | DL50: 0 | DM50: 339 | DO50: 1422500 | DP50: J MHC CINTURA F | DQ50: Ventas | DS50: 31 | DT50: 67 | DU50: 70 | DV50: 67 | DW50: 46 | DX50: 42 | DY50: 0 | DZ50: 323 | EB50: 1422500 | EC50: J MHC CINTURA F | ED50: Ventas | EF50: 29 | EG50: 65 | EH50: 68 | EI50: 65 | EJ50: 45 | EK50: 41 | EL50: 0 | EM50: 313 | EO50: 1422501 | EP50: J MHC CINTURA F | EQ50: Ventas | ES50: 0 | ET50: 4 | EU50: 8 | EV50: 8 | EW50: 7 | EX50: 5 | EY50: 0 | EZ50: 32 | FB50: 1422601 | FC50: J MHC MEDIO PIT | FD50: Ventas | FF50: 21 | FG50: 29 | FH50: 36 | FI50: 33 | FJ50: 26 | FK50: 19 | FL50: 0 | FM50: 164 | FO50: 1422601 | FP50: J MHC MEDIO PIT | FQ50: Ventas | FS50: 21 | FT50: 29 | FU50: 36 | FV50: 33 | FW50: 26 | FX50: 19 | FY50: 0 | FZ50: 164 | GB50: 1422601 | GC50: J MHC MEDIO PIT | GD50: Ventas | GF50: 21 | GG50: 29 | GH50: 36 | GI50: 33 | GJ50: 26 | GK50: 19 | GL50: 0 | GM50: 164 | GO50: 1422601 | GP50: J MHC MEDIO PIT | GQ50: Ventas | GS50: 18 | GT50: 24 | GU50: 29 | GV50: 27 | GW50: 22 | GX50: 16 | GY50: 0 | GZ50: =SUM(GS50:GY50) -> 136
A51: 1422501 | B51: B2868-V3 | C51: 0 | D51: 4 | E51: 8 | F51: 8 | G51: 7 | H51: 5 | J51: =SUM(C51:H51) -> 32 | K51: ='CORTE 4200'!$O$439 -> 32 | O51: 1422501 | P51: J MHC CINTURA F | Q51: Ventas | S51: 0 | T51: 4 | U51: 8 | V51: 8 | W51: 7 | X51: 5 | Y51: 0 | Z51: =SUM(S51:Y51) -> 32 | AB51: 1422501 | AC51: J MHC CINTURA F | AD51: Ventas | AF51: 0 | AG51: 4 | AH51: 8 | AI51: 8 | AJ51: 7 | AK51: 5 | AL51: 0 | AM51: =SUM(AF51:AL51) -> 32 | AO51: 1422501 | AP51: J MHC CINTURA F | AQ51: Ventas | AS51: 0 | AT51: 4 | AU51: 8 | AV51: 8 | AW51: 7 | AX51: 5 | AY51: 0 | AZ51: =SUM(AS51:AY51) -> 32 | BB51: 1422501 | BC51: J MHC CINTURA F | BD51: Ventas | BF51: 0 | BG51: 4 | BH51: 8 | BI51: 8 | BJ51: 7 | BK51: 5 | BL51: 0 | BM51: =SUM(BF51:BL51) -> 32 | BO51: 1422501 | BP51: J MHC CINTURA F | BQ51: Ventas | BS51: 0 | BT51: 4 | BU51: 8 | BV51: 8 | BW51: 7 | BX51: 5 | BY51: 0 | BZ51: =SUM(BS51:BY51) -> 32 | CB51: 1422501 | CC51: J MHC CINTURA F | CD51: Ventas | CF51: 0 | CG51: 4 | CH51: 8 | CI51: 8 | CJ51: 7 | CK51: 5 | CL51: 0 | CM51: =SUM(CF51:CL51) -> 32 | CO51: 1422501 | CP51: J MHC CINTURA F | CQ51: Ventas | CS51: 0 | CT51: 4 | CU51: 8 | CV51: 8 | CW51: 7 | CX51: 5 | CY51: 0 | CZ51: 32 | DB51: 1422501 | DC51: J MHC CINTURA F | DD51: Ventas | DF51: 0 | DG51: 4 | DH51: 8 | DI51: 8 | DJ51: 7 | DK51: 5 | DL51: 0 | DM51: 32 | DO51: 1422501 | DP51: J MHC CINTURA F | DQ51: Ventas | DS51: 0 | DT51: 4 | DU51: 8 | DV51: 8 | DW51: 7 | DX51: 5 | DY51: 0 | DZ51: 32 | EB51: 1422501 | EC51: J MHC CINTURA F | ED51: Ventas | EF51: 0 | EG51: 4 | EH51: 8 | EI51: 8 | EJ51: 7 | EK51: 5 | EL51: 0 | EM51: 32 | EO51: 1422600 | EP51: J MHC MEDIO PIT | EQ51: Ventas | ES51: 38 | ET51: 85 | EU51: 93 | EV51: 88 | EW51: 65 | EX51: 51 | EY51: 0 | EZ51: 420 | FB51: 1422700 | FC51: J MHC CINT.RECT | FD51: Ventas | FF51: 27 | FG51: 66 | FH51: 70 | FI51: 68 | FJ51: 50 | FK51: 40 | FL51: 0 | FM51: 321 | FO51: 1422700 | FP51: J MHC CINT.RECT | FQ51: Ventas | FS51: 27 | FT51: 66 | FU51: 70 | FV51: 68 | FW51: 50 | FX51: 40 | FY51: 0 | FZ51: 321 | GB51: 1422700 | GC51: J MHC CINT.RECT | GD51: Ventas | GF51: 14 | GG51: 30 | GH51: 34 | GI51: 32 | GJ51: 24 | GK51: 15 | GL51: 0 | GM51: 149 | GO51: 1422700 | GP51: J MHC CINT.RECT | GQ51: Ventas | GS51: 11 | GT51: 25 | GU51: 27 | GV51: 26 | GW51: 20 | GX51: 12 | GY51: 0 | GZ51: =SUM(GS51:GY51) -> 121
A52: 1422600 | B52: Ibiza Blue | C52: 51 | D52: 113 | E52: 127 | F52: 120 | G52: 81 | H52: 59 | J52: =SUM(C52:H52) -> 551 | K52: ='CORTE 4200'!$O$448 -> 2 | L52: 50 | O52: 1422600 | P52: J MHC MEDIO PIT | Q52: Ventas | S52: 51 | T52: 113 | U52: 127 | V52: 120 | W52: 81 | X52: 59 | Y52: 0 | Z52: =SUM(S52:Y52) -> 551 | AB52: 1422600 | AC52: J MHC MEDIO PIT | AD52: Ventas | AF52: 51 | AG52: 113 | AH52: 125 | AI52: 118 | AJ52: 80 | AK52: 59 | AL52: 0 | AM52: =SUM(AF52:AL52) -> 546 | AO52: 1422600 | AP52: J MHC MEDIO PIT | AQ52: Ventas | AS52: 51 | AT52: 113 | AU52: 125 | AV52: 118 | AW52: 80 | AX52: 59 | AY52: 0 | AZ52: =SUM(AS52:AY52) -> 546 | BB52: 1422600 | BC52: J MHC MEDIO PIT | BD52: Ventas | BF52: 41 | BG52: 96 | BH52: 107 | BI52: 102 | BJ52: 75 | BK52: 55 | BL52: 0 | BM52: =SUM(BF52:BL52) -> 476 | BO52: 1422600 | BP52: J MHC MEDIO PIT | BQ52: Ventas | BS52: 41 | BT52: 96 | BU52: 107 | BV52: 102 | BW52: 75 | BX52: 55 | BY52: 0 | BZ52: =SUM(BS52:BY52) -> 476 | CB52: 1422600 | CC52: J MHC MEDIO PIT | CD52: Ventas | CF52: 41 | CG52: 96 | CH52: 107 | CI52: 102 | CJ52: 75 | CK52: 55 | CL52: 0 | CM52: =SUM(CF52:CL52) -> 476 | CO52: 1422600 | CP52: J MHC MEDIO PIT | CQ52: Ventas | CS52: 41 | CT52: 92 | CU52: 103 | CV52: 98 | CW52: 72 | CX52: 54 | CY52: 0 | CZ52: 460 | DB52: 1422600 | DC52: J MHC MEDIO PIT | DD52: Ventas | DF52: 39 | DG52: 88 | DH52: 99 | DI52: 94 | DJ52: 68 | DK52: 53 | DL52: 0 | DM52: 441 | DO52: 1422600 | DP52: J MHC MEDIO PIT | DQ52: Ventas | DS52: 39 | DT52: 87 | DU52: 95 | DV52: 90 | DW52: 66 | DX52: 52 | DY52: 0 | DZ52: 429 | EB52: 1422600 | EC52: J MHC MEDIO PIT | ED52: Ventas | EF52: 39 | EG52: 87 | EH52: 95 | EI52: 90 | EJ52: 66 | EK52: 52 | EL52: 0 | EM52: 429 | EO52: 1422601 | EP52: J MHC MEDIO PIT | EQ52: Ventas | ES52: 22 | ET52: 31 | EU52: 38 | EV52: 35 | EW52: 28 | EX52: 20 | EY52: 0 | EZ52: 174 | FB52: 1422701 | FC52: J MHC CINTURA R | FD52: Ventas | FF52: 30 | FG52: 76 | FH52: 79 | FI52: 77 | FJ52: 57 | FK52: 46 | FL52: 0 | FM52: 365 | FO52: 1422701 | FP52: J MHC CINTURA R | FQ52: Ventas | FS52: 28 | FT52: 70 | FU52: 73 | FV52: 71 | FW52: 53 | FX52: 42 | FY52: 0 | FZ52: 337 | GB52: 1422701 | GC52: J MHC CINTURA R | GD52: Ventas | GF52: 13 | GG52: 25 | GH52: 27 | GI52: 25 | GJ52: 21 | GK52: 14 | GL52: 0 | GM52: 125 | GO52: 1422701 | GP52: J MHC CINTURA R | GQ52: Ventas | GS52: 10 | GT52: 20 | GU52: 20 | GV52: 19 | GW52: 17 | GX52: 11 | GY52: 0 | GZ52: =SUM(GS52:GY52) -> 97
A53: 1422601 | B53: Ibiza Blue | C53: 32 | D53: 51 | E53: 58 | F53: 51 | G53: 39 | H53: 24 | J53: =SUM(C53:H53) -> 255 | K53: ='CORTE 4200'!$O$457 -> 49 | O53: 1422601 | P53: J MHC MEDIO PIT | Q53: Ventas | S53: 32 | T53: 51 | U53: 58 | V53: 51 | W53: 39 | X53: 24 | Y53: 0 | Z53: =SUM(S53:Y53) -> 255 | AB53: 1422601 | AC53: J MHC MEDIO PIT | AD53: Ventas | AF53: 35 | AG53: 57 | AH53: 63 | AI53: 54 | AJ53: 40 | AK53: 24 | AL53: 0 | AM53: =SUM(AF53:AL53) -> 273 | AO53: 1422601 | AP53: J MHC MEDIO PIT | AQ53: Ventas | AS53: 35 | AT53: 57 | AU53: 63 | AV53: 54 | AW53: 40 | AX53: 24 | AY53: 0 | AZ53: =SUM(AS53:AY53) -> 273 | BB53: 1422601 | BC53: J MHC MEDIO PIT | BD53: Ventas | BF53: 34 | BG53: 54 | BH53: 60 | BI53: 52 | BJ53: 39 | BK53: 24 | BL53: 0 | BM53: =SUM(BF53:BL53) -> 263 | BO53: 1422601 | BP53: J MHC MEDIO PIT | BQ53: Ventas | BS53: 34 | BT53: 54 | BU53: 60 | BV53: 52 | BW53: 39 | BX53: 24 | BY53: 0 | BZ53: =SUM(BS53:BY53) -> 263 | CB53: 1422601 | CC53: J MHC MEDIO PIT | CD53: Ventas | CF53: 34 | CG53: 54 | CH53: 60 | CI53: 52 | CJ53: 39 | CK53: 24 | CL53: 0 | CM53: =SUM(CF53:CL53) -> 263 | CO53: 1422601 | CP53: J MHC MEDIO PIT | CQ53: Ventas | CS53: 33 | CT53: 51 | CU53: 57 | CV53: 49 | CW53: 37 | CX53: 23 | CY53: 0 | CZ53: 250 | DB53: 1422601 | DC53: J MHC MEDIO PIT | DD53: Ventas | DF53: 32 | DG53: 47 | DH53: 53 | DI53: 46 | DJ53: 34 | DK53: 21 | DL53: 0 | DM53: 233 | DO53: 1422601 | DP53: J MHC MEDIO PIT | DQ53: Ventas | DS53: 27 | DT53: 40 | DU53: 46 | DV53: 41 | DW53: 31 | DX53: 21 | DY53: 0 | DZ53: 206 | EB53: 1422601 | EC53: J MHC MEDIO PIT | ED53: Ventas | EF53: 24 | EG53: 34 | EH53: 41 | EI53: 38 | EJ53: 30 | EK53: 21 | EL53: 0 | EM53: 188 | EO53: 1422700 | EP53: J MHC CINT.RECT | EQ53: Ventas | ES53: 30 | ET53: 72 | EU53: 76 | EV53: 73 | EW53: 51 | EX53: 40 | EY53: 0 | EZ53: 342 | FB53: 1422702 | FC53: J MHC CINTURA R | FD53: Ventas | FF53: 2 | FG53: 3 | FH53: 2 | FI53: 2 | FJ53: 2 | FK53: 1 | FL53: 0 | FM53: 12 | FO53: 1422800 | FP53: J MHC MEDIO FLA | FQ53: Ventas | FS53: 34 | FT53: 49 | FU53: 49 | FV53: 47 | FW53: 34 | FX53: 24 | FY53: 0 | FZ53: 237 | GB53: 1422800 | GC53: J MHC MEDIO FLA | GD53: Ventas | GF53: 24 | GG53: 32 | GH53: 31 | GI53: 30 | GJ53: 22 | GK53: 14 | GL53: 0 | GM53: 153 | GO53: 1422800 | GP53: J MHC MEDIO FLA | GQ53: Ventas | GS53: 23 | GT53: 29 | GU53: 27 | GV53: 27 | GW53: 20 | GX53: 13 | GY53: 0 | GZ53: =SUM(GS53:GY53) -> 139
A54: 1422700 | B54: New Glue | C54: 43 | D54: 103 | E54: 110 | F54: 105 | G54: 77 | H54: 56 | J54: =SUM(C54:H54) -> 494 | K54: ='CORTE 4200'!$O$466 -> 1 | O54: 1422700 | P54: J MHC CINT.RECT | Q54: Ventas | S54: 43 | T54: 103 | U54: 110 | V54: 105 | W54: 77 | X54: 56 | Z54: =SUM(S54:Y54) -> 494 | AB54: 1422700 | AC54: J MHC CINT.RECT | AD54: Ventas | AF54: 44 | AG54: 105 | AH54: 112 | AI54: 105 | AJ54: 77 | AK54: 55 | AM54: =SUM(AF54:AL54) -> 498 | AO54: 1422700 | AP54: J MHC CINT.RECT | AQ54: Ventas | AS54: 42 | AT54: 102 | AU54: 109 | AV54: 103 | AW54: 75 | AX54: 53 | AZ54: =SUM(AS54:AY54) -> 484 | BB54: 1422700 | BC54: J MHC CINT.RECT | BD54: Ventas | BF54: 42 | BG54: 102 | BH54: 109 | BI54: 103 | BJ54: 75 | BK54: 53 | BM54: =SUM(BF54:BL54) -> 484 | BO54: 1422700 | BP54: J MHC CINT.RECT | BQ54: Ventas | BS54: 42 | BT54: 102 | BU54: 109 | BV54: 103 | BW54: 75 | BX54: 53 | BZ54: =SUM(BS54:BY54) -> 484 | CB54: 1422700 | CC54: J MHC CINT.RECT | CD54: Ventas | CF54: 42 | CG54: 102 | CH54: 109 | CI54: 103 | CJ54: 75 | CK54: 53 | CM54: =SUM(CF54:CL54) -> 484 | CO54: 1422700 | CP54: J MHC CINT.RECT | CQ54: Ventas | CS54: 42 | CT54: 97 | CU54: 102 | CV54: 96 | CW54: 69 | CX54: 50 | CY54: 0 | CZ54: 456 | DB54: 1422700 | DC54: J MHC CINT.RECT | DD54: Ventas | DF54: 39 | DG54: 89 | DH54: 94 | DI54: 88 | DJ54: 61 | DK54: 44 | DL54: 0 | DM54: 415 | DO54: 1422700 | DP54: J MHC CINT.RECT | DQ54: Ventas | DS54: 36 | DT54: 83 | DU54: 87 | DV54: 82 | DW54: 56 | DX54: 42 | DY54: 0 | DZ54: 386 | EB54: 1422700 | EC54: J MHC CINT.RECT | ED54: Ventas | EF54: 32 | EG54: 75 | EH54: 79 | EI54: 76 | EJ54: 53 | EK54: 41 | EL54: 0 | EM54: 356 | EO54: 1422701 | EP54: J MHC CINTURA R | EQ54: Ventas | ES54: 35 | ET54: 86 | EU54: 89 | EV54: 87 | EW54: 65 | EX54: 51 | EY54: 0 | EZ54: 413 | FB54: 1422800 | FC54: J MHC MEDIO FLA | FD54: Ventas | FF54: 36 | FG54: 55 | FH54: 55 | FI54: 53 | FJ54: 38 | FK54: 28 | FL54: 0 | FM54: 265 | FO54: 1422900 | FP54: J MHC CINTURA P | FQ54: Ventas | FS54: 33 | FT54: 67 | FU54: 74 | FV54: 71 | FW54: 50 | FX54: 43 | FY54: 0 | FZ54: 338 | GB54: 1422900 | GC54: J MHC CINTURA P | GD54: Ventas | GF54: 22 | GG54: 30 | GH54: 35 | GI54: 33 | GJ54: 25 | GK54: 19 | GL54: 0 | GM54: 164 | GO54: 1422900 | GP54: J MHC CINTURA P | GQ54: Ventas | GS54: 19 | GT54: 25 | GU54: 28 | GV54: 27 | GW54: 21 | GX54: 16 | GY54: 0 | GZ54: =SUM(GS54:GY54) -> 136
A55: 1422701 | B55: New Glue | C55: 41 | D55: 101 | E55: 109 | F55: 108 | G55: 79 | H55: 61 | J55: =SUM(C55:H55) -> 499 | K55: ='CORTE 4200'!$O$475 -> -4 | O55: 1422701 | P55: J MHC CINTURA R | Q55: Ventas | S55: 41 | T55: 101 | U55: 109 | V55: 108 | W55: 79 | X55: 61 | Y55: 0 | Z55: =SUM(S55:Y55) -> 499 | AB55: 1422701 | AC55: J MHC CINTURA R | AD55: Ventas | AF55: 43 | AG55: 105 | AH55: 114 | AI55: 111 | AJ55: 80 | AK55: 62 | AL55: 0 | AM55: =SUM(AF55:AL55) -> 515 | AO55: 1422701 | AP55: J MHC CINTURA R | AQ55: Ventas | AS55: 43 | AT55: 105 | AU55: 114 | AV55: 111 | AW55: 80 | AX55: 62 | AY55: 0 | AZ55: =SUM(AS55:AY55) -> 515 | BB55: 1422701 | BC55: J MHC CINTURA R | BD55: Ventas | BF55: 42 | BG55: 102 | BH55: 111 | BI55: 109 | BJ55: 79 | BK55: 62 | BL55: 0 | BM55: =SUM(BF55:BL55) -> 505 | BO55: 1422701 | BP55: J MHC CINTURA R | BQ55: Ventas | BS55: 42 | BT55: 102 | BU55: 111 | BV55: 109 | BW55: 79 | BX55: 62 | BY55: 0 | BZ55: =SUM(BS55:BY55) -> 505 | CB55: 1422701 | CC55: J MHC CINTURA R | CD55: Ventas | CF55: 42 | CG55: 102 | CH55: 111 | CI55: 109 | CJ55: 79 | CK55: 62 | CL55: 0 | CM55: =SUM(CF55:CL55) -> 505 | CO55: 1422701 | CP55: J MHC CINTURA R | CQ55: Ventas | CS55: 42 | CT55: 102 | CU55: 111 | CV55: 109 | CW55: 79 | CX55: 62 | CY55: 0 | CZ55: 505 | DB55: 1422701 | DC55: J MHC CINTURA R | DD55: Ventas | DF55: 42 | DG55: 101 | DH55: 107 | DI55: 103 | DJ55: 73 | DK55: 56 | DL55: 0 | DM55: 482 | DO55: 1422701 | DP55: J MHC CINTURA R | DQ55: Ventas | DS55: 42 | DT55: 99 | DU55: 102 | DV55: 98 | DW55: 71 | DX55: 55 | DY55: 0 | DZ55: 467 | EB55: 1422701 | EC55: J MHC CINTURA R | ED55: Ventas | EF55: 36 | EG55: 88 | EH55: 91 | EI55: 89 | EJ55: 66 | EK55: 52 | EL55: 0 | EM55: 422 | EO55: 1422702 | EP55: J MHC CINTURA R | EQ55: Ventas | ES55: 2 | ET55: 3 | EU55: 2 | EV55: 2 | EW55: 2 | EX55: 1 | EY55: 0 | EZ55: 12 | FB55: 1422900 | FC55: J MHC CINTURA P | FD55: Ventas | FF55: 35 | FG55: 73 | FH55: 80 | FI55: 77 | FJ55: 54 | FK55: 47 | FL55: 0 | FM55: 366 | FO55: 1423000 | FP55: J MHC CINTURA P | FQ55: Ventas | FS55: 19 | FT55: 28 | FU55: 28 | FV55: 26 | FW55: 19 | FX55: 8 | FY55: 0 | FZ55: 128 | GB55: 1423000 | GC55: J MHC CINTURA P | GD55: Ventas | GF55: 19 | GG55: 28 | GH55: 28 | GI55: 26 | GJ55: 19 | GK55: 8 | GL55: 0 | GM55: 128 | GO55: 1423000 | GP55: J MHC CINTURA P | GQ55: Ventas | GS55: 16 | GT55: 23 | GU55: 21 | GV55: 20 | GW55: 15 | GX55: 5 | GY55: 0 | GZ55: =SUM(GS55:GY55) -> 100
A56: 1422702 | B56: New Glue | C56: 2 | D56: 3 | E56: 2 | F56: 2 | G56: 2 | H56: 1 | J56: =SUM(C56:H56) -> 12 | K56: ='CORTE 4200'!$O$484 -> 0 | O56: 1422702 | P56: J MHC CINTURA R | Q56: Ventas | S56: 2 | T56: 3 | U56: 2 | V56: 2 | W56: 2 | X56: 1 | Y56: 0 | Z56: =SUM(S56:Y56) -> 12 | AB56: 1422702 | AC56: J MHC CINTURA R | AD56: Ventas | AF56: 2 | AG56: 3 | AH56: 2 | AI56: 2 | AJ56: 2 | AK56: 1 | AL56: 0 | AM56: =SUM(AF56:AL56) -> 12 | AO56: 1422702 | AP56: J MHC CINTURA R | AQ56: Ventas | AS56: 2 | AT56: 3 | AU56: 2 | AV56: 2 | AW56: 2 | AX56: 1 | AY56: 0 | AZ56: =SUM(AS56:AY56) -> 12 | BB56: 1422702 | BC56: J MHC CINTURA R | BD56: Ventas | BF56: 2 | BG56: 3 | BH56: 2 | BI56: 2 | BJ56: 2 | BK56: 1 | BL56: 0 | BM56: =SUM(BF56:BL56) -> 12 | BO56: 1422702 | BP56: J MHC CINTURA R | BQ56: Ventas | BS56: 2 | BT56: 3 | BU56: 2 | BV56: 2 | BW56: 2 | BX56: 1 | BY56: 0 | BZ56: =SUM(BS56:BY56) -> 12 | CB56: 1422702 | CC56: J MHC CINTURA R | CD56: Ventas | CF56: 2 | CG56: 3 | CH56: 2 | CI56: 2 | CJ56: 2 | CK56: 1 | CL56: 0 | CM56: =SUM(CF56:CL56) -> 12 | CO56: 1422702 | CP56: J MHC CINTURA R | CQ56: Ventas | CS56: 2 | CT56: 3 | CU56: 2 | CV56: 2 | CW56: 2 | CX56: 1 | CY56: 0 | CZ56: 12 | DB56: 1422702 | DC56: J MHC CINTURA R | DD56: Ventas | DF56: 2 | DG56: 3 | DH56: 2 | DI56: 2 | DJ56: 2 | DK56: 1 | DL56: 0 | DM56: 12 | DO56: 1422702 | DP56: J MHC CINTURA R | DQ56: Ventas | DS56: 2 | DT56: 3 | DU56: 2 | DV56: 2 | DW56: 2 | DX56: 1 | DY56: 0 | DZ56: 12 | EB56: 1422702 | EC56: J MHC CINTURA R | ED56: Ventas | EF56: 2 | EG56: 3 | EH56: 2 | EI56: 2 | EJ56: 2 | EK56: 1 | EL56: 0 | EM56: 12 | EO56: 1422800 | EP56: J MHC MEDIO FLA | EQ56: Ventas | ES56: 40 | ET56: 63 | EU56: 63 | EV56: 61 | EW56: 44 | EX56: 30 | EY56: 0 | EZ56: 301 | FB56: 1423000 | FC56: J MHC CINTURA P | FD56: Ventas | FF56: 19 | FG56: 28 | FH56: 28 | FI56: 26 | FJ56: 19 | FK56: 8 | FL56: 0 | FM56: 128 | FO56: 1423200 | FP56: J MHC CINTURA O | FQ56: Ventas | FS56: 2 | FT56: 6 | FU56: 8 | FV56: 5 | FW56: 3 | FX56: 2 | FY56: 0 | FZ56: 26 | GB56: 1423200 | GC56: J MHC CINTURA O | GD56: Ventas | GF56: 1 | GG56: 3 | GH56: 3 | GI56: 2 | GJ56: 1 | GK56: 1 | GL56: 0 | GM56: 11 | GO56: 1423200 | GP56: J MHC CINTURA O | GQ56: Ventas | GS56: 1 | GT56: 3 | GU56: 3 | GV56: 2 | GW56: 1 | GX56: 1 | GY56: 0 | GZ56: =SUM(GS56:GY56) -> 11
A57: 1422800 | B57: B2868-V3 | C57: 56 | D57: 95 | E57: 97 | F57: 92 | G57: 67 | H57: 44 | J57: =SUM(C57:H57) -> 451 | K57: ='CORTE 4200'!$O$493 -> -99 | O57: 1422800 | P57: J MHC MEDIO FLA | Q57: Ventas | S57: 56 | T57: 95 | U57: 97 | V57: 92 | W57: 67 | X57: 44 | Y57: 0 | Z57: =SUM(S57:Y57) -> 451 | AB57: 1422800 | AC57: J MHC MEDIO FLA | AD57: Ventas | AF57: 58 | AG57: 99 | AH57: 101 | AI57: 94 | AJ57: 68 | AK57: 44 | AL57: 0 | AM57: =SUM(AF57:AL57) -> 464 | AO57: 1422800 | AP57: J MHC MEDIO FLA | AQ57: Ventas | AS57: 56 | AT57: 96 | AU57: 98 | AV57: 92 | AW57: 66 | AX57: 42 | AY57: 0 | AZ57: =SUM(AS57:AY57) -> 450 | BB57: 1422800 | BC57: J MHC MEDIO FLA | BD57: Ventas | BF57: 56 | BG57: 96 | BH57: 98 | BI57: 92 | BJ57: 66 | BK57: 42 | BL57: 0 | BM57: =SUM(BF57:BL57) -> 450 | BO57: 1422800 | BP57: J MHC MEDIO FLA | BQ57: Ventas | BS57: 56 | BT57: 96 | BU57: 98 | BV57: 92 | BW57: 66 | BX57: 42 | BY57: 0 | BZ57: =SUM(BS57:BY57) -> 450 | CB57: 1422800 | CC57: J MHC MEDIO FLA | CD57: Ventas | CF57: 54 | CG57: 93 | CH57: 95 | CI57: 89 | CJ57: 64 | CK57: 41 | CL57: 0 | CM57: =SUM(CF57:CL57) -> 436 | CO57: 1422800 | CP57: J MHC MEDIO FLA | CQ57: Ventas | CS57: 53 | CT57: 87 | CU57: 89 | CV57: 82 | CW57: 58 | CX57: 38 | CY57: 0 | CZ57: 407 | DB57: 1422800 | DC57: J MHC MEDIO FLA | DD57: Ventas | DF57: 50 | DG57: 82 | DH57: 84 | DI57: 78 | DJ57: 54 | DK57: 36 | DL57: 0 | DM57: 384 | DO57: 1422800 | DP57: J MHC MEDIO FLA | DQ57: Ventas | DS57: 47 | DT57: 75 | DU57: 76 | DV57: 72 | DW57: 51 | DX57: 34 | DY57: 0 | DZ57: 355 | EB57: 1422800 | EC57: J MHC MEDIO FLA | ED57: Ventas | EF57: 43 | EG57: 68 | EH57: 68 | EI57: 66 | EJ57: 48 | EK57: 33 | EL57: 0 | EM57: 326 | EO57: 1422900 | EP57: J MHC CINTURA P | EQ57: Ventas | ES57: 35 | ET57: 75 | EU57: 82 | EV57: 79 | EW57: 55 | EX57: 47 | EY57: 0 | EZ57: 373 | FB57: 1423200 | FC57: J MHC CINTURA O | FD57: Ventas | FF57: 2 | FG57: 6 | FH57: 8 | FI57: 5 | FJ57: 3 | FK57: 2 | FL57: 0 | FM57: 26 | GB57: 1423300 | GC57: J MHC CINTURA T | GD57: Ventas | GF57: 0 | GG57: 5 | GH57: 5 | GI57: 4 | GJ57: 3 | GK57: 1 | GL57: 0 | GM57: 18 | GO57: 1423300 | GP57: J MHC CINTURA T | GQ57: Ventas | GS57: 0 | GT57: 5 | GU57: 5 | GV57: 4 | GW57: 3 | GX57: 1 | GY57: 0 | GZ57: =SUM(GS57:GY57) -> 18
A58: 1422900 | B58: New Glue | C58: 43 | D58: 101 | E58: 110 | F58: 108 | G58: 79 | H58: 61 | J58: =SUM(C58:H58) -> 502 | K58: ='CORTE 4200'!$O$502 -> 8 | O58: 1422900 | P58: J MHC CINTURA P | Q58: Ventas | S58: 43 | T58: 101 | U58: 110 | V58: 108 | W58: 79 | X58: 61 | Y58: 0 | Z58: =SUM(S58:Y58) -> 502 | AB58: 1422900 | AC58: J MHC CINTURA P | AD58: Ventas | AF58: 43 | AG58: 101 | AH58: 110 | AI58: 108 | AJ58: 79 | AK58: 61 | AL58: 0 | AM58: =SUM(AF58:AL58) -> 502 | AO58: 1422900 | AP58: J MHC CINTURA P | AQ58: Ventas | AS58: 42 | AT58: 98 | AU58: 108 | AV58: 106 | AW58: 78 | AX58: 60 | AY58: 0 | AZ58: =SUM(AS58:AY58) -> 492 | BB58: 1422900 | BC58: J MHC CINTURA P | BD58: Ventas | BF58: 42 | BG58: 98 | BH58: 108 | BI58: 106 | BJ58: 78 | BK58: 60 | BL58: 0 | BM58: =SUM(BF58:BL58) -> 492 | BO58: 1422900 | BP58: J MHC CINTURA P | BQ58: Ventas | BS58: 42 | BT58: 98 | BU58: 108 | BV58: 106 | BW58: 78 | BX58: 60 | BY58: 0 | BZ58: =SUM(BS58:BY58) -> 492 | CB58: 1422900 | CC58: J MHC CINTURA P | CD58: Ventas | CF58: 42 | CG58: 98 | CH58: 108 | CI58: 106 | CJ58: 78 | CK58: 60 | CL58: 0 | CM58: =SUM(CF58:CL58) -> 492 | CO58: 1422900 | CP58: J MHC CINTURA P | CQ58: Ventas | CS58: 42 | CT58: 92 | CU58: 102 | CV58: 99 | CW58: 72 | CX58: 57 | CY58: 0 | CZ58: 464 | DB58: 1422900 | DC58: J MHC CINTURA P | DD58: Ventas | DF58: 37 | DG58: 82 | DH58: 90 | DI58: 86 | DJ58: 60 | DK58: 50 | DL58: 0 | DM58: 405 | DO58: 1422900 | DP58: J MHC CINTURA P | DQ58: Ventas | DS58: 36 | DT58: 78 | DU58: 84 | DV58: 81 | DW58: 57 | DX58: 49 | DY58: 0 | DZ58: 385 | EB58: 1422900 | EC58: J MHC CINTURA P | ED58: Ventas | EF58: 35 | EG58: 75 | EH58: 82 | EI58: 79 | EJ58: 55 | EK58: 47 | EL58: 0 | EM58: 373 | EO58: 1423000 | EP58: J MHC CINTURA P | EQ58: Ventas | ES58: 24 | ET58: 34 | EU58: 34 | EV58: 31 | EW58: 23 | EX58: 12 | EY58: 0 | EZ58: 158 | FO58: 1423304 | FP58: J MHC CINTURA T | FQ58: Ventas | FS58: 3 | FT58: 8 | FU58: 10 | FV58: 7 | FW58: 5 | FX58: 4 | FY58: 0 | FZ58: 37 | GB58: 1423304 | GC58: J MHC CINTURA T | GD58: Ventas | GF58: 1 | GG58: 3 | GH58: 3 | GI58: 2 | GJ58: 1 | GK58: 1 | GL58: 0 | GM58: 11 | GO58: 1423304 | GP58: J MHC CINTURA T | GQ58: Ventas | GS58: 1 | GT58: 3 | GU58: 3 | GV58: 2 | GW58: 1 | GX58: 1 | GY58: 0 | GZ58: =SUM(GS58:GY58) -> 11
A59: 1423000 | B59: Imperio Max | C59: 41 | D59: 58 | E59: 58 | F59: 54 | G59: 33 | H59: 21 | J59: =SUM(C59:H59) -> 265 | K59: ='CORTE 4200'!$O$511 -> -241 | L59: 50 | O59: 1423000 | P59: J MHC CINTURA P | Q59: Ventas | S59: 41 | T59: 58 | U59: 58 | V59: 54 | W59: 33 | X59: 21 | Y59: 0 | Z59: =SUM(S59:Y59) -> 265 | AB59: 1423000 | AC59: J MHC CINTURA P | AD59: Ventas | AF59: 43 | AG59: 63 | AH59: 63 | AI59: 56 | AJ59: 34 | AK59: 21 | AL59: 0 | AM59: =SUM(AF59:AL59) -> 280 | AO59: 1423000 | AP59: J MHC CINTURA P | AQ59: Ventas | AS59: 40 | AT59: 60 | AU59: 60 | AV59: 54 | AW59: 32 | AX59: 19 | AY59: 0 | AZ59: =SUM(AS59:AY59) -> 265 | BB59: 1423000 | BC59: J MHC CINTURA P | BD59: Ventas | BF59: 40 | BG59: 60 | BH59: 60 | BI59: 54 | BJ59: 32 | BK59: 19 | BL59: 0 | BM59: =SUM(BF59:BL59) -> 265 | BO59: 1423000 | BP59: J MHC CINTURA P | BQ59: Ventas | BS59: 32 | BT59: 48 | BU59: 48 | BV59: 42 | BW59: 29 | BX59: 16 | BY59: 0 | BZ59: =SUM(BS59:BY59) -> 215 | CB59: 1423000 | CC59: J MHC CINTURA P | CD59: Ventas | CF59: 32 | CG59: 48 | CH59: 48 | CI59: 42 | CJ59: 29 | CK59: 16 | CL59: 0 | CM59: =SUM(CF59:CL59) -> 215 | CO59: 1423000 | CP59: J MHC CINTURA P | CQ59: Ventas | CS59: 32 | CT59: 48 | CU59: 48 | CV59: 42 | CW59: 29 | CX59: 16 | CY59: 0 | CZ59: 215 | DB59: 1423000 | DC59: J MHC CINTURA P | DD59: Ventas | DF59: 30 | DG59: 44 | DH59: 44 | DI59: 38 | DJ59: 27 | DK59: 14 | DL59: 0 | DM59: 197 | DO59: 1423000 | DP59: J MHC CINTURA P | DQ59: Ventas | DS59: 30 | DT59: 44 | DU59: 44 | DV59: 38 | DW59: 27 | DX59: 14 | DY59: 0 | DZ59: 197 | EB59: 1423000 | EC59: J MHC CINTURA P | ED59: Ventas | EF59: 26 | EG59: 36 | EH59: 36 | EI59: 33 | EJ59: 24 | EK59: 13 | EL59: 0 | EM59: 168 | EO59: 1423200 | EP59: J MHC CINTURA O | EQ59: Ventas | ES59: 2 | ET59: 6 | EU59: 8 | EV59: 5 | EW59: 3 | EX59: 2 | EY59: 0 | EZ59: 26 | FB59: 1423304 | FC59: J MHC CINTURA T | FD59: Ventas | FF59: 3 | FG59: 8 | FH59: 10 | FI59: 7 | FJ59: 5 | FK59: 4 | FL59: 0 | FM59: 37 | FO59: 1423308 | FP59: J MHC CINTURA T | FQ59: Ventas | FS59: 3 | FT59: 7 | FU59: 7 | FV59: 6 | FW59: 5 | FX59: 3 | FY59: 0 | FZ59: 31 | GB59: 1423308 | GC59: J MHC CINTURA T | GD59: Ventas | GF59: 3 | GG59: 7 | GH59: 7 | GI59: 6 | GJ59: 5 | GK59: 3 | GL59: 0 | GM59: 31 | GO59: 1423308 | GP59: J MHC CINTURA T | GQ59: Ventas | GS59: 3 | GT59: 7 | GU59: 7 | GV59: 6 | GW59: 5 | GX59: 3 | GY59: 0 | GZ59: =SUM(GS59:GY59) -> 31
A60: 1423100 | B60: New Glue | J60: =SUM(C60:H60) -> 0 | K60: ='CORTE 4200'!$O$520 -> 0 | Z60: =SUM(S60:Y60) -> 0 | AB60: 1423100 | AC60: J MHC CINTURA P | AD60: Ventas | AF60: 2 | AG60: 4 | AH60: 3 | AI60: 2 | AJ60: 1 | AK60: 0 | AL60: 0 | AM60: =SUM(AF60:AL60) -> 12 | AO60: 1423100 | AP60: J MHC CINTURA P | AQ60: Ventas | AS60: 2 | AT60: 4 | AU60: 3 | AV60: 2 | AW60: 1 | AX60: 0 | AY60: 0 | AZ60: =SUM(AS60:AY60) -> 12 | BB60: 1423100 | BC60: J MHC CINTURA P | BD60: Ventas | BF60: 2 | BG60: 4 | BH60: 3 | BI60: 2 | BJ60: 1 | BK60: 0 | BL60: 0 | BM60: =SUM(BF60:BL60) -> 12 | BO60: 1423100 | BP60: J MHC CINTURA P | BQ60: Ventas | BS60: 2 | BT60: 4 | BU60: 3 | BV60: 2 | BW60: 1 | BX60: 0 | BY60: 0 | BZ60: =SUM(BS60:BY60) -> 12 | CB60: 1423100 | CC60: J MHC CINTURA P | CD60: Ventas | CF60: 2 | CG60: 4 | CH60: 3 | CI60: 2 | CJ60: 1 | CK60: 0 | CL60: 0 | CM60: =SUM(CF60:CL60) -> 12 | CO60: 1423100 | CP60: J MHC CINTURA P | CQ60: Ventas | CS60: 2 | CT60: 4 | CU60: 3 | CV60: 2 | CW60: 1 | CX60: 0 | CY60: 0 | CZ60: 12 | DB60: 1423100 | DC60: J MHC CINTURA P | DD60: Ventas | DF60: 2 | DG60: 4 | DH60: 3 | DI60: 2 | DJ60: 1 | DK60: 0 | DL60: 0 | DM60: 12 | DO60: 1423100 | DP60: J MHC CINTURA P | DQ60: Ventas | DS60: 2 | DT60: 4 | DU60: 3 | DV60: 2 | DW60: 1 | DX60: 0 | DY60: 0 | DZ60: 12 | EB60: 1423200 | EC60: J MHC CINTURA O | ED60: Ventas | EF60: 6 | EG60: 11 | EH60: 13 | EI60: 10 | EJ60: 6 | EK60: 4 | EL60: 0 | EM60: 50 | FB60: 1423308 | FC60: J MHC CINTURA T | FD60: Ventas | FF60: 3 | FG60: 7 | FH60: 7 | FI60: 6 | FJ60: 5 | FK60: 3 | FL60: 0 | FM60: 31 | FO60: 1423309 | FP60: J MHC CINTURA T | FQ60: Ventas | FS60: 6 | FT60: 8 | FU60: 6 | FV60: 6 | FW60: 4 | FX60: 2 | FY60: 0 | FZ60: 32 | GB60: 1423309 | GC60: J MHC CINTURA T | GD60: Ventas | GF60: 5 | GG60: 6 | GH60: 4 | GI60: 4 | GJ60: 2 | GK60: 0 | GL60: 0 | GM60: 21 | GO60: 1423309 | GP60: J MHC CINTURA T | GQ60: Ventas | GS60: 5 | GT60: 6 | GU60: 4 | GV60: 4 | GW60: 2 | GX60: 0 | GY60: 0 | GZ60: =SUM(GS60:GY60) -> 21
A61: 1423200 | B61: Ayla | C61: 6 | D61: 13 | E61: 15 | F61: 12 | G61: 8 | H61: 6 | J61: =SUM(C61:H61) -> 60 | K61: ='CORTE 4200'!$O$529 -> -140 | O61: 1423200 | P61: J MHC CINTURA O | Q61: Ventas | S61: 6 | T61: 13 | U61: 15 | V61: 12 | W61: 8 | X61: 6 | Y61: 0 | Z61: =SUM(S61:Y61) -> 60 | AB61: 1423200 | AC61: J MHC CINTURA O | AD61: Ventas | AF61: 6 | AG61: 13 | AH61: 15 | AI61: 12 | AJ61: 8 | AK61: 6 | AL61: 0 | AM61: =SUM(AF61:AL61) -> 60 | AO61: 1423200 | AP61: J MHC CINTURA O | AQ61: Ventas | AS61: 6 | AT61: 11 | AU61: 13 | AV61: 10 | AW61: 6 | AX61: 4 | AY61: 0 | AZ61: =SUM(AS61:AY61) -> 50 | BB61: 1423200 | BC61: J MHC CINTURA O | BD61: Ventas | BF61: 6 | BG61: 11 | BH61: 13 | BI61: 10 | BJ61: 6 | BK61: 4 | BL61: 0 | BM61: =SUM(BF61:BL61) -> 50 | BO61: 1423200 | BP61: J MHC CINTURA O | BQ61: Ventas | BS61: 6 | BT61: 11 | BU61: 13 | BV61: 10 | BW61: 6 | BX61: 4 | BY61: 0 | BZ61: =SUM(BS61:BY61) -> 50 | CB61: 1423200 | CC61: J MHC CINTURA O | CD61: Ventas | CF61: 6 | CG61: 11 | CH61: 13 | CI61: 10 | CJ61: 6 | CK61: 4 | CL61: 0 | CM61: =SUM(CF61:CL61) -> 50 | CO61: 1423200 | CP61: J MHC CINTURA O | CQ61: Ventas | CS61: 6 | CT61: 11 | CU61: 13 | CV61: 10 | CW61: 6 | CX61: 4 | CY61: 0 | CZ61: 50 | DB61: 1423200 | DC61: J MHC CINTURA O | DD61: Ventas | DF61: 6 | DG61: 11 | DH61: 13 | DI61: 10 | DJ61: 6 | DK61: 4 | DL61: 0 | DM61: 50 | DO61: 1423200 | DP61: J MHC CINTURA O | DQ61: Ventas | DS61: 6 | DT61: 11 | DU61: 13 | DV61: 10 | DW61: 6 | DX61: 4 | DY61: 0 | DZ61: 50 | EO61: 1423304 | EP61: J MHC CINTURA T | EQ61: Ventas | ES61: 3 | ET61: 8 | EU61: 10 | EV61: 7 | EW61: 5 | EX61: 4 | EY61: 0 | EZ61: 37 | FB61: 1423309 | FC61: J MHC CINTURA T | FD61: Ventas | FF61: 6 | FG61: 8 | FH61: 6 | FI61: 6 | FJ61: 4 | FK61: 2 | FL61: 0 | FM61: 32 | FO61: 1423316 | FP61: J MHC CINTURA T | FQ61: Ventas | FS61: 1 | FT61: 2 | FU61: 2 | FV61: 2 | FW61: 2 | FX61: 1 | FY61: 0 | FZ61: 10
A62: 1423300 | B62: Lavinia | J62: =SUM(C62:H62) -> 0 | K62: ='CORTE 4200'!$O$538 -> 0 | Z62: =SUM(S62:Y62) -> 0 | AM62: =SUM(AF62:AL62) -> 0 | BM62: =SUM(BF62:BL62) -> 0 | CM62: =SUM(CF62:CL62) -> 0 | EB62: 1423304 | EC62: J MHC CINTURA T | ED62: Ventas | EF62: 4 | EG62: 9 | EH62: 11 | EI62: 8 | EJ62: 6 | EK62: 5 | EL62: 0 | EM62: 43 | EO62: 1423308 | EP62: J MHC CINTURA T | EQ62: Ventas | ES62: 6 | ET62: 10 | EU62: 10 | EV62: 8 | EW62: 7 | EX62: 5 | EY62: 0 | EZ62: 46 | FB62: 1423316 | FC62: J MHC CINTURA T | FD62: Ventas | FF62: 1 | FG62: 2 | FH62: 2 | FI62: 2 | FJ62: 2 | FK62: 1 | FL62: 0 | FM62: 10 | FO62: 1423348 | FP62: J MHC CINTURA T | FQ62: Ventas | FS62: 1 | FT62: 3 | FU62: 3 | FV62: 2 | FW62: 1 | FX62: 1 | FY62: 0 | FZ62: 11 | GB62: 1423348 | GC62: J MHC CINTURA T | GD62: Ventas | GF62: 1 | GG62: 3 | GH62: 3 | GI62: 2 | GJ62: 1 | GK62: 1 | GL62: 0 | GM62: 11 | GO62: 1423348 | GP62: J MHC CINTURA T | GQ62: Ventas | GS62: 1 | GT62: 3 | GU62: 3 | GV62: 2 | GW62: 1 | GX62: 1 | GY62: 0 | GZ62: =SUM(GS62:GY62) -> 11
A63: 1423304 | B63: Lavinia | C63: 6 | D63: 15 | E63: 17 | F63: 14 | G63: 10 | H63: 7 | J63: =SUM(C63:H63) -> 69 | K63: ='CORTE 4200'!$O$547 -> -77 | O63: 1423304 | P63: J MHC CINTURA T | Q63: Ventas | S63: 6 | T63: 15 | U63: 17 | V63: 14 | W63: 10 | X63: 7 | Y63: 0 | Z63: =SUM(S63:Y63) -> 69 | AB63: 1423304 | AC63: J MHC CINTURA T | AD63: Ventas | AF63: 8 | AG63: 19 | AH63: 21 | AI63: 16 | AJ63: 11 | AK63: 7 | AL63: 0 | AM63: =SUM(AF63:AL63) -> 82 | AO63: 1423304 | AP63: J MHC CINTURA T | AQ63: Ventas | AS63: 8 | AT63: 19 | AU63: 21 | AV63: 16 | AW63: 11 | AX63: 7 | AY63: 0 | AZ63: =SUM(AS63:AY63) -> 82 | BB63: 1423304 | BC63: J MHC CINTURA T | BD63: Ventas | BF63: 8 | BG63: 19 | BH63: 21 | BI63: 16 | BJ63: 11 | BK63: 7 | BL63: 0 | BM63: =SUM(BF63:BL63) -> 82 | BO63: 1423304 | BP63: J MHC CINTURA T | BQ63: Ventas | BS63: 8 | BT63: 19 | BU63: 21 | BV63: 16 | BW63: 11 | BX63: 7 | BY63: 0 | BZ63: =SUM(BS63:BY63) -> 82 | CB63: 1423304 | CC63: J MHC CINTURA T | CD63: Ventas | CF63: 8 | CG63: 19 | CH63: 21 | CI63: 16 | CJ63: 11 | CK63: 7 | CL63: 0 | CM63: =SUM(CF63:CL63) -> 82 | CO63: 1423304 | CP63: J MHC CINTURA T | CQ63: Ventas | CS63: 8 | CT63: 16 | CU63: 18 | CV63: 13 | CW63: 9 | CX63: 6 | CY63: 0 | CZ63: 70 | DB63: 1423304 | DC63: J MHC CINTURA T | DD63: Ventas | DF63: 8 | DG63: 16 | DH63: 18 | DI63: 13 | DJ63: 9 | DK63: 6 | DL63: 0 | DM63: 70 | DO63: 1423304 | DP63: J MHC CINTURA T | DQ63: Ventas | DS63: 8 | DT63: 16 | DU63: 18 | DV63: 13 | DW63: 9 | DX63: 6 | DY63: 0 | DZ63: 70 | EB63: 1423308 | EC63: J MHC CINTURA T | ED63: Ventas | EF63: 8 | EG63: 13 | EH63: 13 | EI63: 11 | EJ63: 9 | EK63: 6 | EL63: 0 | EM63: 60 | EO63: 1423309 | EP63: J MHC CINTURA T | EQ63: Ventas | ES63: 6 | ET63: 8 | EU63: 6 | EV63: 6 | EW63: 4 | EX63: 2 | EY63: 0 | EZ63: 32 | FB63: 1423348 | FC63: J MHC CINTURA T | FD63: Ventas | FF63: 1 | FG63: 3 | FH63: 3 | FI63: 2 | FJ63: 1 | FK63: 1 | FL63: 0 | FM63: 11 | GB63: 1423400 | GC63: J MHC CINTURA F | GD63: Ventas | GF63: 0 | GG63: 5 | GH63: 5 | GI63: 4 | GJ63: 3 | GK63: 1 | GL63: 0 | GM63: 18 | GO63: 1423400 | GP63: J MHC CINTURA F | GQ63: Ventas | GS63: 0 | GT63: 5 | GU63: 5 | GV63: 4 | GW63: 3 | GX63: 1 | GY63: 0 | GZ63: =SUM(GS63:GY63) -> 18
A64: 1423308 | B64: Lavinia | C64: 8 | D64: 17 | E64: 17 | F64: 15 | G64: 12 | H64: 7 | J64: =SUM(C64:H64) -> 76 | K64: ='CORTE 4200'!$O$556 -> -57 | O64: 1423308 | P64: J MHC CINTURA T | Q64: Ventas | S64: 8 | T64: 17 | U64: 17 | V64: 15 | W64: 12 | X64: 7 | Y64: 0 | Z64: =SUM(S64:Y64) -> 76 | AB64: 1423308 | AC64: J MHC CINTURA T | AD64: Ventas | AF64: 8 | AG64: 17 | AH64: 17 | AI64: 15 | AJ64: 12 | AK64: 7 | AL64: 0 | AM64: =SUM(AF64:AL64) -> 76 | AO64: 1423308 | AP64: J MHC CINTURA T | AQ64: Ventas | AS64: 8 | AT64: 17 | AU64: 17 | AV64: 15 | AW64: 12 | AX64: 7 | AY64: 0 | AZ64: =SUM(AS64:AY64) -> 76 | BB64: 1423308 | BC64: J MHC CINTURA T | BD64: Ventas | BF64: 8 | BG64: 17 | BH64: 17 | BI64: 15 | BJ64: 12 | BK64: 7 | BL64: 0 | BM64: =SUM(BF64:BL64) -> 76 | BO64: 1423308 | BP64: J MHC CINTURA T | BQ64: Ventas | BS64: 8 | BT64: 17 | BU64: 17 | BV64: 15 | BW64: 12 | BX64: 7 | BY64: 0 | BZ64: =SUM(BS64:BY64) -> 76 | CB64: 1423308 | CC64: J MHC CINTURA T | CD64: Ventas | CF64: 8 | CG64: 17 | CH64: 17 | CI64: 15 | CJ64: 12 | CK64: 7 | CL64: 0 | CM64: =SUM(CF64:CL64) -> 76 | CO64: 1423308 | CP64: J MHC CINTURA T | CQ64: Ventas | CS64: 8 | CT64: 14 | CU64: 14 | CV64: 12 | CW64: 10 | CX64: 6 | CY64: 0 | CZ64: 64 | DB64: 1423308 | DC64: J MHC CINTURA T | DD64: Ventas | DF64: 8 | DG64: 14 | DH64: 14 | DI64: 12 | DJ64: 10 | DK64: 6 | DL64: 0 | DM64: 64 | DO64: 1423308 | DP64: J MHC CINTURA T | DQ64: Ventas | DS64: 8 | DT64: 14 | DU64: 14 | DV64: 12 | DW64: 10 | DX64: 6 | DY64: 0 | DZ64: 64 | EB64: 1423309 | EC64: J MHC CINTURA T | ED64: Ventas | EF64: 6 | EG64: 8 | EH64: 6 | EI64: 6 | EJ64: 4 | EK64: 2 | EL64: 0 | EM64: 32 | EO64: 1423316 | EP64: J MHC CINTURA T | EQ64: Ventas | ES64: 1 | ET64: 4 | EU64: 4 | EV64: 4 | EW64: 2 | EX64: 1 | EY64: 0 | EZ64: 16 | FO64: 1423404 | FP64: J MHC CINTURA F | FQ64: Ventas | FS64: 17 | FT64: 41 | FU64: 42 | FV64: 41 | FW64: 27 | FX64: 25 | FY64: 0 | FZ64: 193 | GB64: 1423404 | GC64: J MHC CINTURA F | GD64: Ventas | GF64: 3 | GG64: 5 | GH64: 6 | GI64: 5 | GJ64: 3 | GK64: 3 | GL64: 0 | GM64: 25 | GO64: 1423404 | GP64: J MHC CINTURA F | GQ64: Ventas | GS64: 1 | GT64: 3 | GU64: 3 | GV64: 2 | GW64: 1 | GX64: 1 | GY64: 0 | GZ64: =SUM(GS64:GY64) -> 11
A65: 1423309 | B65: Lavinia | C65: 6 | D65: 8 | E65: 6 | F65: 6 | G65: 4 | H65: 2 | J65: =SUM(C65:H65) -> 32 | K65: ='CORTE 4200'!$O$565 -> -4 | O65: 1423309 | P65: J MHC CINTURA T | Q65: Ventas | S65: 6 | T65: 8 | U65: 6 | V65: 6 | W65: 4 | X65: 2 | Y65: 0 | Z65: =SUM(S65:Y65) -> 32 | AB65: 1423309 | AC65: J MHC CINTURA T | AD65: Ventas | AF65: 6 | AG65: 8 | AH65: 6 | AI65: 6 | AJ65: 4 | AK65: 2 | AL65: 0 | AM65: =SUM(AF65:AL65) -> 32 | AO65: 1423309 | AP65: J MHC CINTURA T | AQ65: Ventas | AS65: 6 | AT65: 8 | AU65: 6 | AV65: 6 | AW65: 4 | AX65: 2 | AY65: 0 | AZ65: =SUM(AS65:AY65) -> 32 | BB65: 1423309 | BC65: J MHC CINTURA T | BD65: Ventas | BF65: 6 | BG65: 8 | BH65: 6 | BI65: 6 | BJ65: 4 | BK65: 2 | BL65: 0 | BM65: =SUM(BF65:BL65) -> 32 | BO65: 1423309 | BP65: J MHC CINTURA T | BQ65: Ventas | BS65: 6 | BT65: 8 | BU65: 6 | BV65: 6 | BW65: 4 | BX65: 2 | BY65: 0 | BZ65: =SUM(BS65:BY65) -> 32 | CB65: 1423309 | CC65: J MHC CINTURA T | CD65: Ventas | CF65: 6 | CG65: 8 | CH65: 6 | CI65: 6 | CJ65: 4 | CK65: 2 | CL65: 0 | CM65: =SUM(CF65:CL65) -> 32 | CO65: 1423309 | CP65: J MHC CINTURA T | CQ65: Ventas | CS65: 6 | CT65: 8 | CU65: 6 | CV65: 6 | CW65: 4 | CX65: 2 | CY65: 0 | CZ65: 32 | DB65: 1423309 | DC65: J MHC CINTURA T | DD65: Ventas | DF65: 6 | DG65: 8 | DH65: 6 | DI65: 6 | DJ65: 4 | DK65: 2 | DL65: 0 | DM65: 32 | DO65: 1423309 | DP65: J MHC CINTURA T | DQ65: Ventas | DS65: 6 | DT65: 8 | DU65: 6 | DV65: 6 | DW65: 4 | DX65: 2 | DY65: 0 | DZ65: 32 | EB65: 1423316 | EC65: J MHC CINTURA T | ED65: Ventas | EF65: 4 | EG65: 8 | EH65: 8 | EI65: 8 | EJ65: 5 | EK65: 3 | EL65: 0 | EM65: 36 | EO65: 1423348 | EP65: J MHC CINTURA T | EQ65: Ventas | ES65: 4 | ET65: 6 | EU65: 6 | EV65: 4 | EW65: 3 | EX65: 3 | EY65: 0 | EZ65: 26 | FB65: 1423404 | FC65: J MHC CINTURA F | FD65: Ventas | FF65: 17 | FG65: 41 | FH65: 42 | FI65: 41 | FJ65: 27 | FK65: 25 | FL65: 0 | FM65: 193 | FO65: 1423408 | FP65: J MHC CINTURA F | FQ65: Ventas | FS65: 27 | FT65: 47 | FU65: 49 | FV65: 46 | FW65: 31 | FX65: 19 | FY65: 0 | FZ65: 219 | GB65: 1423408 | GC65: J MHC CINTURA F | GD65: Ventas | GF65: 16 | GG65: 22 | GH65: 24 | GI65: 20 | GJ65: 14 | GK65: 4 | GL65: 0 | GM65: 100 | GO65: 1423408 | GP65: J MHC CINTURA F | GQ65: Ventas | GS65: 13 | GT65: 17 | GU65: 17 | GV65: 14 | GW65: 10 | GX65: 1 | GY65: 0 | GZ65: =SUM(GS65:GY65) -> 72
A66: 1423316 | B66: Lavinia | C66: 8 | D66: 17 | E66: 17 | F66: 16 | G66: 10 | H66: 5 | J66: =SUM(C66:H66) -> 73 | K66: ='CORTE 4200'!$O$574 -> -16 | O66: 1423316 | P66: J MHC CINTURA T | Q66: Ventas | S66: 8 | T66: 17 | U66: 17 | V66: 16 | W66: 10 | X66: 5 | Y66: 0 | Z66: =SUM(S66:Y66) -> 73 | AB66: 1423316 | AC66: J MHC CINTURA T | AD66: Ventas | AF66: 8 | AG66: 17 | AH66: 17 | AI66: 16 | AJ66: 10 | AK66: 5 | AL66: 0 | AM66: =SUM(AF66:AL66) -> 73 | AO66: 1423316 | AP66: J MHC CINTURA T | AQ66: Ventas | AS66: 8 | AT66: 17 | AU66: 17 | AV66: 16 | AW66: 10 | AX66: 5 | AY66: 0 | AZ66: =SUM(AS66:AY66) -> 73 | BB66: 1423316 | BC66: J MHC CINTURA T | BD66: Ventas | BF66: 8 | BG66: 17 | BH66: 17 | BI66: 16 | BJ66: 10 | BK66: 5 | BL66: 0 | BM66: =SUM(BF66:BL66) -> 73 | BO66: 1423316 | BP66: J MHC CINTURA T | BQ66: Ventas | BS66: 8 | BT66: 17 | BU66: 17 | BV66: 16 | BW66: 10 | BX66: 5 | BY66: 0 | BZ66: =SUM(BS66:BY66) -> 73 | CB66: 1423316 | CC66: J MHC CINTURA T | CD66: Ventas | CF66: 8 | CG66: 17 | CH66: 17 | CI66: 16 | CJ66: 10 | CK66: 5 | CL66: 0 | CM66: =SUM(CF66:CL66) -> 73 | CO66: 1423316 | CP66: J MHC CINTURA T | CQ66: Ventas | CS66: 8 | CT66: 14 | CU66: 14 | CV66: 13 | CW66: 8 | CX66: 4 | CY66: 0 | CZ66: 61 | DB66: 1423316 | DC66: J MHC CINTURA T | DD66: Ventas | DF66: 8 | DG66: 14 | DH66: 14 | DI66: 13 | DJ66: 8 | DK66: 4 | DL66: 0 | DM66: 61 | DO66: 1423316 | DP66: J MHC CINTURA T | DQ66: Ventas | DS66: 6 | DT66: 11 | DU66: 11 | DV66: 11 | DW66: 7 | DX66: 4 | DY66: 0 | DZ66: 50 | EB66: 1423348 | EC66: J MHC CINTURA T | ED66: Ventas | EF66: 7 | EG66: 10 | EH66: 10 | EI66: 8 | EJ66: 6 | EK66: 5 | EL66: 0 | EM66: 46 | FB66: 1423408 | FC66: J MHC CINTURA F | FD66: Ventas | FF66: 27 | FG66: 47 | FH66: 49 | FI66: 46 | FJ66: 31 | FK66: 19 | FL66: 0 | FM66: 219 | FO66: 1423409 | FP66: J MHC CINTURA F | FQ66: Ventas | FS66: 2 | FT66: 4 | FU66: 4 | FV66: 4 | FW66: 4 | FX66: 2 | FY66: 0 | FZ66: 20 | GB66: 1423409 | GC66: J MHC CINTURA F | GD66: Ventas | GF66: 2 | GG66: 4 | GH66: 4 | GI66: 4 | GJ66: 4 | GK66: 2 | GL66: 0 | GM66: 20 | GO66: 1423409 | GP66: J MHC CINTURA F | GQ66: Ventas | GS66: 2 | GT66: 4 | GU66: 4 | GV66: 4 | GW66: 4 | GX66: 2 | GY66: 0 | GZ66: =SUM(GS66:GY66) -> 20
A67: 1423348 | B67: Lavinia | C67: 8 | D67: 14 | E67: 14 | F67: 14 | G67: 10 | H67: 8 | J67: =SUM(C67:H67) -> 68 | K67: ='CORTE 4200'!$O$583 -> -17 | O67: 1423348 | P67: J MHC CINTURA T | Q67: Ventas | S67: 8 | T67: 14 | U67: 14 | V67: 14 | W67: 10 | X67: 8 | Y67: 0 | Z67: =SUM(S67:Y67) -> 68 | AB67: 1423348 | AC67: J MHC CINTURA T | AD67: Ventas | AF67: 8 | AG67: 14 | AH67: 14 | AI67: 14 | AJ67: 10 | AK67: 8 | AL67: 0 | AM67: =SUM(AF67:AL67) -> 68 | AO67: 1423348 | AP67: J MHC CINTURA T | AQ67: Ventas | AS67: 8 | AT67: 14 | AU67: 14 | AV67: 14 | AW67: 10 | AX67: 8 | AY67: 0 | AZ67: =SUM(AS67:AY67) -> 68 | BB67: 1423348 | BC67: J MHC CINTURA T | BD67: Ventas | BF67: 8 | BG67: 14 | BH67: 14 | BI67: 14 | BJ67: 10 | BK67: 8 | BL67: 0 | BM67: =SUM(BF67:BL67) -> 68 | BO67: 1423348 | BP67: J MHC CINTURA T | BQ67: Ventas | BS67: 8 | BT67: 14 | BU67: 14 | BV67: 14 | BW67: 10 | BX67: 8 | BY67: 0 | BZ67: =SUM(BS67:BY67) -> 68 | CB67: 1423348 | CC67: J MHC CINTURA T | CD67: Ventas | CF67: 8 | CG67: 14 | CH67: 14 | CI67: 14 | CJ67: 10 | CK67: 8 | CL67: 0 | CM67: =SUM(CF67:CL67) -> 68 | CO67: 1423348 | CP67: J MHC CINTURA T | CQ67: Ventas | CS67: 8 | CT67: 14 | CU67: 14 | CV67: 14 | CW67: 10 | CX67: 8 | CY67: 0 | CZ67: 68 | DB67: 1423348 | DC67: J MHC CINTURA T | DD67: Ventas | DF67: 7 | DG67: 10 | DH67: 10 | DI67: 8 | DJ67: 6 | DK67: 5 | DL67: 0 | DM67: 46 | DO67: 1423348 | DP67: J MHC CINTURA T | DQ67: Ventas | DS67: 7 | DT67: 10 | DU67: 10 | DV67: 8 | DW67: 6 | DX67: 5 | DY67: 0 | DZ67: 46 | EO67: 1423404 | EP67: J MHC CINTURA F | EQ67: Ventas | ES67: 19 | ET67: 44 | EU67: 45 | EV67: 44 | EW67: 27 | EX67: 25 | EY67: 0 | EZ67: 204 | FB67: 1423409 | FC67: J MHC CINTURA F | FD67: Ventas | FF67: 2 | FG67: 4 | FH67: 4 | FI67: 4 | FJ67: 4 | FK67: 2 | FL67: 0 | FM67: 20 | FO67: 1423416 | FP67: J MHC CINTURA F | FQ67: Ventas | FS67: 8 | FT67: 12 | FU67: 12 | FV67: 12 | FW67: 9 | FX67: 4 | FY67: 0 | FZ67: 57 | GB67: 1423416 | GC67: J MHC CINTURA F | GD67: Ventas | GF67: 2 | GG67: 4 | GH67: 4 | GI67: 4 | GJ67: 4 | GK67: 2 | GL67: 0 | GM67: 20 | GO67: 1423416 | GP67: J MHC CINTURA F | GQ67: Ventas | GS67: 2 | GT67: 4 | GU67: 4 | GV67: 4 | GW67: 4 | GX67: 2 | GY67: 0 | GZ67: =SUM(GS67:GY67) -> 20
A68: 1423400 | B68: Lavinia | C68: 3 | D68: 4 | E68: 2 | F68: 2 | G68: 1 | H68: 0 | J68: =SUM(C68:H68) -> 12 | K68: ='CORTE 4200'!$O$592 -> 12 | O68: 1423400 | P68: J MHC CINTURA F | Q68: Ventas | S68: 3 | T68: 4 | U68: 2 | V68: 2 | W68: 1 | X68: 0 | Y68: 0 | Z68: =SUM(S68:Y68) -> 12 | AB68: 1423400 | AC68: J MHC CINTURA F | AD68: Ventas | AF68: 3 | AG68: 4 | AH68: 2 | AI68: 2 | AJ68: 1 | AK68: 0 | AL68: 0 | AM68: =SUM(AF68:AL68) -> 12 | AO68: 1423400 | AP68: J MHC CINTURA F | AQ68: Ventas | AS68: 3 | AT68: 4 | AU68: 2 | AV68: 2 | AW68: 1 | AX68: 0 | AY68: 0 | AZ68: =SUM(AS68:AY68) -> 12 | BB68: 1423400 | BC68: J MHC CINTURA F | BD68: Ventas | BF68: 3 | BG68: 4 | BH68: 2 | BI68: 2 | BJ68: 1 | BK68: 0 | BL68: 0 | BM68: =SUM(BF68:BL68) -> 12 | CM68: =SUM(CF68:CL68) -> 0 | EB68: 1423404 | EC68: J MHC CINTURA F | ED68: Ventas | EF68: 21 | EG68: 47 | EH68: 48 | EI68: 47 | EJ68: 29 | EK68: 26 | EL68: 0 | EM68: 218 | EO68: 1423408 | EP68: J MHC CINTURA F | EQ68: Ventas | ES68: 31 | ET68: 52 | EU68: 54 | EV68: 51 | EW68: 31 | EX68: 19 | EY68: 0 | EZ68: 238 | FB68: 1423416 | FC68: J MHC CINTURA F | FD68: Ventas | FF68: 8 | FG68: 12 | FH68: 12 | FI68: 12 | FJ68: 9 | FK68: 4 | FL68: 0 | FM68: 57 | FO68: 1423448 | FP68: J MHC CINTURA F | FQ68: Ventas | FS68: 6 | FT68: 9 | FU68: 5 | FV68: 6 | FW68: 4 | FX68: 2 | FY68: 0 | FZ68: 32 | GB68: 1423448 | GC68: J MHC CINTURA F | GD68: Ventas | GF68: 6 | GG68: 9 | GH68: 5 | GI68: 6 | GJ68: 4 | GK68: 2 | GL68: 0 | GM68: 32 | GO68: 1423448 | GP68: J MHC CINTURA F | GQ68: Ventas | GS68: 6 | GT68: 9 | GU68: 5 | GV68: 6 | GW68: 4 | GX68: 2 | GY68: 0 | GZ68: =SUM(GS68:GY68) -> 32
A69: 1423404 | B69: Lavinia | C69: 30 | D69: 64 | E69: 70 | F69: 68 | G69: 42 | H69: 31 | J69: =SUM(C69:H69) -> 305 | K69: ='CORTE 4200'!$O$601 -> -64 | O69: 1423404 | P69: J MHC CINTURA F | Q69: Ventas | S69: 30 | T69: 64 | U69: 70 | V69: 68 | W69: 42 | X69: 31 | Y69: 0 | Z69: =SUM(S69:Y69) -> 305 | AB69: 1423404 | AC69: J MHC CINTURA F | AD69: Ventas | AF69: 30 | AG69: 64 | AH69: 69 | AI69: 67 | AJ69: 41 | AK69: 31 | AL69: 0 | AM69: =SUM(AF69:AL69) -> 302 | AO69: 1423404 | AP69: J MHC CINTURA F | AQ69: Ventas | AS69: 30 | AT69: 64 | AU69: 69 | AV69: 67 | AW69: 41 | AX69: 31 | AY69: 0 | AZ69: =SUM(AS69:AY69) -> 302 | BB69: 1423404 | BC69: J MHC CINTURA F | BD69: Ventas | BF69: 29 | BG69: 62 | BH69: 66 | BI69: 65 | BJ69: 40 | BK69: 30 | BL69: 0 | BM69: =SUM(BF69:BL69) -> 292 | BO69: 1423404 | BP69: J MHC CINTURA F | BQ69: Ventas | BS69: 29 | BT69: 62 | BU69: 66 | BV69: 65 | BW69: 40 | BX69: 30 | BY69: 0 | BZ69: =SUM(BS69:BY69) -> 292 | CB69: 1423404 | CC69: J MHC CINTURA F | CD69: Ventas | CF69: 29 | CG69: 62 | CH69: 66 | CI69: 65 | CJ69: 40 | CK69: 30 | CL69: 0 | CM69: =SUM(CF69:CL69) -> 292 | CO69: 1423404 | CP69: J MHC CINTURA F | CQ69: Ventas | CS69: 28 | CT69: 59 | CU69: 63 | CV69: 62 | CW69: 38 | CX69: 29 | CY69: 0 | CZ69: 279 | DB69: 1423404 | DC69: J MHC CINTURA F | DD69: Ventas | DF69: 28 | DG69: 57 | DH69: 59 | DI69: 56 | DJ69: 34 | DK69: 27 | DL69: 0 | DM69: 261 | DO69: 1423404 | DP69: J MHC CINTURA F | DQ69: Ventas | DS69: 23 | DT69: 50 | DU69: 52 | DV69: 51 | DW69: 31 | DX69: 27 | DY69: 0 | DZ69: 234 | EB69: 1423408 | EC69: J MHC CINTURA F | ED69: Ventas | EF69: 33 | EG69: 55 | EH69: 57 | EI69: 54 | EJ69: 33 | EK69: 20 | EL69: 0 | EM69: 252 | EO69: 1423409 | EP69: J MHC CINTURA F | EQ69: Ventas | ES69: 2 | ET69: 5 | EU69: 5 | EV69: 5 | EW69: 4 | EX69: 2 | EY69: 0 | EZ69: 23 | FB69: 1423448 | FC69: J MHC CINTURA F | FD69: Ventas | FF69: 6 | FG69: 9 | FH69: 5 | FI69: 6 | FJ69: 4 | FK69: 2 | FL69: 0 | FM69: 32 | FO69: 1423500 | FP69: J MHC CINTURA P | FQ69: Ventas | FS69: 41 | FT69: 71 | FU69: 69 | FV69: 68 | FW69: 50 | FX69: 39 | FY69: 0 | FZ69: 338 | GB69: 1423500 | GC69: J MHC CINTURA P | GD69: Ventas | GF69: 28 | GG69: 39 | GH69: 37 | GI69: 36 | GJ69: 28 | GK69: 19 | GL69: 0 | GM69: 187 | GO69: 1423500 | GP69: J MHC CINTURA P | GQ69: Ventas | GS69: 26 | GT69: 37 | GU69: 34 | GV69: 33 | GW69: 26 | GX69: 17 | GY69: 0 | GZ69: =SUM(GS69:GY69) -> 173
A70: 1423408 | B70: Lavinia | C70: 43 | D70: 70 | E70: 72 | F70: 67 | G70: 41 | H70: 23 | J70: =SUM(C70:H70) -> 316 | K70: ='CORTE 4200'!$O$610 -> -103 | O70: 1423408 | P70: J MHC CINTURA F | Q70: Ventas | S70: 43 | T70: 70 | U70: 72 | V70: 67 | W70: 41 | X70: 23 | Y70: 0 | Z70: =SUM(S70:Y70) -> 316 | AB70: 1423408 | AC70: J MHC CINTURA F | AD70: Ventas | AF70: 45 | AG70: 74 | AH70: 76 | AI70: 69 | AJ70: 42 | AK70: 23 | AL70: 0 | AM70: =SUM(AF70:AL70) -> 329 | AO70: 1423408 | AP70: J MHC CINTURA F | AQ70: Ventas | AS70: 45 | AT70: 74 | AU70: 76 | AV70: 69 | AW70: 42 | AX70: 23 | AY70: 0 | AZ70: =SUM(AS70:AY70) -> 329 | BB70: 1423408 | BC70: J MHC CINTURA F | BD70: Ventas | BF70: 45 | BG70: 74 | BH70: 76 | BI70: 69 | BJ70: 42 | BK70: 23 | BL70: 0 | BM70: =SUM(BF70:BL70) -> 329 | BO70: 1423408 | BP70: J MHC CINTURA F | BQ70: Ventas | BS70: 45 | BT70: 74 | BU70: 76 | BV70: 69 | BW70: 42 | BX70: 23 | BY70: 0 | BZ70: =SUM(BS70:BY70) -> 329 | CB70: 1423408 | CC70: J MHC CINTURA F | CD70: Ventas | CF70: 45 | CG70: 74 | CH70: 76 | CI70: 69 | CJ70: 42 | CK70: 23 | CL70: 0 | CM70: =SUM(CF70:CL70) -> 329 | CO70: 1423408 | CP70: J MHC CINTURA F | CQ70: Ventas | CS70: 45 | CT70: 74 | CU70: 76 | CV70: 69 | CW70: 42 | CX70: 23 | CY70: 0 | CZ70: 329 | DB70: 1423408 | DC70: J MHC CINTURA F | DD70: Ventas | DF70: 42 | DG70: 68 | DH70: 70 | DI70: 63 | DJ70: 38 | DK70: 20 | DL70: 0 | DM70: 301 | DO70: 1423408 | DP70: J MHC CINTURA F | DQ70: Ventas | DS70: 37 | DT70: 61 | DU70: 63 | DV70: 58 | DW70: 35 | DX70: 20 | DY70: 0 | DZ70: 274 | EB70: 1423409 | EC70: J MHC CINTURA F | ED70: Ventas | EF70: 4 | EG70: 8 | EH70: 8 | EI70: 8 | EJ70: 6 | EK70: 3 | EL70: 0 | EM70: 37 | EO70: 1423416 | EP70: J MHC CINTURA F | EQ70: Ventas | ES70: 9 | ET70: 15 | EU70: 15 | EV70: 14 | EW70: 10 | EX70: 5 | EY70: 0 | EZ70: 68 | FB70: 1423500 | FC70: J MHC CINTURA P | FD70: Ventas | FF70: 43 | FG70: 77 | FH70: 75 | FI70: 74 | FJ70: 54 | FK70: 43 | FL70: 0 | FM70: 366 | FO70: 1423501 | FP70: J MHC CINTURA P | FQ70: Ventas | FS70: 22 | FT70: 33 | FU70: 38 | FV70: 37 | FW70: 29 | FX70: 22 | FY70: 0 | FZ70: 181 | GB70: 1423501 | GC70: J MHC CINTURA P | GD70: Ventas | GF70: 21 | GG70: 27 | GH70: 32 | GI70: 31 | GJ70: 24 | GK70: 18 | GL70: 0 | GM70: 153 | GO70: 1423501 | GP70: J MHC CINTURA P | GQ70: Ventas | GS70: 18 | GT70: 22 | GU70: 25 | GV70: 25 | GW70: 20 | GX70: 15 | GY70: 0 | GZ70: =SUM(GS70:GY70) -> 125
A71: 1423409 | B71: Lavinia | C71: 5 | D71: 11 | E71: 11 | F71: 12 | G71: 8 | H71: 4 | J71: =SUM(C71:H71) -> 51 | K71: ='CORTE 4200'!$O$619 -> -18 | O71: 1423409 | P71: J MHC CINTURA F | Q71: Ventas | S71: 5 | T71: 11 | U71: 11 | V71: 12 | W71: 8 | X71: 4 | Y71: 0 | Z71: =SUM(S71:Y71) -> 51 | AB71: 1423409 | AC71: J MHC CINTURA F | AD71: Ventas | AF71: 5 | AG71: 11 | AH71: 11 | AI71: 12 | AJ71: 8 | AK71: 4 | AL71: 0 | AM71: =SUM(AF71:AL71) -> 51 | AO71: 1423409 | AP71: J MHC CINTURA F | AQ71: Ventas | AS71: 5 | AT71: 11 | AU71: 11 | AV71: 12 | AW71: 8 | AX71: 4 | AY71: 0 | AZ71: =SUM(AS71:AY71) -> 51 | BB71: 1423409 | BC71: J MHC CINTURA F | BD71: Ventas | BF71: 5 | BG71: 11 | BH71: 11 | BI71: 12 | BJ71: 8 | BK71: 4 | BL71: 0 | BM71: =SUM(BF71:BL71) -> 51 | BO71: 1423409 | BP71: J MHC CINTURA F | BQ71: Ventas | BS71: 5 | BT71: 11 | BU71: 11 | BV71: 12 | BW71: 8 | BX71: 4 | BY71: 0 | BZ71: =SUM(BS71:BY71) -> 51 | CB71: 1423409 | CC71: J MHC CINTURA F | CD71: Ventas | CF71: 5 | CG71: 11 | CH71: 11 | CI71: 12 | CJ71: 8 | CK71: 4 | CL71: 0 | CM71: =SUM(CF71:CL71) -> 51 | CO71: 1423409 | CP71: J MHC CINTURA F | CQ71: Ventas | CS71: 5 | CT71: 11 | CU71: 11 | CV71: 12 | CW71: 8 | CX71: 4 | CY71: 0 | CZ71: 51 | DB71: 1423409 | DC71: J MHC CINTURA F | DD71: Ventas | DF71: 4 | DG71: 8 | DH71: 8 | DI71: 8 | DJ71: 6 | DK71: 3 | DL71: 0 | DM71: 37 | DO71: 1423409 | DP71: J MHC CINTURA F | DQ71: Ventas | DS71: 4 | DT71: 8 | DU71: 8 | DV71: 8 | DW71: 6 | DX71: 3 | DY71: 0 | DZ71: 37 | EB71: 1423416 | EC71: J MHC CINTURA F | ED71: Ventas | EF71: 12 | EG71: 19 | EH71: 19 | EI71: 18 | EJ71: 13 | EK71: 6 | EL71: 0 | EM71: 87 | EO71: 1423448 | EP71: J MHC CINTURA F | EQ71: Ventas | ES71: 6 | ET71: 9 | EU71: 5 | EV71: 6 | EW71: 4 | EX71: 2 | EY71: 0 | EZ71: 32 | FB71: 1423501 | FC71: J MHC CINTURA P | FD71: Ventas | FF71: 22 | FG71: 33 | FH71: 38 | FI71: 37 | FJ71: 29 | FK71: 22 | FL71: 0 | FM71: 181 | FO71: 1423600 | FP71: J MHC CINTURA P | FQ71: Ventas | FS71: 16 | FT71: 38 | FU71: 40 | FV71: 38 | FW71: 25 | FX71: 21 | FY71: 0 | FZ71: 178 | GB71: 1423600 | GC71: J MHC CINTURA P | GD71: Ventas | GF71: 4 | GG71: 8 | GH71: 10 | GI71: 8 | GJ71: 5 | GK71: 4 | GL71: 0 | GM71: 39 | GO71: 1423600 | GP71: J MHC CINTURA P | GQ71: Ventas | GS71: 1 | GT71: 3 | GU71: 3 | GV71: 2 | GW71: 1 | GX71: 1 | GY71: 0 | GZ71: =SUM(GS71:GY71) -> 11
A72: 1423416 | B72: Lavinia | C72: 23 | D72: 39 | E72: 43 | F72: 37 | G72: 22 | H72: 9 | J72: =SUM(C72:H72) -> 173 | K72: ='CORTE 4200'!$O$628 -> -16 | O72: 1423416 | P72: J MHC CINTURA F | Q72: Ventas | S72: 23 | T72: 39 | U72: 43 | V72: 37 | W72: 22 | X72: 9 | Y72: 0 | Z72: =SUM(S72:Y72) -> 173 | AB72: 1423416 | AC72: J MHC CINTURA F | AD72: Ventas | AF72: 23 | AG72: 39 | AH72: 43 | AI72: 37 | AJ72: 22 | AK72: 9 | AL72: 0 | AM72: =SUM(AF72:AL72) -> 173 | AO72: 1423416 | AP72: J MHC CINTURA F | AQ72: Ventas | AS72: 23 | AT72: 39 | AU72: 43 | AV72: 37 | AW72: 22 | AX72: 9 | AY72: 0 | AZ72: =SUM(AS72:AY72) -> 173 | BB72: 1423416 | BC72: J MHC CINTURA F | BD72: Ventas | BF72: 22 | BG72: 37 | BH72: 40 | BI72: 35 | BJ72: 21 | BK72: 8 | BL72: 0 | BM72: =SUM(BF72:BL72) -> 163 | BO72: 1423416 | BP72: J MHC CINTURA F | BQ72: Ventas | BS72: 22 | BT72: 37 | BU72: 40 | BV72: 35 | BW72: 21 | BX72: 8 | BY72: 0 | BZ72: =SUM(BS72:BY72) -> 163 | CB72: 1423416 | CC72: J MHC CINTURA F | CD72: Ventas | CF72: 21 | CG72: 35 | CH72: 38 | CI72: 33 | CJ72: 20 | CK72: 8 | CL72: 0 | CM72: =SUM(CF72:CL72) -> 155 | CO72: 1423416 | CP72: J MHC CINTURA F | CQ72: Ventas | CS72: 20 | CT72: 32 | CU72: 35 | CV72: 30 | CW72: 18 | CX72: 7 | CY72: 0 | CZ72: 142 | DB72: 1423416 | DC72: J MHC CINTURA F | DD72: Ventas | DF72: 20 | DG72: 32 | DH72: 35 | DI72: 30 | DJ72: 18 | DK72: 7 | DL72: 0 | DM72: 142 | DO72: 1423416 | DP72: J MHC CINTURA F | DQ72: Ventas | DS72: 12 | DT72: 19 | DU72: 19 | DV72: 18 | DW72: 13 | DX72: 6 | DY72: 0 | DZ72: 87 | EB72: 1423448 | EC72: J MHC CINTURA F | ED72: Ventas | EF72: 9 | EG72: 13 | EH72: 9 | EI72: 10 | EJ72: 7 | EK72: 3 | EL72: 0 | EM72: 51 | EO72: 1423500 | EP72: J MHC CINTURA P | EQ72: Ventas | ES72: 51 | ET72: 91 | EU72: 89 | EV72: 87 | EW72: 62 | EX72: 48 | EY72: 0 | EZ72: 428 | FB72: 1423600 | FC72: J MHC CINTURA P | FD72: Ventas | FF72: 18 | FG72: 44 | FH72: 46 | FI72: 44 | FJ72: 29 | FK72: 25 | FL72: 0 | FM72: 206 | FO72: 1423800 | FP72: J MHC CINTURA P | FQ72: Ventas | FS72: 7 | FT72: 16 | FU72: 16 | FV72: 16 | FW72: 11 | FX72: 9 | FY72: 0 | FZ72: 75 | GB72: 1423800 | GC72: J MHC CINTURA P | GD72: Ventas | GF72: 3 | GG72: 4 | GH72: 4 | GI72: 4 | GJ72: 3 | GK72: 1 | GL72: 0 | GM72: 19 | GO72: 1423800 | GP72: J MHC CINTURA P | GQ72: Ventas | GS72: 1 | GT72: 2 | GU72: 2 | GV72: 2 | GW72: 1 | GX72: 1 | GY72: 0 | GZ72: =SUM(GS72:GY72) -> 9
A73: 1423448 | B73: Lavinia | C73: 10 | D73: 17 | E73: 17 | F73: 17 | G73: 11 | H73: 4 | J73: =SUM(C73:H73) -> 76 | K73: ='CORTE 4200'!$O$637 -> -62 | O73: 1423448 | P73: J MHC CINTURA F | Q73: Ventas | S73: 10 | T73: 17 | U73: 17 | V73: 17 | W73: 11 | X73: 4 | Y73: 0 | Z73: =SUM(S73:Y73) -> 76 | AB73: 1423448 | AC73: J MHC CINTURA F | AD73: Ventas | AF73: 12 | AG73: 21 | AH73: 21 | AI73: 19 | AJ73: 12 | AK73: 4 | AL73: 0 | AM73: =SUM(AF73:AL73) -> 89 | AO73: 1423448 | AP73: J MHC CINTURA F | AQ73: Ventas | AS73: 12 | AT73: 21 | AU73: 21 | AV73: 19 | AW73: 12 | AX73: 4 | AY73: 0 | AZ73: =SUM(AS73:AY73) -> 89 | BB73: 1423448 | BC73: J MHC CINTURA F | BD73: Ventas | BF73: 12 | BG73: 21 | BH73: 21 | BI73: 19 | BJ73: 12 | BK73: 4 | BL73: 0 | BM73: =SUM(BF73:BL73) -> 89 | BO73: 1423448 | BP73: J MHC CINTURA F | BQ73: Ventas | BS73: 15 | BT73: 25 | BU73: 21 | BV73: 21 | BW73: 14 | BX73: 5 | BY73: 0 | BZ73: =SUM(BS73:BY73) -> 101 | CB73: 1423448 | CC73: J MHC CINTURA F | CD73: Ventas | CF73: 15 | CG73: 25 | CH73: 21 | CI73: 21 | CJ73: 14 | CK73: 5 | CL73: 0 | CM73: =SUM(CF73:CL73) -> 101 | CO73: 1423448 | CP73: J MHC CINTURA F | CQ73: Ventas | CS73: 15 | CT73: 25 | CU73: 21 | CV73: 21 | CW73: 14 | CX73: 5 | CY73: 0 | CZ73: 101 | DB73: 1423448 | DC73: J MHC CINTURA F | DD73: Ventas | DF73: 14 | DG73: 21 | DH73: 17 | DI73: 15 | DJ73: 10 | DK73: 3 | DL73: 0 | DM73: 80 | DO73: 1423448 | DP73: J MHC CINTURA F | DQ73: Ventas | DS73: 11 | DT73: 17 | DU73: 13 | DV73: 12 | DW73: 8 | DX73: 3 | DY73: 0 | DZ73: 64 | EB73: 1423500 | EC73: J MHC CINTURA P | ED73: Ventas | EF73: 52 | EG73: 93 | EH73: 91 | EI73: 89 | EJ73: 63 | EK73: 49 | EL73: 0 | EM73: 437 | EO73: 1423501 | EP73: J MHC CINTURA P | EQ73: Ventas | ES73: 24 | ET73: 38 | EU73: 43 | EV73: 42 | EW73: 32 | EX73: 24 | EY73: 0 | EZ73: 203 | FB73: 1423800 | FC73: J MHC CINTURA P | FD73: Ventas | FF73: 7 | FG73: 16 | FH73: 16 | FI73: 16 | FJ73: 11 | FK73: 9 | FL73: 0 | FM73: 75 | FO73: 1423900 | FP73: J MHC CINTURA F | FQ73: Ventas | FS73: 38 | FT73: 83 | FU73: 83 | FV73: 78 | FW73: 52 | FX73: 46 | FY73: 0 | FZ73: 380 | GB73: 1423900 | GC73: J MHC CINTURA F | GD73: Ventas | GF73: 12 | GG73: 16 | GH73: 13 | GI73: 12 | GJ73: 8 | GK73: 6 | GL73: 0 | GM73: 67 | GO73: 1423900 | GP73: J MHC CINTURA F | GQ73: Ventas | GS73: 10 | GT73: 14 | GU73: 10 | GV73: 9 | GW73: 6 | GX73: 4 | GY73: 0 | GZ73: =SUM(GS73:GY73) -> 53
A74: 1423500 | B74: Ibiza Blue | C74: 68 | D74: 123 | E74: 126 | F74: 121 | G74: 80 | H74: 57 | J74: =SUM(C74:H74) -> 575 | K74: ='CORTE 4200'!$O$646 -> -268 | L74: 50 | O74: 1423500 | P74: J MHC CINTURA P | Q74: Ventas | S74: 68 | T74: 123 | U74: 126 | V74: 121 | W74: 80 | X74: 57 | Y74: 0 | Z74: =SUM(S74:Y74) -> 575 | AB74: 1423500 | AC74: J MHC CINTURA P | AD74: Ventas | AF74: 71 | AG74: 129 | AH74: 131 | AI74: 124 | AJ74: 81 | AK74: 57 | AL74: 0 | AM74: =SUM(AF74:AL74) -> 593 | AO74: 1423500 | AP74: J MHC CINTURA P | AQ74: Ventas | AS74: 71 | AT74: 129 | AU74: 131 | AV74: 124 | AW74: 81 | AX74: 57 | AY74: 0 | AZ74: =SUM(AS74:AY74) -> 593 | BB74: 1423500 | BC74: J MHC CINTURA P | BD74: Ventas | BF74: 63 | BG74: 117 | BH74: 119 | BI74: 112 | BJ74: 78 | BK74: 54 | BL74: 0 | BM74: =SUM(BF74:BL74) -> 543 | BO74: 1423500 | BP74: J MHC CINTURA P | BQ74: Ventas | BS74: 63 | BT74: 117 | BU74: 117 | BV74: 112 | BW74: 79 | BX74: 55 | BY74: 0 | BZ74: =SUM(BS74:BY74) -> 543 | CB74: 1423500 | CC74: J MHC CINTURA P | CD74: Ventas | CF74: 63 | CG74: 117 | CH74: 117 | CI74: 112 | CJ74: 79 | CK74: 55 | CL74: 0 | CM74: =SUM(CF74:CL74) -> 543 | CO74: 1423500 | CP74: J MHC CINTURA P | CQ74: Ventas | CS74: 63 | CT74: 116 | CU74: 116 | CV74: 111 | CW74: 78 | CX74: 55 | CY74: 0 | CZ74: 539 | DB74: 1423500 | DC74: J MHC CINTURA P | DD74: Ventas | DF74: 60 | DG74: 111 | DH74: 111 | DI74: 106 | DJ74: 74 | DK74: 55 | DL74: 0 | DM74: 517 | DO74: 1423500 | DP74: J MHC CINTURA P | DQ74: Ventas | DS74: 58 | DT74: 105 | DU74: 101 | DV74: 97 | DW74: 68 | DX74: 52 | DY74: 0 | DZ74: 481 | EB74: 1423501 | EC74: J MHC CINTURA P | ED74: Ventas | EF74: 24 | EG74: 38 | EH74: 43 | EI74: 42 | EJ74: 32 | EK74: 24 | EL74: 0 | EM74: 203 | EO74: 1423600 | EP74: J MHC CINTURA P | EQ74: Ventas | ES74: 22 | ET74: 49 | EU74: 51 | EV74: 48 | EW74: 33 | EX74: 28 | EY74: 0 | EZ74: 231 | FB74: 1423900 | FC74: J MHC CINTURA F | FD74: Ventas | FF74: 40 | FG74: 89 | FH74: 89 | FI74: 84 | FJ74: 56 | FK74: 50 | FL74: 0 | FM74: 408 | FO74: 1424000 | FP74: J MHC CINTURA P | FQ74: Ventas | FS74: 33 | FT74: 80 | FU74: 81 | FV74: 80 | FW74: 55 | FX74: 54 | FY74: 0 | FZ74: 383 | GB74: 1424000 | GC74: J MHC CINTURA P | GD74: Ventas | GF74: 6 | GG74: 8 | GH74: 9 | GI74: 8 | GJ74: 6 | GK74: 6 | GL74: 0 | GM74: 43 | GO74: 1424000 | GP74: J MHC CINTURA P | GQ74: Ventas | GS74: 4 | GT74: 6 | GU74: 6 | GV74: 5 | GW74: 4 | GX74: 4 | GY74: 0 | GZ74: =SUM(GS74:GY74) -> 29
A75: 1423501 | B75: Ibiza Blue | C75: 27 | D75: 46 | E75: 51 | F75: 49 | G75: 37 | H75: 27 | J75: =SUM(C75:H75) -> 237 | K75: ='CORTE 4200'!$O$655 -> -22 | O75: 1423501 | P75: J MHC CINTURA P | Q75: Ventas | S75: 27 | T75: 46 | U75: 51 | V75: 49 | W75: 37 | X75: 27 | Y75: 0 | Z75: =SUM(S75:Y75) -> 237 | AB75: 1423501 | AC75: J MHC CINTURA P | AD75: Ventas | AF75: 27 | AG75: 44 | AH75: 49 | AI75: 48 | AJ75: 36 | AK75: 26 | AL75: 0 | AM75: =SUM(AF75:AL75) -> 230 | AO75: 1423501 | AP75: J MHC CINTURA P | AQ75: Ventas | AS75: 27 | AT75: 44 | AU75: 49 | AV75: 48 | AW75: 36 | AX75: 26 | AY75: 0 | AZ75: =SUM(AS75:AY75) -> 230 | BB75: 1423501 | BC75: J MHC CINTURA P | BD75: Ventas | BF75: 27 | BG75: 44 | BH75: 49 | BI75: 48 | BJ75: 36 | BK75: 26 | BL75: 0 | BM75: =SUM(BF75:BL75) -> 230 | BO75: 1423501 | BP75: J MHC CINTURA P | BQ75: Ventas | BS75: 27 | BT75: 44 | BU75: 49 | BV75: 48 | BW75: 36 | BX75: 26 | BY75: 0 | BZ75: =SUM(BS75:BY75) -> 230 | CB75: 1423501 | CC75: J MHC CINTURA P | CD75: Ventas | CF75: 27 | CG75: 44 | CH75: 49 | CI75: 48 | CJ75: 36 | CK75: 26 | CL75: 0 | CM75: =SUM(CF75:CL75) -> 230 | CO75: 1423501 | CP75: J MHC CINTURA P | CQ75: Ventas | CS75: 26 | CT75: 41 | CU75: 46 | CV75: 45 | CW75: 34 | CX75: 25 | CY75: 0 | CZ75: 217 | DB75: 1423501 | DC75: J MHC CINTURA P | DD75: Ventas | DF75: 26 | DG75: 41 | DH75: 46 | DI75: 45 | DJ75: 34 | DK75: 25 | DL75: 0 | DM75: 217 | DO75: 1423501 | DP75: J MHC CINTURA P | DQ75: Ventas | DS75: 26 | DT75: 41 | DU75: 46 | DV75: 45 | DW75: 34 | DX75: 25 | DY75: 0 | DZ75: 217 | EB75: 1423600 | EC75: J MHC CINTURA P | ED75: Ventas | EF75: 22 | EG75: 49 | EH75: 51 | EI75: 48 | EJ75: 33 | EK75: 28 | EL75: 0 | EM75: 231 | EO75: 1423800 | EP75: J MHC CINTURA P | EQ75: Ventas | ES75: 7 | ET75: 18 | EU75: 18 | EV75: 17 | EW75: 11 | EX75: 9 | EY75: 0 | EZ75: 80 | FB75: 1424000 | FC75: J MHC CINTURA P | FD75: Ventas | FF75: 35 | FG75: 86 | FH75: 87 | FI75: 86 | FJ75: 59 | FK75: 58 | FL75: 0 | FM75: 411 | FO75: 1424200 | FP75: J MHC CINTURA P | FQ75: Ventas | FS75: 5 | FT75: 14 | FU75: 18 | FV75: 16 | FW75: 13 | FX75: 7 | FY75: 0 | FZ75: 73 | GB75: 1424200 | GC75: J MHC CINTURA P | GD75: Ventas | GF75: 5 | GG75: 11 | GH75: 15 | GI75: 14 | GJ75: 11 | GK75: 6 | GL75: 0 | GM75: 62 | GO75: 1424200 | GP75: J MHC CINTURA P | GQ75: Ventas | GS75: 3 | GT75: 9 | GU75: 13 | GV75: 12 | GW75: 9 | GX75: 6 | GY75: 0 | GZ75: =SUM(GS75:GY75) -> 52
A76: 1423600 | B76: Missy Plus | C76: 39 | D76: 79 | E76: 82 | F76: 74 | G76: 51 | H76: 36 | J76: =SUM(C76:H76) -> 361 | K76: ='CORTE 4200'!$O$664 -> -137 | O76: 1423600 | P76: J MHC CINTURA P | Q76: Ventas | S76: 39 | T76: 79 | U76: 82 | V76: 74 | W76: 51 | X76: 36 | Y76: 0 | Z76: =SUM(S76:Y76) -> 361 | AB76: 1423600 | AC76: J MHC CINTURA P | AD76: Ventas | AF76: 42 | AG76: 85 | AH76: 87 | AI76: 77 | AJ76: 52 | AK76: 36 | AL76: 0 | AM76: =SUM(AF76:AL76) -> 379 | AO76: 1423600 | AP76: J MHC CINTURA P | AQ76: Ventas | AS76: 40 | AT76: 81 | AU76: 83 | AV76: 73 | AW76: 48 | AX76: 32 | AY76: 0 | AZ76: =SUM(AS76:AY76) -> 357 | BB76: 1423600 | BC76: J MHC CINTURA P | BD76: Ventas | BF76: 40 | BG76: 81 | BH76: 83 | BI76: 73 | BJ76: 48 | BK76: 32 | BL76: 0 | BM76: =SUM(BF76:BL76) -> 357 | BO76: 1423600 | BP76: J MHC CINTURA P | BQ76: Ventas | BS76: 40 | BT76: 81 | BU76: 83 | BV76: 73 | BW76: 48 | BX76: 32 | BY76: 0 | BZ76: =SUM(BS76:BY76) -> 357 | CB76: 1423600 | CC76: J MHC CINTURA P | CD76: Ventas | CF76: 40 | CG76: 81 | CH76: 83 | CI76: 73 | CJ76: 48 | CK76: 32 | CL76: 0 | CM76: =SUM(CF76:CL76) -> 357 | CO76: 1423600 | CP76: J MHC CINTURA P | CQ76: Ventas | CS76: 39 | CT76: 78 | CU76: 79 | CV76: 70 | CW76: 45 | CX76: 32 | CY76: 0 | CZ76: 343 | DB76: 1423600 | DC76: J MHC CINTURA P | DD76: Ventas | DF76: 33 | DG76: 67 | DH76: 68 | DI76: 59 | DJ76: 37 | DK76: 28 | DL76: 0 | DM76: 292 | DO76: 1423600 | DP76: J MHC CINTURA P | DQ76: Ventas | DS76: 25 | DT76: 55 | DU76: 56 | DV76: 51 | DW76: 34 | DX76: 28 | DY76: 0 | DZ76: 249 | EB76: 1423800 | EC76: J MHC CINTURA P | ED76: Ventas | EF76: 9 | EG76: 21 | EH76: 21 | EI76: 20 | EJ76: 13 | EK76: 10 | EL76: 0 | EM76: 94 | EO76: 1423900 | EP76: J MHC CINTURA F | EQ76: Ventas | ES76: 44 | ET76: 96 | EU76: 96 | EV76: 91 | EW76: 62 | EX76: 54 | EY76: 0 | EZ76: 443 | FB76: 1424200 | FC76: J MHC CINTURA P | FD76: Ventas | FF76: 5 | FG76: 14 | FH76: 18 | FI76: 16 | FJ76: 13 | FK76: 7 | FL76: 0 | FM76: 73 | FO76: 1424300 | FP76: J MHC CINTURA P | FQ76: Ventas | FS76: 26 | FT76: 47 | FU76: 51 | FV76: 51 | FW76: 38 | FX76: 31 | FY76: 0 | FZ76: 244 | GB76: 1424300 | GC76: J MHC CINTURA P | GD76: Ventas | GF76: 16 | GG76: 20 | GH76: 23 | GI76: 23 | GJ76: 18 | GK76: 13 | GL76: 0 | GM76: 113 | GO76: 1424300 | GP76: J MHC CINTURA P | GQ76: Ventas | GS76: 16 | GT76: 20 | GU76: 23 | GV76: 23 | GW76: 18 | GX76: 13 | GY76: 0 | GZ76: =SUM(GS76:GY76) -> 113
A77: 1423800 | B77: X206-B1 | C77: 13 | D77: 32 | E77: 36 | F77: 30 | G77: 21 | H77: 16 | J77: =SUM(C77:H77) -> 148 | K77: ='CORTE 4200'!$O$673 -> -10 | M77: Girar | O77: 1423800 | P77: J MHC CINTURA P | Q77: Ventas | S77: 13 | T77: 32 | U77: 36 | V77: 30 | W77: 21 | X77: 16 | Y77: 0 | Z77: =SUM(S77:Y77) -> 148 | AB77: 1423800 | AC77: J MHC CINTURA P | AD77: Ventas | AF77: 13 | AG77: 31 | AH77: 35 | AI77: 30 | AJ77: 21 | AK77: 16 | AL77: 0 | AM77: =SUM(AF77:AL77) -> 146 | AO77: 1423800 | AP77: J MHC CINTURA P | AQ77: Ventas | AS77: 13 | AT77: 29 | AU77: 33 | AV77: 28 | AW77: 19 | AX77: 14 | AY77: 0 | AZ77: =SUM(AS77:AY77) -> 136 | BB77: 1423800 | BC77: J MHC CINTURA P | BD77: Ventas | BF77: 13 | BG77: 29 | BH77: 33 | BI77: 28 | BJ77: 19 | BK77: 14 | BL77: 0 | BM77: =SUM(BF77:BL77) -> 136 | BO77: 1423800 | BP77: J MHC CINTURA P | BQ77: Ventas | BS77: 13 | BT77: 29 | BU77: 33 | BV77: 28 | BW77: 19 | BX77: 14 | BY77: 0 | BZ77: =SUM(BS77:BY77) -> 136 | CB77: 1423800 | CC77: J MHC CINTURA P | CD77: Ventas | CF77: 13 | CG77: 29 | CH77: 33 | CI77: 28 | CJ77: 19 | CK77: 14 | CL77: 0 | CM77: =SUM(CF77:CL77) -> 136 | CO77: 1423800 | CP77: J MHC CINTURA P | CQ77: Ventas | CS77: 13 | CT77: 29 | CU77: 33 | CV77: 28 | CW77: 19 | CX77: 14 | CY77: 0 | CZ77: 136 | DB77: 1423800 | DC77: J MHC CINTURA P | DD77: Ventas | DF77: 13 | DG77: 29 | DH77: 33 | DI77: 28 | DJ77: 19 | DK77: 14 | DL77: 0 | DM77: 136 | DO77: 1423800 | DP77: J MHC CINTURA P | DQ77: Ventas | DS77: 9 | DT77: 21 | DU77: 21 | DV77: 20 | DW77: 13 | DX77: 10 | DY77: 0 | DZ77: 94 | EB77: 1423900 | EC77: J MHC CINTURA F | ED77: Ventas | EF77: 44 | EG77: 96 | EH77: 96 | EI77: 91 | EJ77: 62 | EK77: 54 | EL77: 0 | EM77: 443 | EO77: 1424000 | EP77: J MHC CINTURA P | EQ77: Ventas | ES77: 39 | ET77: 92 | EU77: 93 | EV77: 92 | EW77: 61 | EX77: 60 | EY77: 0 | EZ77: 437 | FB77: 1424300 | FC77: J MHC CINTURA P | FD77: Ventas | FF77: 26 | FG77: 47 | FH77: 51 | FI77: 51 | FJ77: 38 | FK77: 31 | FL77: 0 | FM77: 244 | FO77: 1424400 | FP77: J MHC CINTURA P | FQ77: Ventas | FS77: 6 | FT77: 8 | FU77: 9 | FV77: 9 | FW77: 8 | FX77: 6 | FY77: 0 | FZ77: 46 | GB77: 1424400 | GC77: J MHC CINTURA P | GD77: Ventas | GF77: 6 | GG77: 8 | GH77: 9 | GI77: 9 | GJ77: 8 | GK77: 6 | GL77: 0 | GM77: 46 | GO77: 1424400 | GP77: J MHC CINTURA P | GQ77: Ventas | GS77: 4 | GT77: 6 | GU77: 6 | GV77: 6 | GW77: 6 | GX77: 4 | GY77: 0 | GZ77: =SUM(GS77:GY77) -> 32
A78: 1423900 | B78: B2868-V3 | C78: 55 | D78: 115 | E78: 117 | F78: 113 | G78: 74 | H78: 63 | J78: =SUM(C78:H78) -> 537 | K78: ='CORTE 4200'!$O$682 -> -107 | L78: 50 | O78: 1423900 | P78: J MHC CINTURA F | Q78: Ventas | S78: 55 | T78: 115 | U78: 117 | V78: 113 | W78: 74 | X78: 63 | Y78: 0 | Z78: =SUM(S78:Y78) -> 537 | AB78: 1423900 | AC78: J MHC CINTURA F | AD78: Ventas | AF78: 57 | AG78: 120 | AH78: 122 | AI78: 116 | AJ78: 76 | AK78: 64 | AL78: 0 | AM78: =SUM(AF78:AL78) -> 555 | AO78: 1423900 | AP78: J MHC CINTURA F | AQ78: Ventas | AS78: 57 | AT78: 120 | AU78: 122 | AV78: 116 | AW78: 76 | AX78: 64 | AY78: 0 | AZ78: =SUM(AS78:AY78) -> 555 | BB78: 1423900 | BC78: J MHC CINTURA F | BD78: Ventas | BF78: 49 | BG78: 108 | BH78: 110 | BI78: 104 | BJ78: 73 | BK78: 61 | BL78: 0 | BM78: =SUM(BF78:BL78) -> 505 | BO78: 1423900 | BP78: J MHC CINTURA F | BQ78: Ventas | BS78: 49 | BT78: 108 | BU78: 110 | BV78: 104 | BW78: 73 | BX78: 61 | BY78: 0 | BZ78: =SUM(BS78:BY78) -> 505 | CB78: 1423900 | CC78: J MHC CINTURA F | CD78: Ventas | CF78: 49 | CG78: 108 | CH78: 110 | CI78: 104 | CJ78: 73 | CK78: 61 | CL78: 0 | CM78: =SUM(CF78:CL78) -> 505 | CO78: 1423900 | CP78: J MHC CINTURA F | CQ78: Ventas | CS78: 49 | CT78: 106 | CU78: 108 | CV78: 101 | CW78: 70 | CX78: 59 | CY78: 0 | CZ78: 493 | DB78: 1423900 | DC78: J MHC CINTURA F | DD78: Ventas | DF78: 48 | DG78: 105 | DH78: 106 | DI78: 99 | DJ78: 68 | DK78: 58 | DL78: 0 | DM78: 484 | DO78: 1423900 | DP78: J MHC CINTURA F | DQ78: Ventas | DS78: 48 | DT78: 103 | DU78: 103 | DV78: 96 | DW78: 65 | DX78: 56 | DY78: 0 | DZ78: 471 | EB78: 1424000 | EC78: J MHC CINTURA P | ED78: Ventas | EF78: 43 | EG78: 96 | EH78: 97 | EI78: 95 | EJ78: 63 | EK78: 62 | EL78: 0 | EM78: 456 | EO78: 1424200 | EP78: J MHC CINTURA P | EQ78: Ventas | ES78: 8 | ET78: 18 | EU78: 23 | EV78: 19 | EW78: 15 | EX78: 9 | EY78: 0 | EZ78: 92 | FB78: 1424400 | FC78: J MHC CINTURA P | FD78: Ventas | FF78: 6 | FG78: 8 | FH78: 9 | FI78: 9 | FJ78: 8 | FK78: 6 | FL78: 0 | FM78: 46 | FO78: 1424500 | FP78: J MHC CINTURA P | FQ78: Ventas | FS78: 8 | FT78: 19 | FU78: 17 | FV78: 17 | FW78: 11 | FX78: 10 | FY78: 0 | FZ78: 82 | GB78: 1424500 | GC78: J MHC CINTURA P | GD78: Ventas | GF78: 3 | GG78: 4 | GH78: 2 | GI78: 2 | GJ78: 1 | GK78: 0 | GL78: 0 | GM78: 12 | GO78: 1424500 | GP78: J MHC CINTURA P | GQ78: Ventas | GS78: 3 | GT78: 4 | GU78: 2 | GV78: 2 | GW78: 1 | GX78: 0 | GY78: 0 | GZ78: =SUM(GS78:GY78) -> 12
